Workbook

Sheet Semaine 21-09-2025
B1: ="Semaine du :" -> Semaine du : | C1: 44459 | D1: ="( "&AVERAGE($E$2:$I$2)&" )" -> ( 8 ) | E1: =IFERROR("Lun.: " & TEXT($Y$2,"00%"),"Lun.: 0%") -> Lun.: 50% | F1: =IFERROR("Mar.: " & TEXT($Z$2,"00%"),"Mar.: 0%") -> Mar.: 19% | G1: =IFERROR("Mer.: " & TEXT($AA$2,"00%"),"Mer.: 0%") -> Mer.: 34% | H1: =IFERROR("Jeu.: " & TEXT($AB$2,"00%"),"Jeu.: 0%") -> Jeu.: 80% | I1: =IFERROR("Ven.: " & TEXT($AC$2,"00%"),"Ven.: 0%") -> Ven.: 36% | J1: =IFERROR("S.: " & TEXT($AD$2,"00%"),"S.: 0%") -> S.: 00% | K1: =IFERROR("D.: " & TEXT($AE$2,"00%"), "D.: 0%") -> D.: 00% | M1: =M2/Total -> 0.46753247 | N1: =N2/$C$2 -> 0 | O1: =O2/$C$2 -> 0.1625 | P1: =P2/$C$2 -> 0.1125 | Q1: =Q2/$C$2 -> 0.2375 | R1: =R2/$C$2 -> 0 | S1: =S2/$C$2 -> 0 | T1: =T2/$C$2 -> 0.03125 | U1: =U2/$C$2 -> 0 | X1: =SUM(#REF!) -> #REF! | Y1: Lundi | Z1: Mardi | AA1: Mercredi | AB1: Jeudi | AC1: Vendredi | AD1: Samedi | AE1: Dimanche
B2: =X2 -> 0.47096774 | C2: =SUM(Horo82[Durée]) -> 40 | D2: =ROUND(SUM(Horo82[T]),2) & " / " & ROUND($C$2-SUM(Horo82[T]),2) -> 28 / 12 | E2: =SUMIF(Horo82[Jour],"Lundi",Horo82[Durée]) -> 9 | F2: =SUMIF(Horo82[Jour],"Mardi",Horo82[Durée]) -> 8 | G2: =SUMIF(Horo82[Jour],"Mercredi",Horo82[Durée]) -> 7.25 | H2: =SUMIF(Horo82[Jour],"Jeudi",Horo82[Durée]) -> 8.75 | I2: =SUMIF(Horo82[Jour],"Vendredi",Horo82[Durée]) -> 7 | J2: =SUMIF(Horo82[Jour],"Samedi",Horo82[Durée]) -> 0 | K2: =SUMIF(Horo82[Jour],"Dimanche",Horo82[Durée]) -> 0 | M2: =SUM(Horo82[GPF]) -> 18 | N2: =SUM(Horo82[RI]) -> 0 | O2: =SUM(Horo82[GB]) -> 6.5 | P2: =SUM(Horo82[RD]) -> 4.5 | Q2: =SUM(Horo82[FG]) -> 9.5 | R2: =SUM(Horo82[CONGÉ]) -> 0 | S2: =SUM(Horo82[PS]) -> 0 | T2: =SUM(Horo82[TD]) -> 1.25 | U2: =SUM(Horo82[N/C]) -> 0 | V2: =(C2-(SUM(N2:T2))) -> 18.25 | W2: =C2-(R2+S2+T2) -> 38.75 | X2: =V2/W2 -> 0.47096774 | Y2: =SUMIF(Horo82[Jour],"Lundi",Horo82[GPF]) / $E$2 -> 0.5 | Z2: =SUMIF(Horo82[Jour],"Mardi",Horo82[GPF]) / $F$2 -> 0.1875 | AA2: =SUMIF(Horo82[Jour],"Mercredi",Horo82[GPF]) / $G$2 -> 0.34482759 | AB2: =SUMIF(Horo82[Jour],"Jeudi",Horo82[GPF]) / $H$2 -> 0.8 | AC2: =SUMIF(Horo82[Jour],"Vendredi",Horo82[GPF]) / $I$2 -> 0.35714286 | AD2: =IFERROR(SUMIF(Horo82[Jour],"Samedi",Horo82[GPF]) / $J$2,0) -> 0 | AE2: =IFERROR(SUMIF(Horo82[Jour],"Dimanche",Horo82[GPF]) / $K$2,0) -> 0
A3: O | B3: Date | C3: Jour | D3: Début | E3: Fin | F3: Client | G3: Tâche | H3: Description | I3: Description 2 | J3: Durée | K3: hrs | L3: % | M3: GPF | N3: RI | O3: GB | P3: RD | Q3: FG | R3: CONGÉ | S3: PS | T3: TD | U3: N/C | V3: W | W3: T | X3: Durée (60)2
A4: o | B4: =IF(Horo82[[#This Row],[Jour]]="Lundi",$C$1+1, IF(Horo82[[#This Row],[Jour]]="Mardi",$C$1+2, IF(Horo82[[#This Row],[Jour]]="Mercredi",$C$1+3, IF(Horo82[[#This Row],[Jour]]="Jeudi",$C$1+4, IF(Horo82[[#This Row],[Jour]]="Vendredi",$C$1+5, IF(Horo82[[#This Row],[Jour]]="Samedi",$C$1+6, IF(Horo82[[#This Row],[Jour]]="Dimanche",$C$1, ))))))) -> 44460 | C4: Lundi | D4: 0.29166667 | E4: 0.35416667 | F4: FORGESTIK | G4: GB | H4: . | J4: =IF(Horo82[[#This Row],[Début]]=0,"",(Horo82[[#This Row],[Durée (60)2]]-INT(Horo82[[#This Row],[Durée (60)2]]))*24) -> 1.5 | K4: =SUMIF(Horo82[Jour],C4,Horo82[Durée]) -> 9 | L4: =IFERROR(SUMIF(Horo82[[#This Row],[Jour]],Horo82[[#This Row],[Jour]],Horo82[[#This Row],[GPF]]) / Horo82[[#This Row],[hrs]],"") -> 0 | M4: =IF("GPF"=Horo82[[#This Row],[Tâche]],Horo82[[#This Row],[Durée]],"") | N4: =IF("RI"=Horo82[[#This Row],[Tâche]],Horo82[[#This Row],[Durée]],"") | O4: =IF("GB"=Horo82[[#This Row],[Tâche]],Horo82[[#This Row],[Durée]],"") -> 1.5 | P4: =IF("RD"=Horo82[[#This Row],[Tâche]],Horo82[[#This Row],[Durée]],"") | Q4: =IF("FG"=Horo82[[#This Row],[Tâche]],Horo82[[#This Row],[Durée]],"") | R4: =IF("CONGÉ"=Horo82[[#This Row],[Tâche]],Horo82[[#This Row],[Durée]],"") | S4: =IF("PS"=Horo82[[#This Row],[Tâche]],Horo82[[#This Row],[Durée]],"") | T4: =IF("TD"=Horo82[[#This Row],[Tâche]],Horo82[[#This Row],[Durée]],"") | U4: =IF("N/C"=Horo82[[#This Row],[Tâche]],Horo82[[#This Row],[Durée]],"") | W4: =IF(Horo82[[#This Row],[O]]="o",Horo82[[#This Row],[Durée]],".") -> 1.5 | X4: =IF(Horo82[[#This Row],[Début]]=0,"",Horo82[[#This Row],[Fin]]-Horo82[[#This Row],[Début]]) -> 0.0625
A5: . | B5: =IF(Horo82[[#This Row],[Jour]]="Lundi",$C$1+1, IF(Horo82[[#This Row],[Jour]]="Mardi",$C$1+2, IF(Horo82[[#This Row],[Jour]]="Mercredi",$C$1+3, IF(Horo82[[#This Row],[Jour]]="Jeudi",$C$1+4, IF(Horo82[[#This Row],[Jour]]="Vendredi",$C$1+5, IF(Horo82[[#This Row],[Jour]]="Samedi",$C$1+6, IF(Horo82[[#This Row],[Jour]]="Dimanche",$C$1, ))))))) -> 44460 | C5: Lundi | D5: 0.35416667 | E5: 0.375 | F5: HYPERTEC | G5: GPF | H5: Appel avec | I5: Elhane et Francine | J5: =IF(Horo82[[#This Row],[Début]]=0,"",(Horo82[[#This Row],[Durée (60)2]]-INT(Horo82[[#This Row],[Durée (60)2]]))*24) -> 0.5 | K5: =SUMIF(Horo82[Jour],C5,Horo82[Durée]) -> 9 | L5: =IFERROR(SUMIF(Horo82[[#This Row],[Jour]],Horo82[[#This Row],[Jour]],Horo82[[#This Row],[GPF]]) / Horo82[[#This Row],[hrs]],"") -> 0.055555556 | M5: =IF("GPF"=Horo82[[#This Row],[Tâche]],Horo82[[#This Row],[Durée]],"") -> 0.5 | N5: =IF("RI"=Horo82[[#This Row],[Tâche]],Horo82[[#This Row],[Durée]],"") | O5: =IF("GB"=Horo82[[#This Row],[Tâche]],Horo82[[#This Row],[Durée]],"") | P5: =IF("RD"=Horo82[[#This Row],[Tâche]],Horo82[[#This Row],[Durée]],"") | Q5: =IF("FG"=Horo82[[#This Row],[Tâche]],Horo82[[#This Row],[Durée]],"") | R5: =IF("CONGÉ"=Horo82[[#This Row],[Tâche]],Horo82[[#This Row],[Durée]],"") | S5: =IF("PS"=Horo82[[#This Row],[Tâche]],Horo82[[#This Row],[Durée]],"") | T5: =IF("TD"=Horo82[[#This Row],[Tâche]],Horo82[[#This Row],[Durée]],"") | U5: =IF("N/C"=Horo82[[#This Row],[Tâche]],Horo82[[#This Row],[Durée]],"") | W5: =IF(Horo82[[#This Row],[O]]="o",Horo82[[#This Row],[Durée]],".") -> . | X5: =IF(Horo82[[#This Row],[Début]]=0,"",Horo82[[#This Row],[Fin]]-Horo82[[#This Row],[Début]]) -> 0.020833333
A6: o | B6: =IF(Horo82[[#This Row],[Jour]]="Lundi",$C$1+1, IF(Horo82[[#This Row],[Jour]]="Mardi",$C$1+2, IF(Horo82[[#This Row],[Jour]]="Mercredi",$C$1+3, IF(Horo82[[#This Row],[Jour]]="Jeudi",$C$1+4, IF(Horo82[[#This Row],[Jour]]="Vendredi",$C$1+5, IF(Horo82[[#This Row],[Jour]]="Samedi",$C$1+6, IF(Horo82[[#This Row],[Jour]]="Dimanche",$C$1, ))))))) -> 44460 | C6: Lundi | D6: 0.375 | E6: 0.41666667 | F6: FORGESTIK | G6: GB | H6: . | J6: =IF(Horo82[[#This Row],[Début]]=0,"",(Horo82[[#This Row],[Durée (60)2]]-INT(Horo82[[#This Row],[Durée (60)2]]))*24) -> 1 | K6: =SUMIF(Horo82[Jour],C6,Horo82[Durée]) -> 9 | L6: =IFERROR(SUMIF(Horo82[[#This Row],[Jour]],Horo82[[#This Row],[Jour]],Horo82[[#This Row],[GPF]]) / Horo82[[#This Row],[hrs]],"") -> 0 | M6: =IF("GPF"=Horo82[[#This Row],[Tâche]],Horo82[[#This Row],[Durée]],"") | N6: =IF("RI"=Horo82[[#This Row],[Tâche]],Horo82[[#This Row],[Durée]],"") | O6: =IF("GB"=Horo82[[#This Row],[Tâche]],Horo82[[#This Row],[Durée]],"") -> 1 | P6: =IF("RD"=Horo82[[#This Row],[Tâche]],Horo82[[#This Row],[Durée]],"") | Q6: =IF("FG"=Horo82[[#This Row],[Tâche]],Horo82[[#This Row],[Durée]],"") | R6: =IF("CONGÉ"=Horo82[[#This Row],[Tâche]],Horo82[[#This Row],[Durée]],"") | S6: =IF("PS"=Horo82[[#This Row],[Tâche]],Horo82[[#This Row],[Durée]],"") | T6: =IF("TD"=Horo82[[#This Row],[Tâche]],Horo82[[#This Row],[Durée]],"") | U6: =IF("N/C"=Horo82[[#This Row],[Tâche]],Horo82[[#This Row],[Durée]],"") | W6: =IF(Horo82[[#This Row],[O]]="o",Horo82[[#This Row],[Durée]],".") -> 1 | X6: =IF(Horo82[[#This Row],[Début]]=0,"",Horo82[[#This Row],[Fin]]-Horo82[[#This Row],[Début]]) -> 0.041666667
A7: o | B7: =IF(Horo82[[#This Row],[Jour]]="Lundi",$C$1+1, IF(Horo82[[#This Row],[Jour]]="Mardi",$C$1+2, IF(Horo82[[#This Row],[Jour]]="Mercredi",$C$1+3, IF(Horo82[[#This Row],[Jour]]="Jeudi",$C$1+4, IF(Horo82[[#This Row],[Jour]]="Vendredi",$C$1+5, IF(Horo82[[#This Row],[Jour]]="Samedi",$C$1+6, IF(Horo82[[#This Row],[Jour]]="Dimanche",$C$1, ))))))) -> 44460 | C7: Lundi | D7: 0.41666667 | E7: 0.5 | F7: RBF | G7: RD | H7: Étiquette client | I7: Création étiquette shipping avec liste d'articles | J7: =IF(Horo82[[#This Row],[Début]]=0,"",(Horo82[[#This Row],[Durée (60)2]]-INT(Horo82[[#This Row],[Durée (60)2]]))*24) -> 2 | K7: =SUMIF(Horo82[Jour],C7,Horo82[Durée]) -> 9 | L7: =IFERROR(SUMIF(Horo82[[#This Row],[Jour]],Horo82[[#This Row],[Jour]],Horo82[[#This Row],[GPF]]) / Horo82[[#This Row],[hrs]],"") -> 0 | M7: =IF("GPF"=Horo82[[#This Row],[Tâche]],Horo82[[#This Row],[Durée]],"") | N7: =IF("RI"=Horo82[[#This Row],[Tâche]],Horo82[[#This Row],[Durée]],"") | O7: =IF("GB"=Horo82[[#This Row],[Tâche]],Horo82[[#This Row],[Durée]],"") | P7: =IF("RD"=Horo82[[#This Row],[Tâche]],Horo82[[#This Row],[Durée]],"") -> 2 | Q7: =IF("FG"=Horo82[[#This Row],[Tâche]],Horo82[[#This Row],[Durée]],"") | R7: =IF("CONGÉ"=Horo82[[#This Row],[Tâche]],Horo82[[#This Row],[Durée]],"") | S7: =IF("PS"=Horo82[[#This Row],[Tâche]],Horo82[[#This Row],[Durée]],"") | T7: =IF("TD"=Horo82[[#This Row],[Tâche]],Horo82[[#This Row],[Durée]],"") | U7: =IF("N/C"=Horo82[[#This Row],[Tâche]],Horo82[[#This Row],[Durée]],"") | W7: =IF(Horo82[[#This Row],[O]]="o",Horo82[[#This Row],[Durée]],".") -> 2 | X7: =IF(Horo82[[#This Row],[Début]]=0,"",Horo82[[#This Row],[Fin]]-Horo82[[#This Row],[Début]]) -> 0.083333333
A8: o | B8: =IF(Horo82[[#This Row],[Jour]]="Lundi",$C$1+1, IF(Horo82[[#This Row],[Jour]]="Mardi",$C$1+2, IF(Horo82[[#This Row],[Jour]]="Mercredi",$C$1+3, IF(Horo82[[#This Row],[Jour]]="Jeudi",$C$1+4, IF(Horo82[[#This Row],[Jour]]="Vendredi",$C$1+5, IF(Horo82[[#This Row],[Jour]]="Samedi",$C$1+6, IF(Horo82[[#This Row],[Jour]]="Dimanche",$C$1, ))))))) -> 44460 | C8: Lundi | D8: 0.5625 | E8: 0.72916667 | F8: RBF | G8: GPF | H8: Étiquette client | I8: Création étiquette shipping avec liste d'articles | J8: =IF(Horo82[[#This Row],[Début]]=0,"",(Horo82[[#This Row],[Durée (60)2]]-INT(Horo82[[#This Row],[Durée (60)2]]))*24) -> 4 | K8: =SUMIF(Horo82[Jour],C8,Horo82[Durée]) -> 9 | L8: =IFERROR(SUMIF(Horo82[[#This Row],[Jour]],Horo82[[#This Row],[Jour]],Horo82[[#This Row],[GPF]]) / Horo82[[#This Row],[hrs]],"") -> 0.44444444 | M8: =IF("GPF"=Horo82[[#This Row],[Tâche]],Horo82[[#This Row],[Durée]],"") -> 4 | N8: =IF("RI"=Horo82[[#This Row],[Tâche]],Horo82[[#This Row],[Durée]],"") | O8: =IF("GB"=Horo82[[#This Row],[Tâche]],Horo82[[#This Row],[Durée]],"") | P8: =IF("RD"=Horo82[[#This Row],[Tâche]],Horo82[[#This Row],[Durée]],"") | Q8: =IF("FG"=Horo82[[#This Row],[Tâche]],Horo82[[#This Row],[Durée]],"") | R8: =IF("CONGÉ"=Horo82[[#This Row],[Tâche]],Horo82[[#This Row],[Durée]],"") | S8: =IF("PS"=Horo82[[#This Row],[Tâche]],Horo82[[#This Row],[Durée]],"") | T8: =IF("TD"=Horo82[[#This Row],[Tâche]],Horo82[[#This Row],[Durée]],"") | U8: =IF("N/C"=Horo82[[#This Row],[Tâche]],Horo82[[#This Row],[Durée]],"") | W8: =IF(Horo82[[#This Row],[O]]="o",Horo82[[#This Row],[Durée]],".") -> 4 | X8: =IF(Horo82[[#This Row],[Début]]=0,"",Horo82[[#This Row],[Fin]]-Horo82[[#This Row],[Début]]) -> 0.16666667
A9: o | B9: =IF(Horo82[[#This Row],[Jour]]="Lundi",$C$1+1, IF(Horo82[[#This Row],[Jour]]="Mardi",$C$1+2, IF(Horo82[[#This Row],[Jour]]="Mercredi",$C$1+3, IF(Horo82[[#This Row],[Jour]]="Jeudi",$C$1+4, IF(Horo82[[#This Row],[Jour]]="Vendredi",$C$1+5, IF(Horo82[[#This Row],[Jour]]="Samedi",$C$1+6, IF(Horo82[[#This Row],[Jour]]="Dimanche",$C$1, ))))))) -> 44461 | C9: Mardi | D9: 0.33333333 | E9: 0.375 | F9: FORGESTIK | G9: GB | I9: copie BD VM | J9: =IF(Horo82[[#This Row],[Début]]=0,"",(Horo82[[#This Row],[Durée (60)2]]-INT(Horo82[[#This Row],[Durée (60)2]]))*24) -> 1 | K9: =SUMIF(Horo82[Jour],C9,Horo82[Durée]) -> 8 | L9: =IFERROR(SUMIF(Horo82[[#This Row],[Jour]],Horo82[[#This Row],[Jour]],Horo82[[#This Row],[GPF]]) / Horo82[[#This Row],[hrs]],"") -> 0 | M9: =IF("GPF"=Horo82[[#This Row],[Tâche]],Horo82[[#This Row],[Durée]],"") | N9: =IF("RI"=Horo82[[#This Row],[Tâche]],Horo82[[#This Row],[Durée]],"") | O9: =IF("GB"=Horo82[[#This Row],[Tâche]],Horo82[[#This Row],[Durée]],"") -> 1 | P9: =IF("RD"=Horo82[[#This Row],[Tâche]],Horo82[[#This Row],[Durée]],"") | Q9: =IF("FG"=Horo82[[#This Row],[Tâche]],Horo82[[#This Row],[Durée]],"") | R9: =IF("CONGÉ"=Horo82[[#This Row],[Tâche]],Horo82[[#This Row],[Durée]],"") | S9: =IF("PS"=Horo82[[#This Row],[Tâche]],Horo82[[#This Row],[Durée]],"") | T9: =IF("TD"=Horo82[[#This Row],[Tâche]],Horo82[[#This Row],[Durée]],"") | U9: =IF("N/C"=Horo82[[#This Row],[Tâche]],Horo82[[#This Row],[Durée]],"") | W9: =IF(Horo82[[#This Row],[O]]="o",Horo82[[#This Row],[Durée]],".") -> 1 | X9: =IF(Horo82[[#This Row],[Début]]=0,"",Horo82[[#This Row],[Fin]]-Horo82[[#This Row],[Début]]) -> 0.041666667
A10: o | B10: =IF(Horo82[[#This Row],[Jour]]="Lundi",$C$1+1, IF(Horo82[[#This Row],[Jour]]="Mardi",$C$1+2, IF(Horo82[[#This Row],[Jour]]="Mercredi",$C$1+3, IF(Horo82[[#This Row],[Jour]]="Jeudi",$C$1+4, IF(Horo82[[#This Row],[Jour]]="Vendredi",$C$1+5, IF(Horo82[[#This Row],[Jour]]="Samedi",$C$1+6, IF(Horo82[[#This Row],[Jour]]="Dimanche",$C$1, ))))))) -> 44461 | C10: Mardi | D10: 0.375 | E10: 0.39583333 | F10: FORGESTIK | G10: GB | J10: =IF(Horo82[[#This Row],[Début]]=0,"",(Horo82[[#This Row],[Durée (60)2]]-INT(Horo82[[#This Row],[Durée (60)2]]))*24) -> 0.5 | K10: =SUMIF(Horo82[Jour],C10,Horo82[Durée]) -> 8 | L10: =IFERROR(SUMIF(Horo82[[#This Row],[Jour]],Horo82[[#This Row],[Jour]],Horo82[[#This Row],[GPF]]) / Horo82[[#This Row],[hrs]],"") -> 0 | M10: =IF("GPF"=Horo82[[#This Row],[Tâche]],Horo82[[#This Row],[Durée]],"") | N10: =IF("RI"=Horo82[[#This Row],[Tâche]],Horo82[[#This Row],[Durée]],"") | O10: =IF("GB"=Horo82[[#This Row],[Tâche]],Horo82[[#This Row],[Durée]],"") -> 0.5 | P10: =IF("RD"=Horo82[[#This Row],[Tâche]],Horo82[[#This Row],[Durée]],"") | Q10: =IF("FG"=Horo82[[#This Row],[Tâche]],Horo82[[#This Row],[Durée]],"") | R10: =IF("CONGÉ"=Horo82[[#This Row],[Tâche]],Horo82[[#This Row],[Durée]],"") | S10: =IF("PS"=Horo82[[#This Row],[Tâche]],Horo82[[#This Row],[Durée]],"") | T10: =IF("TD"=Horo82[[#This Row],[Tâche]],Horo82[[#This Row],[Durée]],"") | U10: =IF("N/C"=Horo82[[#This Row],[Tâche]],Horo82[[#This Row],[Durée]],"") | W10: =IF(Horo82[[#This Row],[O]]="o",Horo82[[#This Row],[Durée]],".") -> 0.5 | X10: =IF(Horo82[[#This Row],[Début]]=0,"",Horo82[[#This Row],[Fin]]-Horo82[[#This Row],[Début]]) -> 0.020833333
A11: . | B11: =IF(Horo82[[#This Row],[Jour]]="Lundi",$C$1+1, IF(Horo82[[#This Row],[Jour]]="Mardi",$C$1+2, IF(Horo82[[#This Row],[Jour]]="Mercredi",$C$1+3, IF(Horo82[[#This Row],[Jour]]="Jeudi",$C$1+4, IF(Horo82[[#This Row],[Jour]]="Vendredi",$C$1+5, IF(Horo82[[#This Row],[Jour]]="Samedi",$C$1+6, IF(Horo82[[#This Row],[Jour]]="Dimanche",$C$1, ))))))) -> 44461 | C11: Mardi | D11: 0.39583333 | E11: 0.4375 | F11: DUER | G11: FG | H11: Billet | I11: T20250922.0054 | J11: =IF(Horo82[[#This Row],[Début]]=0,"",(Horo82[[#This Row],[Durée (60)2]]-INT(Horo82[[#This Row],[Durée (60)2]]))*24) -> 1 | K11: =SUMIF(Horo82[Jour],C11,Horo82[Durée]) -> 8 | L11: =IFERROR(SUMIF(Horo82[[#This Row],[Jour]],Horo82[[#This Row],[Jour]],Horo82[[#This Row],[GPF]]) / Horo82[[#This Row],[hrs]],"") -> 0 | M11: =IF("GPF"=Horo82[[#This Row],[Tâche]],Horo82[[#This Row],[Durée]],"") | N11: =IF("RI"=Horo82[[#This Row],[Tâche]],Horo82[[#This Row],[Durée]],"") | O11: =IF("GB"=Horo82[[#This Row],[Tâche]],Horo82[[#This Row],[Durée]],"") | P11: =IF("RD"=Horo82[[#This Row],[Tâche]],Horo82[[#This Row],[Durée]],"") | Q11: =IF("FG"=Horo82[[#This Row],[Tâche]],Horo82[[#This Row],[Durée]],"") -> 1 | R11: =IF("CONGÉ"=Horo82[[#This Row],[Tâche]],Horo82[[#This Row],[Durée]],"") | S11: =IF("PS"=Horo82[[#This Row],[Tâche]],Horo82[[#This Row],[Durée]],"") | T11: =IF("TD"=Horo82[[#This Row],[Tâche]],Horo82[[#This Row],[Durée]],"") | U11: =IF("N/C"=Horo82[[#This Row],[Tâche]],Horo82[[#This Row],[Durée]],"") | W11: =IF(Horo82[[#This Row],[O]]="o",Horo82[[#This Row],[Durée]],".") -> . | X11: =IF(Horo82[[#This Row],[Début]]=0,"",Horo82[[#This Row],[Fin]]-Horo82[[#This Row],[Début]]) -> 0.041666667
A12: . | B12: =IF(Horo82[[#This Row],[Jour]]="Lundi",$C$1+1, IF(Horo82[[#This Row],[Jour]]="Mardi",$C$1+2, IF(Horo82[[#This Row],[Jour]]="Mercredi",$C$1+3, IF(Horo82[[#This Row],[Jour]]="Jeudi",$C$1+4, IF(Horo82[[#This Row],[Jour]]="Vendredi",$C$1+5, IF(Horo82[[#This Row],[Jour]]="Samedi",$C$1+6, IF(Horo82[[#This Row],[Jour]]="Dimanche",$C$1, ))))))) -> 44461 | C12: Mardi | D12: 0.4375 | E12: 0.5 | F12: RBF | G12: GPF | H12: Étiquette client | J12: =IF(Horo82[[#This Row],[Début]]=0,"",(Horo82[[#This Row],[Durée (60)2]]-INT(Horo82[[#This Row],[Durée (60)2]]))*24) -> 1.5 | K12: =SUMIF(Horo82[Jour],C12,Horo82[Durée]) -> 8 | L12: =IFERROR(SUMIF(Horo82[[#This Row],[Jour]],Horo82[[#This Row],[Jour]],Horo82[[#This Row],[GPF]]) / Horo82[[#This Row],[hrs]],"") -> 0.1875 | M12: =IF("GPF"=Horo82[[#This Row],[Tâche]],Horo82[[#This Row],[Durée]],"") -> 1.5 | N12: =IF("RI"=Horo82[[#This Row],[Tâche]],Horo82[[#This Row],[Durée]],"") | O12: =IF("GB"=Horo82[[#This Row],[Tâche]],Horo82[[#This Row],[Durée]],"") | P12: =IF("RD"=Horo82[[#This Row],[Tâche]],Horo82[[#This Row],[Durée]],"") | Q12: =IF("FG"=Horo82[[#This Row],[Tâche]],Horo82[[#This Row],[Durée]],"") | R12: =IF("CONGÉ"=Horo82[[#This Row],[Tâche]],Horo82[[#This Row],[Durée]],"") | S12: =IF("PS"=Horo82[[#This Row],[Tâche]],Horo82[[#This Row],[Durée]],"") | T12: =IF("TD"=Horo82[[#This Row],[Tâche]],Horo82[[#This Row],[Durée]],"") | U12: =IF("N/C"=Horo82[[#This Row],[Tâche]],Horo82[[#This Row],[Durée]],"") | W12: =IF(Horo82[[#This Row],[O]]="o",Horo82[[#This Row],[Durée]],".") -> . | X12: =IF(Horo82[[#This Row],[Début]]=0,"",Horo82[[#This Row],[Fin]]-Horo82[[#This Row],[Début]]) -> 0.0625
A13: o | B13: =IF(Horo82[[#This Row],[Jour]]="Lundi",$C$1+1, IF(Horo82[[#This Row],[Jour]]="Mardi",$C$1+2, IF(Horo82[[#This Row],[Jour]]="Mercredi",$C$1+3, IF(Horo82[[#This Row],[Jour]]="Jeudi",$C$1+4, IF(Horo82[[#This Row],[Jour]]="Vendredi",$C$1+5, IF(Horo82[[#This Row],[Jour]]="Samedi",$C$1+6, IF(Horo82[[#This Row],[Jour]]="Dimanche",$C$1, ))))))) -> 44461 | C13: Mardi | D13: 0.5625 | E13: 0.72916667 | F13: FORGESTIK | G13: FG | J13: =IF(Horo82[[#This Row],[Début]]=0,"",(Horo82[[#This Row],[Durée (60)2]]-INT(Horo82[[#This Row],[Durée (60)2]]))*24) -> 4 | K13: =SUMIF(Horo82[Jour],C13,Horo82[Durée]) -> 8 | L13: =IFERROR(SUMIF(Horo82[[#This Row],[Jour]],Horo82[[#This Row],[Jour]],Horo82[[#This Row],[GPF]]) / Horo82[[#This Row],[hrs]],"") -> 0 | M13: =IF("GPF"=Horo82[[#This Row],[Tâche]],Horo82[[#This Row],[Durée]],"") | N13: =IF("RI"=Horo82[[#This Row],[Tâche]],Horo82[[#This Row],[Durée]],"") | O13: =IF("GB"=Horo82[[#This Row],[Tâche]],Horo82[[#This Row],[Durée]],"") | P13: =IF("RD"=Horo82[[#This Row],[Tâche]],Horo82[[#This Row],[Durée]],"") | Q13: =IF("FG"=Horo82[[#This Row],[Tâche]],Horo82[[#This Row],[Durée]],"") -> 4 | R13: =IF("CONGÉ"=Horo82[[#This Row],[Tâche]],Horo82[[#This Row],[Durée]],"") | S13: =IF("PS"=Horo82[[#This Row],[Tâche]],Horo82[[#This Row],[Durée]],"") | T13: =IF("TD"=Horo82[[#This Row],[Tâche]],Horo82[[#This Row],[Durée]],"") | U13: =IF("N/C"=Horo82[[#This Row],[Tâche]],Horo82[[#This Row],[Durée]],"") | W13: =IF(Horo82[[#This Row],[O]]="o",Horo82[[#This Row],[Durée]],".") -> 4 | X13: =IF(Horo82[[#This Row],[Début]]=0,"",Horo82[[#This Row],[Fin]]-Horo82[[#This Row],[Début]]) -> 0.16666667
A14: o | B14: =IF(Horo82[[#This Row],[Jour]]="Lundi",$C$1+1, IF(Horo82[[#This Row],[Jour]]="Mardi",$C$1+2, IF(Horo82[[#This Row],[Jour]]="Mercredi",$C$1+3, IF(Horo82[[#This Row],[Jour]]="Jeudi",$C$1+4, IF(Horo82[[#This Row],[Jour]]="Vendredi",$C$1+5, IF(Horo82[[#This Row],[Jour]]="Samedi",$C$1+6, IF(Horo82[[#This Row],[Jour]]="Dimanche",$C$1, ))))))) -> 44462 | C14: Mercredi | D14: 0.33333333 | E14: 0.35416667 | F14: FORGESTIK | G14: GB | H14: . | J14: =IF(Horo82[[#This Row],[Début]]=0,"",(Horo82[[#This Row],[Durée (60)2]]-INT(Horo82[[#This Row],[Durée (60)2]]))*24) -> 0.5 | K14: =SUMIF(Horo82[Jour],C14,Horo82[Durée]) -> 7.25 | L14: =IFERROR(SUMIF(Horo82[[#This Row],[Jour]],Horo82[[#This Row],[Jour]],Horo82[[#This Row],[GPF]]) / Horo82[[#This Row],[hrs]],"") -> 0 | M14: =IF("GPF"=Horo82[[#This Row],[Tâche]],Horo82[[#This Row],[Durée]],"") | N14: =IF("RI"=Horo82[[#This Row],[Tâche]],Horo82[[#This Row],[Durée]],"") | O14: =IF("GB"=Horo82[[#This Row],[Tâche]],Horo82[[#This Row],[Durée]],"") -> 0.5 | P14: =IF("RD"=Horo82[[#This Row],[Tâche]],Horo82[[#This Row],[Durée]],"") | Q14: =IF("FG"=Horo82[[#This Row],[Tâche]],Horo82[[#This Row],[Durée]],"") | R14: =IF("CONGÉ"=Horo82[[#This Row],[Tâche]],Horo82[[#This Row],[Durée]],"") | S14: =IF("PS"=Horo82[[#This Row],[Tâche]],Horo82[[#This Row],[Durée]],"") | T14: =IF("TD"=Horo82[[#This Row],[Tâche]],Horo82[[#This Row],[Durée]],"") | U14: =IF("N/C"=Horo82[[#This Row],[Tâche]],Horo82[[#This Row],[Durée]],"") | W14: =IF(Horo82[[#This Row],[O]]="o",Horo82[[#This Row],[Durée]],".") -> 0.5 | X14: =IF(Horo82[[#This Row],[Début]]=0,"",Horo82[[#This Row],[Fin]]-Horo82[[#This Row],[Début]]) -> 0.020833333
A15: . | B15: =IF(Horo82[[#This Row],[Jour]]="Lundi",$C$1+1, IF(Horo82[[#This Row],[Jour]]="Mardi",$C$1+2, IF(Horo82[[#This Row],[Jour]]="Mercredi",$C$1+3, IF(Horo82[[#This Row],[Jour]]="Jeudi",$C$1+4, IF(Horo82[[#This Row],[Jour]]="Vendredi",$C$1+5, IF(Horo82[[#This Row],[Jour]]="Samedi",$C$1+6, IF(Horo82[[#This Row],[Jour]]="Dimanche",$C$1, ))))))) -> 44462 | C15: Mercredi | D15: 0.35416667 | E15: 0.41666667 | F15: DUER | G15: GPF | H15: Billet | I15: T20250922.0054 | J15: =IF(Horo82[[#This Row],[Début]]=0,"",(Horo82[[#This Row],[Durée (60)2]]-INT(Horo82[[#This Row],[Durée (60)2]]))*24) -> 1.5 | K15: =SUMIF(Horo82[Jour],C15,Horo82[Durée]) -> 7.25 | L15: =IFERROR(SUMIF(Horo82[[#This Row],[Jour]],Horo82[[#This Row],[Jour]],Horo82[[#This Row],[GPF]]) / Horo82[[#This Row],[hrs]],"") -> 0.20689655 | M15: =IF("GPF"=Horo82[[#This Row],[Tâche]],Horo82[[#This Row],[Durée]],"") -> 1.5 | N15: =IF("RI"=Horo82[[#This Row],[Tâche]],Horo82[[#This Row],[Durée]],"") | O15: =IF("GB"=Horo82[[#This Row],[Tâche]],Horo82[[#This Row],[Durée]],"") | P15: =IF("RD"=Horo82[[#This Row],[Tâche]],Horo82[[#This Row],[Durée]],"") | Q15: =IF("FG"=Horo82[[#This Row],[Tâche]],Horo82[[#This Row],[Durée]],"") | R15: =IF("CONGÉ"=Horo82[[#This Row],[Tâche]],Horo82[[#This Row],[Durée]],"") | S15: =IF("PS"=Horo82[[#This Row],[Tâche]],Horo82[[#This Row],[Durée]],"") | T15: =IF("TD"=Horo82[[#This Row],[Tâche]],Horo82[[#This Row],[Durée]],"") | U15: =IF("N/C"=Horo82[[#This Row],[Tâche]],Horo82[[#This Row],[Durée]],"") | W15: =IF(Horo82[[#This Row],[O]]="o",Horo82[[#This Row],[Durée]],".") -> . | X15: =IF(Horo82[[#This Row],[Début]]=0,"",Horo82[[#This Row],[Fin]]-Horo82[[#This Row],[Début]]) -> 0.0625
A16: o | B16: =IF(Horo82[[#This Row],[Jour]]="Lundi",$C$1+1, IF(Horo82[[#This Row],[Jour]]="Mardi",$C$1+2, IF(Horo82[[#This Row],[Jour]]="Mercredi",$C$1+3, IF(Horo82[[#This Row],[Jour]]="Jeudi",$C$1+4, IF(Horo82[[#This Row],[Jour]]="Vendredi",$C$1+5, IF(Horo82[[#This Row],[Jour]]="Samedi",$C$1+6, IF(Horo82[[#This Row],[Jour]]="Dimanche",$C$1, ))))))) -> 44462 | C16: Mercredi | D16: 0.41666667 | E16: 0.4375 | F16: RBF | G16: GPF | I16: fichier imporation | J16: =IF(Horo82[[#This Row],[Début]]=0,"",(Horo82[[#This Row],[Durée (60)2]]-INT(Horo82[[#This Row],[Durée (60)2]]))*24) -> 0.5 | K16: =SUMIF(Horo82[Jour],C16,Horo82[Durée]) -> 7.25 | L16: =IFERROR(SUMIF(Horo82[[#This Row],[Jour]],Horo82[[#This Row],[Jour]],Horo82[[#This Row],[GPF]]) / Horo82[[#This Row],[hrs]],"") -> 0.068965517 | M16: =IF("GPF"=Horo82[[#This Row],[Tâche]],Horo82[[#This Row],[Durée]],"") -> 0.5 | N16: =IF("RI"=Horo82[[#This Row],[Tâche]],Horo82[[#This Row],[Durée]],"") | O16: =IF("GB"=Horo82[[#This Row],[Tâche]],Horo82[[#This Row],[Durée]],"") | P16: =IF("RD"=Horo82[[#This Row],[Tâche]],Horo82[[#This Row],[Durée]],"") | Q16: =IF("FG"=Horo82[[#This Row],[Tâche]],Horo82[[#This Row],[Durée]],"") | R16: =IF("CONGÉ"=Horo82[[#This Row],[Tâche]],Horo82[[#This Row],[Durée]],"") | S16: =IF("PS"=Horo82[[#This Row],[Tâche]],Horo82[[#This Row],[Durée]],"") | T16: =IF("TD"=Horo82[[#This Row],[Tâche]],Horo82[[#This Row],[Durée]],"") | U16: =IF("N/C"=Horo82[[#This Row],[Tâche]],Horo82[[#This Row],[Durée]],"") | W16: =IF(Horo82[[#This Row],[O]]="o",Horo82[[#This Row],[Durée]],".") -> 0.5 | X16: =IF(Horo82[[#This Row],[Début]]=0,"",Horo82[[#This Row],[Fin]]-Horo82[[#This Row],[Début]]) -> 0.020833333
A17: . | B17: =IF(Horo82[[#This Row],[Jour]]="Lundi",$C$1+1, IF(Horo82[[#This Row],[Jour]]="Mardi",$C$1+2, IF(Horo82[[#This Row],[Jour]]="Mercredi",$C$1+3, IF(Horo82[[#This Row],[Jour]]="Jeudi",$C$1+4, IF(Horo82[[#This Row],[Jour]]="Vendredi",$C$1+5, IF(Horo82[[#This Row],[Jour]]="Samedi",$C$1+6, IF(Horo82[[#This Row],[Jour]]="Dimanche",$C$1, ))))))) -> 44462 | C17: Mercredi | D17: 0.4375 | E17: 0.5 | F17: DUER | G17: FG | H17: Billet | I17: T20250922.0054 | J17: =IF(Horo82[[#This Row],[Début]]=0,"",(Horo82[[#This Row],[Durée (60)2]]-INT(Horo82[[#This Row],[Durée (60)2]]))*24) -> 1.5 | K17: =SUMIF(Horo82[Jour],C17,Horo82[Durée]) -> 7.25 | L17: =IFERROR(SUMIF(Horo82[[#This Row],[Jour]],Horo82[[#This Row],[Jour]],Horo82[[#This Row],[GPF]]) / Horo82[[#This Row],[hrs]],"") -> 0 | M17: =IF("GPF"=Horo82[[#This Row],[Tâche]],Horo82[[#This Row],[Durée]],"") | N17: =IF("RI"=Horo82[[#This Row],[Tâche]],Horo82[[#This Row],[Durée]],"") | O17: =IF("GB"=Horo82[[#This Row],[Tâche]],Horo82[[#This Row],[Durée]],"") | P17: =IF("RD"=Horo82[[#This Row],[Tâche]],Horo82[[#This Row],[Durée]],"") | Q17: =IF("FG"=Horo82[[#This Row],[Tâche]],Horo82[[#This Row],[Durée]],"") -> 1.5 | R17: =IF("CONGÉ"=Horo82[[#This Row],[Tâche]],Horo82[[#This Row],[Durée]],"") | S17: =IF("PS"=Horo82[[#This Row],[Tâche]],Horo82[[#This Row],[Durée]],"") | T17: =IF("TD"=Horo82[[#This Row],[Tâche]],Horo82[[#This Row],[Durée]],"") | U17: =IF("N/C"=Horo82[[#This Row],[Tâche]],Horo82[[#This Row],[Durée]],"") | W17: =IF(Horo82[[#This Row],[O]]="o",Horo82[[#This Row],[Durée]],".") -> . | X17: =IF(Horo82[[#This Row],[Début]]=0,"",Horo82[[#This Row],[Fin]]-Horo82[[#This Row],[Début]]) -> 0.0625
A18: o | B18: =IF(Horo82[[#This Row],[Jour]]="Lundi",$C$1+1, IF(Horo82[[#This Row],[Jour]]="Mardi",$C$1+2, IF(Horo82[[#This Row],[Jour]]="Mercredi",$C$1+3, IF(Horo82[[#This Row],[Jour]]="Jeudi",$C$1+4, IF(Horo82[[#This Row],[Jour]]="Vendredi",$C$1+5, IF(Horo82[[#This Row],[Jour]]="Samedi",$C$1+6, IF(Horo82[[#This Row],[Jour]]="Dimanche",$C$1, ))))))) -> 44462 | C18: Mercredi | D18: 0.61458333 | E18: 0.625 | F18: TENZO | H18: Billet | I18: T20250923.0052 - réponse à Gérard | J18: =IF(Horo82[[#This Row],[Début]]=0,"",(Horo82[[#This Row],[Durée (60)2]]-INT(Horo82[[#This Row],[Durée (60)2]]))*24) -> 0.25 | K18: =SUMIF(Horo82[Jour],C18,Horo82[Durée]) -> 7.25 | L18: =IFERROR(SUMIF(Horo82[[#This Row],[Jour]],Horo82[[#This Row],[Jour]],Horo82[[#This Row],[GPF]]) / Horo82[[#This Row],[hrs]],"") -> 0 | M18: =IF("GPF"=Horo82[[#This Row],[Tâche]],Horo82[[#This Row],[Durée]],"") | N18: =IF("RI"=Horo82[[#This Row],[Tâche]],Horo82[[#This Row],[Durée]],"") | O18: =IF("GB"=Horo82[[#This Row],[Tâche]],Horo82[[#This Row],[Durée]],"") | P18: =IF("RD"=Horo82[[#This Row],[Tâche]],Horo82[[#This Row],[Durée]],"") | Q18: =IF("FG"=Horo82[[#This Row],[Tâche]],Horo82[[#This Row],[Durée]],"") | R18: =IF("CONGÉ"=Horo82[[#This Row],[Tâche]],Horo82[[#This Row],[Durée]],"") | S18: =IF("PS"=Horo82[[#This Row],[Tâche]],Horo82[[#This Row],[Durée]],"") | T18: =IF("TD"=Horo82[[#This Row],[Tâche]],Horo82[[#This Row],[Durée]],"") | U18: =IF("N/C"=Horo82[[#This Row],[Tâche]],Horo82[[#This Row],[Durée]],"") | W18: =IF(Horo82[[#This Row],[O]]="o",Horo82[[#This Row],[Durée]],".") -> 0.25 | X18: =IF(Horo82[[#This Row],[Début]]=0,"",Horo82[[#This Row],[Fin]]-Horo82[[#This Row],[Début]]) -> 0.010416667
A19: =IF(Horo82[[#This Row],[Date]]="",".",".") -> . | B19: =IF(Horo82[[#This Row],[Jour]]="Lundi",$C$1+1, IF(Horo82[[#This Row],[Jour]]="Mardi",$C$1+2, IF(Horo82[[#This Row],[Jour]]="Mercredi",$C$1+3, IF(Horo82[[#This Row],[Jour]]="Jeudi",$C$1+4, IF(Horo82[[#This Row],[Jour]]="Vendredi",$C$1+5, IF(Horo82[[#This Row],[Jour]]="Samedi",$C$1+6, IF(Horo82[[#This Row],[Jour]]="Dimanche",$C$1, ))))))) -> 44462 | C19: Mercredi | D19: 0.66666667 | E19: 0.6875 | F19: COATICOOK | G19: GPF | H19: Investigation | I19: Troubl Shot - Test scanneur pour quai n'est paas disponible | J19: =IF(Horo82[[#This Row],[Début]]=0,"",(Horo82[[#This Row],[Durée (60)2]]-INT(Horo82[[#This Row],[Durée (60)2]]))*24) -> 0.5 | K19: =SUMIF(Horo82[Jour],C19,Horo82[Durée]) -> 7.25 | L19: =IFERROR(SUMIF(Horo82[[#This Row],[Jour]],Horo82[[#This Row],[Jour]],Horo82[[#This Row],[GPF]]) / Horo82[[#This Row],[hrs]],"") -> 0.068965517 | M19: =IF("GPF"=Horo82[[#This Row],[Tâche]],Horo82[[#This Row],[Durée]],"") -> 0.5 | N19: =IF("RI"=Horo82[[#This Row],[Tâche]],Horo82[[#This Row],[Durée]],"") | O19: =IF("GB"=Horo82[[#This Row],[Tâche]],Horo82[[#This Row],[Durée]],"") | P19: =IF("RD"=Horo82[[#This Row],[Tâche]],Horo82[[#This Row],[Durée]],"") | Q19: =IF("FG"=Horo82[[#This Row],[Tâche]],Horo82[[#This Row],[Durée]],"") | R19: =IF("CONGÉ"=Horo82[[#This Row],[Tâche]],Horo82[[#This Row],[Durée]],"") | S19: =IF("PS"=Horo82[[#This Row],[Tâche]],Horo82[[#This Row],[Durée]],"") | T19: =IF("TD"=Horo82[[#This Row],[Tâche]],Horo82[[#This Row],[Durée]],"") | U19: =IF("N/C"=Horo82[[#This Row],[Tâche]],Horo82[[#This Row],[Durée]],"") | W19: =IF(Horo82[[#This Row],[O]]="o",Horo82[[#This Row],[Durée]],".") -> . | X19: =IF(Horo82[[#This Row],[Début]]=0,"",Horo82[[#This Row],[Fin]]-Horo82[[#This Row],[Début]]) -> 0.020833333
A20: o | B20: =IF(Horo82[[#This Row],[Jour]]="Lundi",$C$1+1, IF(Horo82[[#This Row],[Jour]]="Mardi",$C$1+2, IF(Horo82[[#This Row],[Jour]]="Mercredi",$C$1+3, IF(Horo82[[#This Row],[Jour]]="Jeudi",$C$1+4, IF(Horo82[[#This Row],[Jour]]="Vendredi",$C$1+5, IF(Horo82[[#This Row],[Jour]]="Samedi",$C$1+6, IF(Horo82[[#This Row],[Jour]]="Dimanche",$C$1, ))))))) -> 44462 | C20: Mercredi | D20: 0.70833333 | E20: 0.77083333 | F20: RBF | G20: FG | I20: Créer le UDF pour Liquide, granule, …connecter crystal à l'udf | J20: =IF(Horo82[[#This Row],[Début]]=0,"",(Horo82[[#This Row],[Durée (60)2]]-INT(Horo82[[#This Row],[Durée (60)2]]))*24) -> 1.5 | K20: =SUMIF(Horo82[Jour],C20,Horo82[Durée]) -> 7.25 | L20: =IFERROR(SUMIF(Horo82[[#This Row],[Jour]],Horo82[[#This Row],[Jour]],Horo82[[#This Row],[GPF]]) / Horo82[[#This Row],[hrs]],"") -> 0 | M20: =IF("GPF"=Horo82[[#This Row],[Tâche]],Horo82[[#This Row],[Durée]],"") | N20: =IF("RI"=Horo82[[#This Row],[Tâche]],Horo82[[#This Row],[Durée]],"") | O20: =IF("GB"=Horo82[[#This Row],[Tâche]],Horo82[[#This Row],[Durée]],"") | P20: =IF("RD"=Horo82[[#This Row],[Tâche]],Horo82[[#This Row],[Durée]],"") | Q20: =IF("FG"=Horo82[[#This Row],[Tâche]],Horo82[[#This Row],[Durée]],"") -> 1.5 | R20: =IF("CONGÉ"=Horo82[[#This Row],[Tâche]],Horo82[[#This Row],[Durée]],"") | S20: =IF("PS"=Horo82[[#This Row],[Tâche]],Horo82[[#This Row],[Durée]],"") | T20: =IF("TD"=Horo82[[#This Row],[Tâche]],Horo82[[#This Row],[Durée]],"") | U20: =IF("N/C"=Horo82[[#This Row],[Tâche]],Horo82[[#This Row],[Durée]],"") | W20: =IF(Horo82[[#This Row],[O]]="o",Horo82[[#This Row],[Durée]],".") -> 1.5 | X20: =IF(Horo82[[#This Row],[Début]]=0,"",Horo82[[#This Row],[Fin]]-Horo82[[#This Row],[Début]]) -> 0.0625
A21: o | B21: =IF(Horo82[[#This Row],[Jour]]="Lundi",$C$1+1, IF(Horo82[[#This Row],[Jour]]="Mardi",$C$1+2, IF(Horo82[[#This Row],[Jour]]="Mercredi",$C$1+3, IF(Horo82[[#This Row],[Jour]]="Jeudi",$C$1+4, IF(Horo82[[#This Row],[Jour]]="Vendredi",$C$1+5, IF(Horo82[[#This Row],[Jour]]="Samedi",$C$1+6, IF(Horo82[[#This Row],[Jour]]="Dimanche",$C$1, ))))))) -> 44462 | C21: Mercredi | D21: 0.77083333 | E21: 0.8125 | F21: FORGESTIK | G21: FG | J21: =IF(Horo82[[#This Row],[Début]]=0,"",(Horo82[[#This Row],[Durée (60)2]]-INT(Horo82[[#This Row],[Durée (60)2]]))*24) -> 1 | K21: =SUMIF(Horo82[Jour],C21,Horo82[Durée]) -> 7.25 | L21: =IFERROR(SUMIF(Horo82[[#This Row],[Jour]],Horo82[[#This Row],[Jour]],Horo82[[#This Row],[GPF]]) / Horo82[[#This Row],[hrs]],"") -> 0 | M21: =IF("GPF"=Horo82[[#This Row],[Tâche]],Horo82[[#This Row],[Durée]],"") | N21: =IF("RI"=Horo82[[#This Row],[Tâche]],Horo82[[#This Row],[Durée]],"") | O21: =IF("GB"=Horo82[[#This Row],[Tâche]],Horo82[[#This Row],[Durée]],"") | P21: =IF("RD"=Horo82[[#This Row],[Tâche]],Horo82[[#This Row],[Durée]],"") | Q21: =IF("FG"=Horo82[[#This Row],[Tâche]],Horo82[[#This Row],[Durée]],"") -> 1 | R21: =IF("CONGÉ"=Horo82[[#This Row],[Tâche]],Horo82[[#This Row],[Durée]],"") | S21: =IF("PS"=Horo82[[#This Row],[Tâche]],Horo82[[#This Row],[Durée]],"") | T21: =IF("TD"=Horo82[[#This Row],[Tâche]],Horo82[[#This Row],[Durée]],"") | U21: =IF("N/C"=Horo82[[#This Row],[Tâche]],Horo82[[#This Row],[Durée]],"") | W21: =IF(Horo82[[#This Row],[O]]="o",Horo82[[#This Row],[Durée]],".") -> 1 | X21: =IF(Horo82[[#This Row],[Début]]=0,"",Horo82[[#This Row],[Fin]]-Horo82[[#This Row],[Début]]) -> 0.041666667
A22: o | B22: =IF(Horo82[[#This Row],[Jour]]="Lundi",$C$1+1, IF(Horo82[[#This Row],[Jour]]="Mardi",$C$1+2, IF(Horo82[[#This Row],[Jour]]="Mercredi",$C$1+3, IF(Horo82[[#This Row],[Jour]]="Jeudi",$C$1+4, IF(Horo82[[#This Row],[Jour]]="Vendredi",$C$1+5, IF(Horo82[[#This Row],[Jour]]="Samedi",$C$1+6, IF(Horo82[[#This Row],[Jour]]="Dimanche",$C$1, ))))))) -> 44463 | C22: Jeudi | D22: 0.3125 | E22: 0.33333333 | F22: FORGESTIK | G22: GB | J22: =IF(Horo82[[#This Row],[Début]]=0,"",(Horo82[[#This Row],[Durée (60)2]]-INT(Horo82[[#This Row],[Durée (60)2]]))*24) -> 0.5 | K22: =SUMIF(Horo82[Jour],C22,Horo82[Durée]) -> 8.75 | L22: =IFERROR(SUMIF(Horo82[[#This Row],[Jour]],Horo82[[#This Row],[Jour]],Horo82[[#This Row],[GPF]]) / Horo82[[#This Row],[hrs]],"") -> 0 | M22: =IF("GPF"=Horo82[[#This Row],[Tâche]],Horo82[[#This Row],[Durée]],"") | N22: =IF("RI"=Horo82[[#This Row],[Tâche]],Horo82[[#This Row],[Durée]],"") | O22: =IF("GB"=Horo82[[#This Row],[Tâche]],Horo82[[#This Row],[Durée]],"") -> 0.5 | P22: =IF("RD"=Horo82[[#This Row],[Tâche]],Horo82[[#This Row],[Durée]],"") | Q22: =IF("FG"=Horo82[[#This Row],[Tâche]],Horo82[[#This Row],[Durée]],"") | R22: =IF("CONGÉ"=Horo82[[#This Row],[Tâche]],Horo82[[#This Row],[Durée]],"") | S22: =IF("PS"=Horo82[[#This Row],[Tâche]],Horo82[[#This Row],[Durée]],"") | T22: =IF("TD"=Horo82[[#This Row],[Tâche]],Horo82[[#This Row],[Durée]],"") | U22: =IF("N/C"=Horo82[[#This Row],[Tâche]],Horo82[[#This Row],[Durée]],"") | W22: =IF(Horo82[[#This Row],[O]]="o",Horo82[[#This Row],[Durée]],".") -> 0.5 | X22: =IF(Horo82[[#This Row],[Début]]=0,"",Horo82[[#This Row],[Fin]]-Horo82[[#This Row],[Début]]) -> 0.020833333
A23: =IF(Horo82[[#This Row],[Date]]="",".",".") -> . | B23: =IF(Horo82[[#This Row],[Jour]]="Lundi",$C$1+1, IF(Horo82[[#This Row],[Jour]]="Mardi",$C$1+2, IF(Horo82[[#This Row],[Jour]]="Mercredi",$C$1+3, IF(Horo82[[#This Row],[Jour]]="Jeudi",$C$1+4, IF(Horo82[[#This Row],[Jour]]="Vendredi",$C$1+5, IF(Horo82[[#This Row],[Jour]]="Samedi",$C$1+6, IF(Horo82[[#This Row],[Jour]]="Dimanche",$C$1, ))))))) -> 44463 | C23: Jeudi | D23: 0.33333333 | E23: 0.47916667 | F23: RBF | G23: GPF | H23: Étiquette client | J23: =IF(Horo82[[#This Row],[Début]]=0,"",(Horo82[[#This Row],[Durée (60)2]]-INT(Horo82[[#This Row],[Durée (60)2]]))*24) -> 3.5 | K23: =SUMIF(Horo82[Jour],C23,Horo82[Durée]) -> 8.75 | L23: =IFERROR(SUMIF(Horo82[[#This Row],[Jour]],Horo82[[#This Row],[Jour]],Horo82[[#This Row],[GPF]]) / Horo82[[#This Row],[hrs]],"") -> 0.4 | M23: =IF("GPF"=Horo82[[#This Row],[Tâche]],Horo82[[#This Row],[Durée]],"") -> 3.5 | N23: =IF("RI"=Horo82[[#This Row],[Tâche]],Horo82[[#This Row],[Durée]],"") | O23: =IF("GB"=Horo82[[#This Row],[Tâche]],Horo82[[#This Row],[Durée]],"") | P23: =IF("RD"=Horo82[[#This Row],[Tâche]],Horo82[[#This Row],[Durée]],"") | Q23: =IF("FG"=Horo82[[#This Row],[Tâche]],Horo82[[#This Row],[Durée]],"") | R23: =IF("CONGÉ"=Horo82[[#This Row],[Tâche]],Horo82[[#This Row],[Durée]],"") | S23: =IF("PS"=Horo82[[#This Row],[Tâche]],Horo82[[#This Row],[Durée]],"") | T23: =IF("TD"=Horo82[[#This Row],[Tâche]],Horo82[[#This Row],[Durée]],"") | U23: =IF("N/C"=Horo82[[#This Row],[Tâche]],Horo82[[#This Row],[Durée]],"") | W23: =IF(Horo82[[#This Row],[O]]="o",Horo82[[#This Row],[Durée]],".") -> . | X23: =IF(Horo82[[#This Row],[Début]]=0,"",Horo82[[#This Row],[Fin]]-Horo82[[#This Row],[Début]]) -> 0.14583333
A24: o | B24: =IF(Horo82[[#This Row],[Jour]]="Lundi",$C$1+1, IF(Horo82[[#This Row],[Jour]]="Mardi",$C$1+2, IF(Horo82[[#This Row],[Jour]]="Mercredi",$C$1+3, IF(Horo82[[#This Row],[Jour]]="Jeudi",$C$1+4, IF(Horo82[[#This Row],[Jour]]="Vendredi",$C$1+5, IF(Horo82[[#This Row],[Jour]]="Samedi",$C$1+6, IF(Horo82[[#This Row],[Jour]]="Dimanche",$C$1, ))))))) -> 44463 | C24: Jeudi | D24: 0.5 | E24: 0.52083333 | F24: RBF | G24: TD | H24: Déplacement chez le client | I24: RBF ST-Jérôme | J24: =IF(Horo82[[#This Row],[Début]]=0,"",(Horo82[[#This Row],[Durée (60)2]]-INT(Horo82[[#This Row],[Durée (60)2]]))*24) -> 0.5 | K24: =SUMIF(Horo82[Jour],C24,Horo82[Durée]) -> 8.75 | L24: =IFERROR(SUMIF(Horo82[[#This Row],[Jour]],Horo82[[#This Row],[Jour]],Horo82[[#This Row],[GPF]]) / Horo82[[#This Row],[hrs]],"") -> 0 | M24: =IF("GPF"=Horo82[[#This Row],[Tâche]],Horo82[[#This Row],[Durée]],"") | N24: =IF("RI"=Horo82[[#This Row],[Tâche]],Horo82[[#This Row],[Durée]],"") | O24: =IF("GB"=Horo82[[#This Row],[Tâche]],Horo82[[#This Row],[Durée]],"") | P24: =IF("RD"=Horo82[[#This Row],[Tâche]],Horo82[[#This Row],[Durée]],"") | Q24: =IF("FG"=Horo82[[#This Row],[Tâche]],Horo82[[#This Row],[Durée]],"") | R24: =IF("CONGÉ"=Horo82[[#This Row],[Tâche]],Horo82[[#This Row],[Durée]],"") | S24: =IF("PS"=Horo82[[#This Row],[Tâche]],Horo82[[#This Row],[Durée]],"") | T24: =IF("TD"=Horo82[[#This Row],[Tâche]],Horo82[[#This Row],[Durée]],"") -> 0.5 | U24: =IF("N/C"=Horo82[[#This Row],[Tâche]],Horo82[[#This Row],[Durée]],"") | W24: =IF(Horo82[[#This Row],[O]]="o",Horo82[[#This Row],[Durée]],".") -> 0.5 | X24: =IF(Horo82[[#This Row],[Début]]=0,"",Horo82[[#This Row],[Fin]]-Horo82[[#This Row],[Début]]) -> 0.020833333
A25: o | B25: =IF(Horo82[[#This Row],[Jour]]="Lundi",$C$1+1, IF(Horo82[[#This Row],[Jour]]="Mardi",$C$1+2, IF(Horo82[[#This Row],[Jour]]="Mercredi",$C$1+3, IF(Horo82[[#This Row],[Jour]]="Jeudi",$C$1+4, IF(Horo82[[#This Row],[Jour]]="Vendredi",$C$1+5, IF(Horo82[[#This Row],[Jour]]="Samedi",$C$1+6, IF(Horo82[[#This Row],[Jour]]="Dimanche",$C$1, ))))))) -> 44463 | C25: Jeudi | D25: 0.52083333 | E25: 0.66666667 | F25: RBF | G25: GPF | H25: Formation PMX | I25: Rencontre sur place avec Christian,Geneviève, Brian, Francine | J25: =IF(Horo82[[#This Row],[Début]]=0,"",(Horo82[[#This Row],[Durée (60)2]]-INT(Horo82[[#This Row],[Durée (60)2]]))*24) -> 3.5 | K25: =SUMIF(Horo82[Jour],C25,Horo82[Durée]) -> 8.75 | L25: =IFERROR(SUMIF(Horo82[[#This Row],[Jour]],Horo82[[#This Row],[Jour]],Horo82[[#This Row],[GPF]]) / Horo82[[#This Row],[hrs]],"") -> 0.4 | M25: =IF("GPF"=Horo82[[#This Row],[Tâche]],Horo82[[#This Row],[Durée]],"") -> 3.5 | N25: =IF("RI"=Horo82[[#This Row],[Tâche]],Horo82[[#This Row],[Durée]],"") | O25: =IF("GB"=Horo82[[#This Row],[Tâche]],Horo82[[#This Row],[Durée]],"") | P25: =IF("RD"=Horo82[[#This Row],[Tâche]],Horo82[[#This Row],[Durée]],"") | Q25: =IF("FG"=Horo82[[#This Row],[Tâche]],Horo82[[#This Row],[Durée]],"") | R25: =IF("CONGÉ"=Horo82[[#This Row],[Tâche]],Horo82[[#This Row],[Durée]],"") | S25: =IF("PS"=Horo82[[#This Row],[Tâche]],Horo82[[#This Row],[Durée]],"") | T25: =IF("TD"=Horo82[[#This Row],[Tâche]],Horo82[[#This Row],[Durée]],"") | U25: =IF("N/C"=Horo82[[#This Row],[Tâche]],Horo82[[#This Row],[Durée]],"") | W25: =IF(Horo82[[#This Row],[O]]="o",Horo82[[#This Row],[Durée]],".") -> 3.5 | X25: =IF(Horo82[[#This Row],[Début]]=0,"",Horo82[[#This Row],[Fin]]-Horo82[[#This Row],[Début]]) -> 0.14583333
A26: o | B26: =IF(Horo82[[#This Row],[Jour]]="Lundi",$C$1+1, IF(Horo82[[#This Row],[Jour]]="Mardi",$C$1+2, IF(Horo82[[#This Row],[Jour]]="Mercredi",$C$1+3, IF(Horo82[[#This Row],[Jour]]="Jeudi",$C$1+4, IF(Horo82[[#This Row],[Jour]]="Vendredi",$C$1+5, IF(Horo82[[#This Row],[Jour]]="Samedi",$C$1+6, IF(Horo82[[#This Row],[Jour]]="Dimanche",$C$1, ))))))) -> 44463 | C26: Jeudi | D26: 0.66666667 | E26: 0.69791667 | F26: RBF | G26: TD | H26: Déplacement chez le client | I26: RBF ST-Jérôme | J26: =IF(Horo82[[#This Row],[Début]]=0,"",(Horo82[[#This Row],[Durée (60)2]]-INT(Horo82[[#This Row],[Durée (60)2]]))*24) -> 0.75 | K26: =SUMIF(Horo82[Jour],C26,Horo82[Durée]) -> 8.75 | L26: =IFERROR(SUMIF(Horo82[[#This Row],[Jour]],Horo82[[#This Row],[Jour]],Horo82[[#This Row],[GPF]]) / Horo82[[#This Row],[hrs]],"") -> 0 | M26: =IF("GPF"=Horo82[[#This Row],[Tâche]],Horo82[[#This Row],[Durée]],"") | N26: =IF("RI"=Horo82[[#This Row],[Tâche]],Horo82[[#This Row],[Durée]],"") | O26: =IF("GB"=Horo82[[#This Row],[Tâche]],Horo82[[#This Row],[Durée]],"") | P26: =IF("RD"=Horo82[[#This Row],[Tâche]],Horo82[[#This Row],[Durée]],"") | Q26: =IF("FG"=Horo82[[#This Row],[Tâche]],Horo82[[#This Row],[Durée]],"") | R26: =IF("CONGÉ"=Horo82[[#This Row],[Tâche]],Horo82[[#This Row],[Durée]],"") | S26: =IF("PS"=Horo82[[#This Row],[Tâche]],Horo82[[#This Row],[Durée]],"") | T26: =IF("TD"=Horo82[[#This Row],[Tâche]],Horo82[[#This Row],[Durée]],"") -> 0.75 | U26: =IF("N/C"=Horo82[[#This Row],[Tâche]],Horo82[[#This Row],[Durée]],"") | W26: =IF(Horo82[[#This Row],[O]]="o",Horo82[[#This Row],[Durée]],".") -> 0.75 | X26: =IF(Horo82[[#This Row],[Début]]=0,"",Horo82[[#This Row],[Fin]]-Horo82[[#This Row],[Début]]) -> 0.03125
A27: o | B27: =IF(Horo82[[#This Row],[Jour]]="Lundi",$C$1+1, IF(Horo82[[#This Row],[Jour]]="Mardi",$C$1+2, IF(Horo82[[#This Row],[Jour]]="Mercredi",$C$1+3, IF(Horo82[[#This Row],[Jour]]="Jeudi",$C$1+4, IF(Horo82[[#This Row],[Jour]]="Vendredi",$C$1+5, IF(Horo82[[#This Row],[Jour]]="Samedi",$C$1+6, IF(Horo82[[#This Row],[Jour]]="Dimanche",$C$1, ))))))) -> 44464 | C27: Vendredi | D27: 0.3125 | E27: 0.33333333 | F27: FORGESTIK | G27: GB | H27: . | J27: =IF(Horo82[[#This Row],[Début]]=0,"",(Horo82[[#This Row],[Durée (60)2]]-INT(Horo82[[#This Row],[Durée (60)2]]))*24) -> 0.5 | K27: =SUMIF(Horo82[Jour],C27,Horo82[Durée]) -> 7 | L27: =IFERROR(SUMIF(Horo82[[#This Row],[Jour]],Horo82[[#This Row],[Jour]],Horo82[[#This Row],[GPF]]) / Horo82[[#This Row],[hrs]],"") -> 0 | M27: =IF("GPF"=Horo82[[#This Row],[Tâche]],Horo82[[#This Row],[Durée]],"") | N27: =IF("RI"=Horo82[[#This Row],[Tâche]],Horo82[[#This Row],[Durée]],"") | O27: =IF("GB"=Horo82[[#This Row],[Tâche]],Horo82[[#This Row],[Durée]],"") -> 0.5 | P27: =IF("RD"=Horo82[[#This Row],[Tâche]],Horo82[[#This Row],[Durée]],"") | Q27: =IF("FG"=Horo82[[#This Row],[Tâche]],Horo82[[#This Row],[Durée]],"") | R27: =IF("CONGÉ"=Horo82[[#This Row],[Tâche]],Horo82[[#This Row],[Durée]],"") | S27: =IF("PS"=Horo82[[#This Row],[Tâche]],Horo82[[#This Row],[Durée]],"") | T27: =IF("TD"=Horo82[[#This Row],[Tâche]],Horo82[[#This Row],[Durée]],"") | U27: =IF("N/C"=Horo82[[#This Row],[Tâche]],Horo82[[#This Row],[Durée]],"") | W27: =IF(Horo82[[#This Row],[O]]="o",Horo82[[#This Row],[Durée]],".") -> 0.5 | X27: =IF(Horo82[[#This Row],[Début]]=0,"",Horo82[[#This Row],[Fin]]-Horo82[[#This Row],[Début]]) -> 0.020833333
A28: . | B28: =IF(Horo82[[#This Row],[Jour]]="Lundi",$C$1+1, IF(Horo82[[#This Row],[Jour]]="Mardi",$C$1+2, IF(Horo82[[#This Row],[Jour]]="Mercredi",$C$1+3, IF(Horo82[[#This Row],[Jour]]="Jeudi",$C$1+4, IF(Horo82[[#This Row],[Jour]]="Vendredi",$C$1+5, IF(Horo82[[#This Row],[Jour]]="Samedi",$C$1+6, IF(Horo82[[#This Row],[Jour]]="Dimanche",$C$1, ))))))) -> 44464 | C28: Vendredi | D28: 0.33333333 | E28: 0.39583333 | F28: RBF | G28: GPF | H28: Étiquette client | J28: =IF(Horo82[[#This Row],[Début]]=0,"",(Horo82[[#This Row],[Durée (60)2]]-INT(Horo82[[#This Row],[Durée (60)2]]))*24) -> 1.5 | K28: =SUMIF(Horo82[Jour],C28,Horo82[Durée]) -> 7 | L28: =IFERROR(SUMIF(Horo82[[#This Row],[Jour]],Horo82[[#This Row],[Jour]],Horo82[[#This Row],[GPF]]) / Horo82[[#This Row],[hrs]],"") -> 0.21428571 | M28: =IF("GPF"=Horo82[[#This Row],[Tâche]],Horo82[[#This Row],[Durée]],"") -> 1.5 | N28: =IF("RI"=Horo82[[#This Row],[Tâche]],Horo82[[#This Row],[Durée]],"") | O28: =IF("GB"=Horo82[[#This Row],[Tâche]],Horo82[[#This Row],[Durée]],"") | P28: =IF("RD"=Horo82[[#This Row],[Tâche]],Horo82[[#This Row],[Durée]],"") | Q28: =IF("FG"=Horo82[[#This Row],[Tâche]],Horo82[[#This Row],[Durée]],"") | R28: =IF("CONGÉ"=Horo82[[#This Row],[Tâche]],Horo82[[#This Row],[Durée]],"") | S28: =IF("PS"=Horo82[[#This Row],[Tâche]],Horo82[[#This Row],[Durée]],"") | T28: =IF("TD"=Horo82[[#This Row],[Tâche]],Horo82[[#This Row],[Durée]],"") | U28: =IF("N/C"=Horo82[[#This Row],[Tâche]],Horo82[[#This Row],[Durée]],"") | W28: =IF(Horo82[[#This Row],[O]]="o",Horo82[[#This Row],[Durée]],".") -> . | X28: =IF(Horo82[[#This Row],[Début]]=0,"",Horo82[[#This Row],[Fin]]-Horo82[[#This Row],[Début]]) -> 0.0625
A29: o | B29: =IF(Horo82[[#This Row],[Jour]]="Lundi",$C$1+1, IF(Horo82[[#This Row],[Jour]]="Mardi",$C$1+2, IF(Horo82[[#This Row],[Jour]]="Mercredi",$C$1+3, IF(Horo82[[#This Row],[Jour]]="Jeudi",$C$1+4, IF(Horo82[[#This Row],[Jour]]="Vendredi",$C$1+5, IF(Horo82[[#This Row],[Jour]]="Samedi",$C$1+6, IF(Horo82[[#This Row],[Jour]]="Dimanche",$C$1, ))))))) -> 44464 | C29: Vendredi | D29: 0.39583333 | E29: 0.4375 | F29: COATICOOK | G29: GPF | H29: Suivi de projet | I29: Avec David et Francine | J29: =IF(Horo82[[#This Row],[Début]]=0,"",(Horo82[[#This Row],[Durée (60)2]]-INT(Horo82[[#This Row],[Durée (60)2]]))*24) -> 1 | K29: =SUMIF(Horo82[Jour],C29,Horo82[Durée]) -> 7 | L29: =IFERROR(SUMIF(Horo82[[#This Row],[Jour]],Horo82[[#This Row],[Jour]],Horo82[[#This Row],[GPF]]) / Horo82[[#This Row],[hrs]],"") -> 0.14285714 | M29: =IF("GPF"=Horo82[[#This Row],[Tâche]],Horo82[[#This Row],[Durée]],"") -> 1 | N29: =IF("RI"=Horo82[[#This Row],[Tâche]],Horo82[[#This Row],[Durée]],"") | O29: =IF("GB"=Horo82[[#This Row],[Tâche]],Horo82[[#This Row],[Durée]],"") | P29: =IF("RD"=Horo82[[#This Row],[Tâche]],Horo82[[#This Row],[Durée]],"") | Q29: =IF("FG"=Horo82[[#This Row],[Tâche]],Horo82[[#This Row],[Durée]],"") | R29: =IF("CONGÉ"=Horo82[[#This Row],[Tâche]],Horo82[[#This Row],[Durée]],"") | S29: =IF("PS"=Horo82[[#This Row],[Tâche]],Horo82[[#This Row],[Durée]],"") | T29: =IF("TD"=Horo82[[#This Row],[Tâche]],Horo82[[#This Row],[Durée]],"") | U29: =IF("N/C"=Horo82[[#This Row],[Tâche]],Horo82[[#This Row],[Durée]],"") | W29: =IF(Horo82[[#This Row],[O]]="o",Horo82[[#This Row],[Durée]],".") -> 1 | X29: =IF(Horo82[[#This Row],[Début]]=0,"",Horo82[[#This Row],[Fin]]-Horo82[[#This Row],[Début]]) -> 0.041666667
A30: . | B30: =IF(Horo82[[#This Row],[Jour]]="Lundi",$C$1+1, IF(Horo82[[#This Row],[Jour]]="Mardi",$C$1+2, IF(Horo82[[#This Row],[Jour]]="Mercredi",$C$1+3, IF(Horo82[[#This Row],[Jour]]="Jeudi",$C$1+4, IF(Horo82[[#This Row],[Jour]]="Vendredi",$C$1+5, IF(Horo82[[#This Row],[Jour]]="Samedi",$C$1+6, IF(Horo82[[#This Row],[Jour]]="Dimanche",$C$1, ))))))) -> 44464 | C30: Vendredi | D30: 0.4375 | E30: 0.45833333 | F30: RBF | G30: FG | H30: Étiquette client | J30: =IF(Horo82[[#This Row],[Début]]=0,"",(Horo82[[#This Row],[Durée (60)2]]-INT(Horo82[[#This Row],[Durée (60)2]]))*24) -> 0.5 | K30: =SUMIF(Horo82[Jour],C30,Horo82[Durée]) -> 7 | L30: =IFERROR(SUMIF(Horo82[[#This Row],[Jour]],Horo82[[#This Row],[Jour]],Horo82[[#This Row],[GPF]]) / Horo82[[#This Row],[hrs]],"") -> 0 | M30: =IF("GPF"=Horo82[[#This Row],[Tâche]],Horo82[[#This Row],[Durée]],"") | N30: =IF("RI"=Horo82[[#This Row],[Tâche]],Horo82[[#This Row],[Durée]],"") | O30: =IF("GB"=Horo82[[#This Row],[Tâche]],Horo82[[#This Row],[Durée]],"") | P30: =IF("RD"=Horo82[[#This Row],[Tâche]],Horo82[[#This Row],[Durée]],"") | Q30: =IF("FG"=Horo82[[#This Row],[Tâche]],Horo82[[#This Row],[Durée]],"") -> 0.5 | R30: =IF("CONGÉ"=Horo82[[#This Row],[Tâche]],Horo82[[#This Row],[Durée]],"") | S30: =IF("PS"=Horo82[[#This Row],[Tâche]],Horo82[[#This Row],[Durée]],"") | T30: =IF("TD"=Horo82[[#This Row],[Tâche]],Horo82[[#This Row],[Durée]],"") | U30: =IF("N/C"=Horo82[[#This Row],[Tâche]],Horo82[[#This Row],[Durée]],"") | W30: =IF(Horo82[[#This Row],[O]]="o",Horo82[[#This Row],[Durée]],".") -> . | X30: =IF(Horo82[[#This Row],[Début]]=0,"",Horo82[[#This Row],[Fin]]-Horo82[[#This Row],[Début]]) -> 0.020833333
A31: o | B31: =IF(Horo82[[#This Row],[Jour]]="Lundi",$C$1+1, IF(Horo82[[#This Row],[Jour]]="Mardi",$C$1+2, IF(Horo82[[#This Row],[Jour]]="Mercredi",$C$1+3, IF(Horo82[[#This Row],[Jour]]="Jeudi",$C$1+4, IF(Horo82[[#This Row],[Jour]]="Vendredi",$C$1+5, IF(Horo82[[#This Row],[Jour]]="Samedi",$C$1+6, IF(Horo82[[#This Row],[Jour]]="Dimanche",$C$1, ))))))) -> 44464 | C31: Vendredi | D31: 0.66666667 | E31: 0.77083333 | F31: RBF | G31: RD | H31: Étiquette client | J31: =IF(Horo82[[#This Row],[Début]]=0,"",(Horo82[[#This Row],[Durée (60)2]]-INT(Horo82[[#This Row],[Durée (60)2]]))*24) -> 2.5 | K31: =SUMIF(Horo82[Jour],C31,Horo82[Durée]) -> 7 | L31: =IFERROR(SUMIF(Horo82[[#This Row],[Jour]],Horo82[[#This Row],[Jour]],Horo82[[#This Row],[GPF]]) / Horo82[[#This Row],[hrs]],"") -> 0 | M31: =IF("GPF"=Horo82[[#This Row],[Tâche]],Horo82[[#This Row],[Durée]],"") | N31: =IF("RI"=Horo82[[#This Row],[Tâche]],Horo82[[#This Row],[Durée]],"") | O31: =IF("GB"=Horo82[[#This Row],[Tâche]],Horo82[[#This Row],[Durée]],"") | P31: =IF("RD"=Horo82[[#This Row],[Tâche]],Horo82[[#This Row],[Durée]],"") -> 2.5 | Q31: =IF("FG"=Horo82[[#This Row],[Tâche]],Horo82[[#This Row],[Durée]],"") | R31: =IF("CONGÉ"=Horo82[[#This Row],[Tâche]],Horo82[[#This Row],[Durée]],"") | S31: =IF("PS"=Horo82[[#This Row],[Tâche]],Horo82[[#This Row],[Durée]],"") | T31: =IF("TD"=Horo82[[#This Row],[Tâche]],Horo82[[#This Row],[Durée]],"") | U31: =IF("N/C"=Horo82[[#This Row],[Tâche]],Horo82[[#This Row],[Durée]],"") | W31: =IF(Horo82[[#This Row],[O]]="o",Horo82[[#This Row],[Durée]],".") -> 2.5 | X31: =IF(Horo82[[#This Row],[Début]]=0,"",Horo82[[#This Row],[Fin]]-Horo82[[#This Row],[Début]]) -> 0.10416667
A32: o | B32: =IF(Horo82[[#This Row],[Jour]]="Lundi",$C$1+1, IF(Horo82[[#This Row],[Jour]]="Mardi",$C$1+2, IF(Horo82[[#This Row],[Jour]]="Mercredi",$C$1+3, IF(Horo82[[#This Row],[Jour]]="Jeudi",$C$1+4, IF(Horo82[[#This Row],[Jour]]="Vendredi",$C$1+5, IF(Horo82[[#This Row],[Jour]]="Samedi",$C$1+6, IF(Horo82[[#This Row],[Jour]]="Dimanche",$C$1, ))))))) -> 44464 | C32: Vendredi | D32: 0.77083333 | E32: 0.8125 | F32: FORGESTIK | G32: GB | J32: =IF(Horo82[[#This Row],[Début]]=0,"",(Horo82[[#This Row],[Durée (60)2]]-INT(Horo82[[#This Row],[Durée (60)2]]))*24) -> 1 | K32: =SUMIF(Horo82[Jour],C32,Horo82[Durée]) -> 7 | L32: =IFERROR(SUMIF(Horo82[[#This Row],[Jour]],Horo82[[#This Row],[Jour]],Horo82[[#This Row],[GPF]]) / Horo82[[#This Row],[hrs]],"") -> 0 | M32: =IF("GPF"=Horo82[[#This Row],[Tâche]],Horo82[[#This Row],[Durée]],"") | N32: =IF("RI"=Horo82[[#This Row],[Tâche]],Horo82[[#This Row],[Durée]],"") | O32: =IF("GB"=Horo82[[#This Row],[Tâche]],Horo82[[#This Row],[Durée]],"") -> 1 | P32: =IF("RD"=Horo82[[#This Row],[Tâche]],Horo82[[#This Row],[Durée]],"") | Q32: =IF("FG"=Horo82[[#This Row],[Tâche]],Horo82[[#This Row],[Durée]],"") | R32: =IF("CONGÉ"=Horo82[[#This Row],[Tâche]],Horo82[[#This Row],[Durée]],"") | S32: =IF("PS"=Horo82[[#This Row],[Tâche]],Horo82[[#This Row],[Durée]],"") | T32: =IF("TD"=Horo82[[#This Row],[Tâche]],Horo82[[#This Row],[Durée]],"") | U32: =IF("N/C"=Horo82[[#This Row],[Tâche]],Horo82[[#This Row],[Durée]],"") | W32: =IF(Horo82[[#This Row],[O]]="o",Horo82[[#This Row],[Durée]],".") -> 1 | X32: =IF(Horo82[[#This Row],[Début]]=0,"",Horo82[[#This Row],[Fin]]-Horo82[[#This Row],[Début]]) -> 0.041666667
A33: . | B33: =IF(Horo82[[#This Row],[Jour]]="Lundi",$C$1+1, IF(Horo82[[#This Row],[Jour]]="Mardi",$C$1+2, IF(Horo82[[#This Row],[Jour]]="Mercredi",$C$1+3, IF(Horo82[[#This Row],[Jour]]="Jeudi",$C$1+4, IF(Horo82[[#This Row],[Jour]]="Vendredi",$C$1+5, IF(Horo82[[#This Row],[Jour]]="Samedi",$C$1+6, IF(Horo82[[#This Row],[Jour]]="Dimanche",$C$1, ))))))) -> 0 | F33: FORGESTIK | G33: N/C | H33: . | J33: =IF(Horo82[[#This Row],[Début]]=0,"",(Horo82[[#This Row],[Durée (60)2]]-INT(Horo82[[#This Row],[Durée (60)2]]))*24) | K33: =SUMIF(Horo82[Jour],C33,Horo82[Durée]) -> 0 | L33: =IFERROR(SUMIF(Horo82[[#This Row],[Jour]],Horo82[[#This Row],[Jour]],Horo82[[#This Row],[GPF]]) / Horo82[[#This Row],[hrs]],"") | M33: =IF("GPF"=Horo82[[#This Row],[Tâche]],Horo82[[#This Row],[Durée]],"") | N33: =IF("RI"=Horo82[[#This Row],[Tâche]],Horo82[[#This Row],[Durée]],"") | O33: =IF("GB"=Horo82[[#This Row],[Tâche]],Horo82[[#This Row],[Durée]],"") | P33: =IF("RD"=Horo82[[#This Row],[Tâche]],Horo82[[#This Row],[Durée]],"") | Q33: =IF("FG"=Horo82[[#This Row],[Tâche]],Horo82[[#This Row],[Durée]],"") | R33: =IF("CONGÉ"=Horo82[[#This Row],[Tâche]],Horo82[[#This Row],[Durée]],"") | S33: =IF("PS"=Horo82[[#This Row],[Tâche]],Horo82[[#This Row],[Durée]],"") | T33: =IF("TD"=Horo82[[#This Row],[Tâche]],Horo82[[#This Row],[Durée]],"") | U33: =IF("N/C"=Horo82[[#This Row],[Tâche]],Horo82[[#This Row],[Durée]],"") | W33: =IF(Horo82[[#This Row],[O]]="o",Horo82[[#This Row],[Durée]],".") -> . | X33: =IF(Horo82[[#This Row],[Début]]=0,"",Horo82[[#This Row],[Fin]]-Horo82[[#This Row],[Début]])
A40: % | B40: Clients | C40: Total
A41: =IF((SUMIF(Horo82[Client],B41,Horo82[Durée]) / Total)=0,"",(SUMIF(Horo82[Client],B41,Horo82[Durée]) / Total)) -> 0.2987013 | B41: FORGESTIK | C41: =IF(SUMIF(Horo82[Client],B41,Horo82[Durée])=0,"",SUMIF(Horo82[Client],B41,Horo82[Durée])) -> 11.5
A42: =IF((SUMIF(Horo82[Client],B42,Horo82[Durée]) / Total)=0,"",(SUMIF(Horo82[Client],B42,Horo82[Durée]) / Total)) | B42: AGENCE GRAVEL | C42: =IF(SUMIF(Horo82[Client],B42,Horo82[Durée])=0,"",SUMIF(Horo82[Client],B42,Horo82[Durée]))
A43: =IF((SUMIF(Horo82[Client],B43,Horo82[Durée]) / Total)=0,"",(SUMIF(Horo82[Client],B43,Horo82[Durée]) / Total)) | B43: ZITTA | C43: =IF(SUMIF(Horo82[Client],B43,Horo82[Durée])=0,"",SUMIF(Horo82[Client],B43,Horo82[Durée]))
A44: =IF((SUMIF(Horo82[Client],B44,Horo82[Durée]) / Total)=0,"",(SUMIF(Horo82[Client],B44,Horo82[Durée]) / Total)) | B44: EURODIB | C44: =IF(SUMIF(Horo82[Client],B44,Horo82[Durée])=0,"",SUMIF(Horo82[Client],B44,Horo82[Durée]))
A45: =IF((SUMIF(Horo82[Client],B45,Horo82[Durée]) / Total)=0,"",(SUMIF(Horo82[Client],B45,Horo82[Durée]) / Total)) | B45: AREVA | C45: =IF(SUMIF(Horo82[Client],B45,Horo82[Durée])=0,"",SUMIF(Horo82[Client],B45,Horo82[Durée]))
A46: =IF((SUMIF(Horo82[Client],B46,Horo82[Durée]) / Total)=0,"",(SUMIF(Horo82[Client],B46,Horo82[Durée]) / Total)) | B46: ATLANTIS POMPE | C46: =IF(SUMIF(Horo82[Client],B46,Horo82[Durée])=0,"",SUMIF(Horo82[Client],B46,Horo82[Durée]))
A47: =IF((SUMIF(Horo82[Client],B47,Horo82[Durée]) / Total)=0,"",(SUMIF(Horo82[Client],B47,Horo82[Durée]) / Total)) | B47: BTRUST | C47: =IF(SUMIF(Horo82[Client],B47,Horo82[Durée])=0,"",SUMIF(Horo82[Client],B47,Horo82[Durée]))
A48: =IF((SUMIF(Horo82[Client],B48,Horo82[Durée]) / Total)=0,"",(SUMIF(Horo82[Client],B48,Horo82[Durée]) / Total)) | B48: CARNOT | C48: =IF(SUMIF(Horo82[Client],B48,Horo82[Durée])=0,"",SUMIF(Horo82[Client],B48,Horo82[Durée]))
A49: =IF((SUMIF(Horo82[Client],B49,Horo82[Durée]) / Total)=0,"",(SUMIF(Horo82[Client],B49,Horo82[Durée]) / Total)) | B49: CÉRAGRÈS | C49: =IF(SUMIF(Horo82[Client],B49,Horo82[Durée])=0,"",SUMIF(Horo82[Client],B49,Horo82[Durée]))
A50: =IF((SUMIF(Horo82[Client],B50,Horo82[Durée]) / Total)=0,"",(SUMIF(Horo82[Client],B50,Horo82[Durée]) / Total)) -> 0.038961039 | B50: COATICOOK | C50: =IF(SUMIF(Horo82[Client],B50,Horo82[Durée])=0,"",SUMIF(Horo82[Client],B50,Horo82[Durée])) -> 1.5
A51: =IF((SUMIF(Horo82[Client],B51,Horo82[Durée]) / Total)=0,"",(SUMIF(Horo82[Client],B51,Horo82[Durée]) / Total)) | B51: DANFREIGHT | C51: =IF(SUMIF(Horo82[Client],B51,Horo82[Durée])=0,"",SUMIF(Horo82[Client],B51,Horo82[Durée]))
A52: =IF((SUMIF(Horo82[Client],B52,Horo82[Durée]) / Total)=0,"",(SUMIF(Horo82[Client],B52,Horo82[Durée]) / Total)) | B52: DISSAN | C52: =IF(SUMIF(Horo82[Client],B52,Horo82[Durée])=0,"",SUMIF(Horo82[Client],B52,Horo82[Durée]))
... A68: =IF((SUMIF(Horo82[Client],B68,Horo82[Durée]) / Total)=0,"",(SUMIF(Horo82[Client],B68,Horo82[Durée]) / Total)) | B68: ADC | C68: =IF(SUMIF(Horo82[Client],B68,Horo82[Durée])=0,"",SUMIF(Horo82[Client],B68,Horo82[Durée]))

Sheet Data
A1: Année | B1: NumérosSemaine | C1: Jours | D1: Tâches | E1: Clients | F1: Description
A2: 44193 | B2: 1 | C2: Lundi | D2: CONGÉ | F2: . | H2: Test & Doc. | I2: FG /Analyse et réingienérie | J2: 44193
A3: 44200 | B3: 2 | C3: Mardi | D3: FG | E3: ADC | F3: Analyse fonctionnelle | H3: Installation PMX | I3: GB /Gestion de projet client | J3: =J2+7 -> 44200
A4: 44207 | B4: 3 | C4: Mercredi | D4: GB | E4: AGENCE GRAVEL | F4: Appel avec | H4: Configuration PMX | I4: RD /Revue de Processus | J4: =J3+7 -> 44207
A5: 44214 | B5: 4 | C5: Jeudi | D5: GPF | E5: AREVA | F5: Autotask | H5: Formation Client | I5: RI / Analyse, revue et planification de projet | J5: =J4+7 -> 44214
A6: 44221 | B6: 5 | C6: Vendredi | D6: PS | E6: ATLANTIS POMPE | F6: Billet | I6: TD / Temps de déplacement | J6: =J5+7 -> 44221
A7: 44228 | B7: 6 | C7: Samedi | D7: RD | E7: BORÉALE | F7: Courriel | H7: Formation SAP | I7: PS / Preuve de concept | J7: =J6+7 -> 44228
A8: 44235 | B8: 7 | C8: Dimanche | D8: RI | E8: BTRUST | F8: Déplacement chez le client | H8: Formation PMX | J8: =J7+7 -> 44235
A9: 44242 | B9: 8 | D9: TD | E9: CARNOT | F9: Développement | H9: Formation Générale | J9: =J8+7 -> 44242
A10: 44249 | B10: 9 | D10: N/C | E10: CÉRAGRÈS | F10: EDI | H10: Shadow | J10: =J9+7 -> 44249
A11: 44256 | B11: 10 | E11: COATICOOK | F11: Étiquette | J11: =J10+7 -> 44256
A12: 44263 | B12: 11 | E12: DANFREIGHT | F12: Étiquette client | J12: =J11+7 -> 44263
A13: 44270 | B13: 12 | E13: DISSAN | F13: Étiquette EDI | J13: =J12+7 -> 44270
A14: 44277 | B14: 13 | E14: DUER | F14: Fichiers d'importation | J14: =J13+7 -> 44277
A15: 44284 | B15: 14 | E15: EURODIB | F15: Formation | J15: =J14+7 -> 44284
A16: 44291 | B16: 15 | E16: FORGESTIK | F16: Formation C# | J16: =J15+7 -> 44291
A17: 44298 | B17: 16 | E17: GPR - BELLEVILLE | F17: Formation PMX | J17: =J16+7 -> 44298
A18: 44305 | B18: 17 | E18: HRS | F18: Formation PMX - Module | J18: =J17+7 -> 44305
A19: 44312 | B19: 18 | E19: HYPERTEC | F19: Formation SAP -PMX | J19: =J18+7 -> 44312
A20: 44319 | B20: 19 | E20: iSpice | F20: Gestion de fichiers | J20: =J19+7 -> 44319
A21: 44326 | B21: 20 | E21: KATHELEEN | F21: Importation | J21: =J20+7 -> 44326
A22: 44333 | B22: 21 | E22: MONDOUX | F22: Installation de Produmex | J22: =J21+7 -> 44333
... A31: 44396 | B31: 30 | E31: ZITTA | F31: Révision BluePrint | J31: =J30+7 -> 44396
A32: 44403 | B32: 31 | F32: Révision document de formation | J32: =J31+7 -> 44403
A33: 44410 | B33: 32 | F33: Suivi de projet | J33: =J32+7 -> 44410
A34: 44417 | B34: 33 | F34: Suivi projet post GoLive | J34: =J33+7 -> 44417
A35: 44424 | B35: 34 | F35: Support | J35: =J34+7 -> 44424
A36: 44431 | B36: 35 | F36: Support au test | J36: =J35+7 -> 44431
A37: 44438 | B37: 36 | F37: Temps repris | J37: =J36+7 -> 44438
A38: 44445 | B38: 37 | F38: Test | J38: =J37+7 -> 44445
A39: 44452 | B39: 38 | F39: Tests unitaires et documentation guide | J39: =J38+7 -> 44452
A40: 44459 | B40: 39 | F40: Vacances | J40: =J39+7 -> 44459
A41: 44466 | B41: 40 | J41: =J40+7 -> 44466
A42: 44473 | B42: 41 | J42: =J41+7 -> 44473
A43: 44480 | B43: 42 | J43: =J42+7 -> 44480
A44: 44487 | B44: 43 | J44: =J43+7 -> 44487
A45: 44494 | B45: 44 | J45: =J44+7 -> 44494
A46: 44501 | B46: 45 | J46: =J45+7 -> 44501
A47: 44508 | B47: 46 | J47: =J46+7 -> 44508
A48: 44515 | B48: 47 | J48: =J47+7 -> 44515
A49: 44522 | B49: 48 | J49: =J48+7 -> 44522
A50: 44529 | B50: 49 | J50: =J49+7 -> 44529
A51: 44536 | B51: 50 | J51: =J50+7 -> 44536
A52: 44543 | B52: 51 | J52: =J51+7 -> 44543
... A54: 44557 | B54: 0 | J54: =J53+7 -> 44557
J55: =J54+7 -> 44564
J56: =J55+7 -> 44571
J57: =J56+7 -> 44578
J58: =J57+7 -> 44585
J59: =J58+7 -> 44592
J60: =J59+7 -> 44599
J61: =J60+7 -> 44606
J62: =J61+7 -> 44613
J63: =J62+7 -> 44620
J64: =J63+7 -> 44627
J65: =J64+7 -> 44634
J66: =J65+7 -> 44641
... J106: =J105+7 -> 44921

Sheet Semaine 14-09-2025
B1: ="Semaine du :" -> Semaine du : | C1: 44452 | D1: ="( "&AVERAGE($E$2:$I$2)&" )" -> ( 8 ) | E1: =IFERROR("Lun.: " & TEXT($Y$2,"00%"),"Lun.: 0%") -> Lun.: 18% | F1: =IFERROR("Mar.: " & TEXT($Z$2,"00%"),"Mar.: 0%") -> Mar.: 40% | G1: =IFERROR("Mer.: " & TEXT($AA$2,"00%"),"Mer.: 0%") -> Mer.: 64% | H1: =IFERROR("Jeu.: " & TEXT($AB$2,"00%"),"Jeu.: 0%") -> Jeu.: 46% | I1: =IFERROR("Ven.: " & TEXT($AC$2,"00%"),"Ven.: 0%") -> Ven.: 00% | J1: =IFERROR("S.: " & TEXT($AD$2,"00%"),"S.: 0%") -> S.: 00% | K1: =IFERROR("D.: " & TEXT($AE$2,"00%"), "D.: 0%") -> D.: 00% | M1: =M2/Total -> 0.35714286 | N1: =N2/$C$2 -> 0.01875 | O1: =O2/$C$2 -> 0.1125 | P1: =P2/$C$2 -> 0.43125 | Q1: =Q2/$C$2 -> 0 | R1: =R2/$C$2 -> 0 | S1: =S2/$C$2 -> 0 | T1: =T2/$C$2 -> 0.05625 | U1: =U2/$C$2 -> 0.0375 | X1: =SUM(#REF!) -> #REF! | Y1: Lundi | Z1: Mardi | AA1: Mercredi | AB1: Jeudi | AC1: Vendredi | AD1: Samedi | AE1: Dimanche
B2: =X2 -> 0.40397351 | C2: =SUM(Horo82111[Durée]) -> 40 | D2: =ROUND(SUM(Horo82111[T]),2) & " / " & ROUND($C$2-SUM(Horo82111[T]),2) -> 40 / 0 | E2: =SUMIF(Horo82111[Jour],"Lundi",Horo82111[Durée]) -> 8.5 | F2: =SUMIF(Horo82111[Jour],"Mardi",Horo82111[Durée]) -> 8.75 | G2: =SUMIF(Horo82111[Jour],"Mercredi",Horo82111[Durée]) -> 7 | H2: =SUMIF(Horo82111[Jour],"Jeudi",Horo82111[Durée]) -> 9.25 | I2: =SUMIF(Horo82111[Jour],"Vendredi",Horo82111[Durée]) -> 6.5 | J2: =SUMIF(Horo82111[Jour],"Samedi",Horo82111[Durée]) -> 0 | K2: =SUMIF(Horo82111[Jour],"Dimanche",Horo82111[Durée]) -> 0 | M2: =SUM(Horo82111[GPF]) -> 13.75 | N2: =SUM(Horo82111[RI]) -> 0.75 | O2: =SUM(Horo82111[GB]) -> 4.5 | P2: =SUM(Horo82111[RD]) -> 17.25 | Q2: =SUM(Horo82111[FG]) -> 0 | R2: =SUM(Horo82111[CONGÉ]) -> 0 | S2: =SUM(Horo82111[PS]) -> 0 | T2: =SUM(Horo82111[TD]) -> 2.25 | U2: =SUM(Horo82111[N/C]) -> 1.5 | V2: =(C2-(SUM(N2:T2))) -> 15.25 | W2: =C2-(R2+S2+T2) -> 37.75 | X2: =V2/W2 -> 0.40397351 | Y2: =SUMIF(Horo82111[Jour],"Lundi",Horo82111[GPF]) / $E$2 -> 0.17647059 | Z2: =SUMIF(Horo82111[Jour],"Mardi",Horo82111[GPF]) / $F$2 -> 0.4 | AA2: =SUMIF(Horo82111[Jour],"Mercredi",Horo82111[GPF]) / $G$2 -> 0.64285714 | AB2: =SUMIF(Horo82111[Jour],"Jeudi",Horo82111[GPF]) / $H$2 -> 0.45945946 | AC2: =SUMIF(Horo82111[Jour],"Vendredi",Horo82111[GPF]) / $I$2 -> 0 | AD2: =IFERROR(SUMIF(Horo82111[Jour],"Samedi",Horo82111[GPF]) / $J$2,0) -> 0 | AE2: =IFERROR(SUMIF(Horo82111[Jour],"Dimanche",Horo82111[GPF]) / $K$2,0) -> 0
A3: O | B3: Date | C3: Jour | D3: Début | E3: Fin | F3: Client | G3: Tâche | H3: Description | I3: Description 2 | J3: Durée | K3: hrs | L3: % | M3: GPF | N3: RI | O3: GB | P3: RD | Q3: FG | R3: CONGÉ | S3: PS | T3: TD | U3: N/C | V3: W | W3: T | X3: Durée (60)2
A4: o | B4: =IF(Horo82111[[#This Row],[Jour]]="Lundi",$C$1+1, IF(Horo82111[[#This Row],[Jour]]="Mardi",$C$1+2, IF(Horo82111[[#This Row],[Jour]]="Mercredi",$C$1+3, IF(Horo82111[[#This Row],[Jour]]="Jeudi",$C$1+4, IF(Horo82111[[#This Row],[Jour]]="Vendredi",$C$1+5, IF(Horo82111[[#This Row],[Jour]]="Samedi",$C$1+6, IF(Horo82111[[#This Row],[Jour]]="Dimanche",$C$1, ))))))) -> 44453 | C4: Lundi | D4: 0.30208333 | E4: 0.36458333 | F4: FORGESTIK | G4: GB | H4: . | J4: =IF(Horo82111[[#This Row],[Début]]=0,"",(Horo82111[[#This Row],[Durée (60)2]]-INT(Horo82111[[#This Row],[Durée (60)2]]))*24) -> 1.5 | K4: =SUMIF(Horo82111[Jour],C4,Horo82111[Durée]) -> 8.5 | L4: =IFERROR(SUMIF(Horo82111[[#This Row],[Jour]],Horo82111[[#This Row],[Jour]],Horo82111[[#This Row],[GPF]]) / Horo82111[[#This Row],[hrs]],"") -> 0 | M4: =IF("GPF"=Horo82111[[#This Row],[Tâche]],Horo82111[[#This Row],[Durée]],"") | N4: =IF("RI"=Horo82111[[#This Row],[Tâche]],Horo82111[[#This Row],[Durée]],"") | O4: =IF("GB"=Horo82111[[#This Row],[Tâche]],Horo82111[[#This Row],[Durée]],"") -> 1.5 | P4: =IF("RD"=Horo82111[[#This Row],[Tâche]],Horo82111[[#This Row],[Durée]],"") | Q4: =IF("FG"=Horo82111[[#This Row],[Tâche]],Horo82111[[#This Row],[Durée]],"") | R4: =IF("CONGÉ"=Horo82111[[#This Row],[Tâche]],Horo82111[[#This Row],[Durée]],"") | S4: =IF("PS"=Horo82111[[#This Row],[Tâche]],Horo82111[[#This Row],[Durée]],"") | T4: =IF("TD"=Horo82111[[#This Row],[Tâche]],Horo82111[[#This Row],[Durée]],"") | U4: =IF("N/C"=Horo82111[[#This Row],[Tâche]],Horo82111[[#This Row],[Durée]],"") | W4: =IF(Horo82111[[#This Row],[O]]="o",Horo82111[[#This Row],[Durée]],".") -> 1.5 | X4: =IF(Horo82111[[#This Row],[Début]]=0,"",Horo82111[[#This Row],[Fin]]-Horo82111[[#This Row],[Début]]) -> 0.0625
A5: o | B5: =IF(Horo82111[[#This Row],[Jour]]="Lundi",$C$1+1, IF(Horo82111[[#This Row],[Jour]]="Mardi",$C$1+2, IF(Horo82111[[#This Row],[Jour]]="Mercredi",$C$1+3, IF(Horo82111[[#This Row],[Jour]]="Jeudi",$C$1+4, IF(Horo82111[[#This Row],[Jour]]="Vendredi",$C$1+5, IF(Horo82111[[#This Row],[Jour]]="Samedi",$C$1+6, IF(Horo82111[[#This Row],[Jour]]="Dimanche",$C$1, ))))))) -> 44453 | C5: Lundi | D5: 0.36458333 | E5: 0.38541667 | F5: FORGESTIK | G5: RI | H5: Réunion OPS | J5: =IF(Horo82111[[#This Row],[Début]]=0,"",(Horo82111[[#This Row],[Durée (60)2]]-INT(Horo82111[[#This Row],[Durée (60)2]]))*24) -> 0.5 | K5: =SUMIF(Horo82111[Jour],C5,Horo82111[Durée]) -> 8.5 | L5: =IFERROR(SUMIF(Horo82111[[#This Row],[Jour]],Horo82111[[#This Row],[Jour]],Horo82111[[#This Row],[GPF]]) / Horo82111[[#This Row],[hrs]],"") -> 0 | M5: =IF("GPF"=Horo82111[[#This Row],[Tâche]],Horo82111[[#This Row],[Durée]],"") | N5: =IF("RI"=Horo82111[[#This Row],[Tâche]],Horo82111[[#This Row],[Durée]],"") -> 0.5 | O5: =IF("GB"=Horo82111[[#This Row],[Tâche]],Horo82111[[#This Row],[Durée]],"") | P5: =IF("RD"=Horo82111[[#This Row],[Tâche]],Horo82111[[#This Row],[Durée]],"") | Q5: =IF("FG"=Horo82111[[#This Row],[Tâche]],Horo82111[[#This Row],[Durée]],"") | R5: =IF("CONGÉ"=Horo82111[[#This Row],[Tâche]],Horo82111[[#This Row],[Durée]],"") | S5: =IF("PS"=Horo82111[[#This Row],[Tâche]],Horo82111[[#This Row],[Durée]],"") | T5: =IF("TD"=Horo82111[[#This Row],[Tâche]],Horo82111[[#This Row],[Durée]],"") | U5: =IF("N/C"=Horo82111[[#This Row],[Tâche]],Horo82111[[#This Row],[Durée]],"") | W5: =IF(Horo82111[[#This Row],[O]]="o",Horo82111[[#This Row],[Durée]],".") -> 0.5 | X5: =IF(Horo82111[[#This Row],[Début]]=0,"",Horo82111[[#This Row],[Fin]]-Horo82111[[#This Row],[Début]]) -> 0.020833333
A6: o | B6: =IF(Horo82111[[#This Row],[Jour]]="Lundi",$C$1+1, IF(Horo82111[[#This Row],[Jour]]="Mardi",$C$1+2, IF(Horo82111[[#This Row],[Jour]]="Mercredi",$C$1+3, IF(Horo82111[[#This Row],[Jour]]="Jeudi",$C$1+4, IF(Horo82111[[#This Row],[Jour]]="Vendredi",$C$1+5, IF(Horo82111[[#This Row],[Jour]]="Samedi",$C$1+6, IF(Horo82111[[#This Row],[Jour]]="Dimanche",$C$1, ))))))) -> 44453 | C6: Lundi | D6: 0.38541667 | E6: 0.39583333 | F6: FORGESTIK | G6: GB | H6: . | J6: =IF(Horo82111[[#This Row],[Début]]=0,"",(Horo82111[[#This Row],[Durée (60)2]]-INT(Horo82111[[#This Row],[Durée (60)2]]))*24) -> 0.25 | K6: =SUMIF(Horo82111[Jour],C6,Horo82111[Durée]) -> 8.5 | L6: =IFERROR(SUMIF(Horo82111[[#This Row],[Jour]],Horo82111[[#This Row],[Jour]],Horo82111[[#This Row],[GPF]]) / Horo82111[[#This Row],[hrs]],"") -> 0 | M6: =IF("GPF"=Horo82111[[#This Row],[Tâche]],Horo82111[[#This Row],[Durée]],"") | N6: =IF("RI"=Horo82111[[#This Row],[Tâche]],Horo82111[[#This Row],[Durée]],"") | O6: =IF("GB"=Horo82111[[#This Row],[Tâche]],Horo82111[[#This Row],[Durée]],"") -> 0.25 | P6: =IF("RD"=Horo82111[[#This Row],[Tâche]],Horo82111[[#This Row],[Durée]],"") | Q6: =IF("FG"=Horo82111[[#This Row],[Tâche]],Horo82111[[#This Row],[Durée]],"") | R6: =IF("CONGÉ"=Horo82111[[#This Row],[Tâche]],Horo82111[[#This Row],[Durée]],"") | S6: =IF("PS"=Horo82111[[#This Row],[Tâche]],Horo82111[[#This Row],[Durée]],"") | T6: =IF("TD"=Horo82111[[#This Row],[Tâche]],Horo82111[[#This Row],[Durée]],"") | U6: =IF("N/C"=Horo82111[[#This Row],[Tâche]],Horo82111[[#This Row],[Durée]],"") | W6: =IF(Horo82111[[#This Row],[O]]="o",Horo82111[[#This Row],[Durée]],".") -> 0.25 | X6: =IF(Horo82111[[#This Row],[Début]]=0,"",Horo82111[[#This Row],[Fin]]-Horo82111[[#This Row],[Début]]) -> 0.010416667
A7: o | B7: =IF(Horo82111[[#This Row],[Jour]]="Lundi",$C$1+1, IF(Horo82111[[#This Row],[Jour]]="Mardi",$C$1+2, IF(Horo82111[[#This Row],[Jour]]="Mercredi",$C$1+3, IF(Horo82111[[#This Row],[Jour]]="Jeudi",$C$1+4, IF(Horo82111[[#This Row],[Jour]]="Vendredi",$C$1+5, IF(Horo82111[[#This Row],[Jour]]="Samedi",$C$1+6, IF(Horo82111[[#This Row],[Jour]]="Dimanche",$C$1, ))))))) -> 44453 | C7: Lundi | D7: 0.39583333 | E7: 0.41666667 | F7: RBF | G7: GPF | H7: Suivi de projet | J7: =IF(Horo82111[[#This Row],[Début]]=0,"",(Horo82111[[#This Row],[Durée (60)2]]-INT(Horo82111[[#This Row],[Durée (60)2]]))*24) -> 0.5 | K7: =SUMIF(Horo82111[Jour],C7,Horo82111[Durée]) -> 8.5 | L7: =IFERROR(SUMIF(Horo82111[[#This Row],[Jour]],Horo82111[[#This Row],[Jour]],Horo82111[[#This Row],[GPF]]) / Horo82111[[#This Row],[hrs]],"") -> 0.058823529 | M7: =IF("GPF"=Horo82111[[#This Row],[Tâche]],Horo82111[[#This Row],[Durée]],"") -> 0.5 | N7: =IF("RI"=Horo82111[[#This Row],[Tâche]],Horo82111[[#This Row],[Durée]],"") | O7: =IF("GB"=Horo82111[[#This Row],[Tâche]],Horo82111[[#This Row],[Durée]],"") | P7: =IF("RD"=Horo82111[[#This Row],[Tâche]],Horo82111[[#This Row],[Durée]],"") | Q7: =IF("FG"=Horo82111[[#This Row],[Tâche]],Horo82111[[#This Row],[Durée]],"") | R7: =IF("CONGÉ"=Horo82111[[#This Row],[Tâche]],Horo82111[[#This Row],[Durée]],"") | S7: =IF("PS"=Horo82111[[#This Row],[Tâche]],Horo82111[[#This Row],[Durée]],"") | T7: =IF("TD"=Horo82111[[#This Row],[Tâche]],Horo82111[[#This Row],[Durée]],"") | U7: =IF("N/C"=Horo82111[[#This Row],[Tâche]],Horo82111[[#This Row],[Durée]],"") | W7: =IF(Horo82111[[#This Row],[O]]="o",Horo82111[[#This Row],[Durée]],".") -> 0.5 | X7: =IF(Horo82111[[#This Row],[Début]]=0,"",Horo82111[[#This Row],[Fin]]-Horo82111[[#This Row],[Début]]) -> 0.020833333
A8: o | B8: =IF(Horo82111[[#This Row],[Jour]]="Lundi",$C$1+1, IF(Horo82111[[#This Row],[Jour]]="Mardi",$C$1+2, IF(Horo82111[[#This Row],[Jour]]="Mercredi",$C$1+3, IF(Horo82111[[#This Row],[Jour]]="Jeudi",$C$1+4, IF(Horo82111[[#This Row],[Jour]]="Vendredi",$C$1+5, IF(Horo82111[[#This Row],[Jour]]="Samedi",$C$1+6, IF(Horo82111[[#This Row],[Jour]]="Dimanche",$C$1, ))))))) -> 44453 | C8: Lundi | D8: 0.41666667 | E8: 0.42708333 | F8: COATICOOK | G8: RI | H8: Suivi de projet | I8: INTERNE Coaticook revue budget projet | J8: =IF(Horo82111[[#This Row],[Début]]=0,"",(Horo82111[[#This Row],[Durée (60)2]]-INT(Horo82111[[#This Row],[Durée (60)2]]))*24) -> 0.25 | K8: =SUMIF(Horo82111[Jour],C8,Horo82111[Durée]) -> 8.5 | L8: =IFERROR(SUMIF(Horo82111[[#This Row],[Jour]],Horo82111[[#This Row],[Jour]],Horo82111[[#This Row],[GPF]]) / Horo82111[[#This Row],[hrs]],"") -> 0 | M8: =IF("GPF"=Horo82111[[#This Row],[Tâche]],Horo82111[[#This Row],[Durée]],"") | N8: =IF("RI"=Horo82111[[#This Row],[Tâche]],Horo82111[[#This Row],[Durée]],"") -> 0.25 | O8: =IF("GB"=Horo82111[[#This Row],[Tâche]],Horo82111[[#This Row],[Durée]],"") | P8: =IF("RD"=Horo82111[[#This Row],[Tâche]],Horo82111[[#This Row],[Durée]],"") | Q8: =IF("FG"=Horo82111[[#This Row],[Tâche]],Horo82111[[#This Row],[Durée]],"") | R8: =IF("CONGÉ"=Horo82111[[#This Row],[Tâche]],Horo82111[[#This Row],[Durée]],"") | S8: =IF("PS"=Horo82111[[#This Row],[Tâche]],Horo82111[[#This Row],[Durée]],"") | T8: =IF("TD"=Horo82111[[#This Row],[Tâche]],Horo82111[[#This Row],[Durée]],"") | U8: =IF("N/C"=Horo82111[[#This Row],[Tâche]],Horo82111[[#This Row],[Durée]],"") | W8: =IF(Horo82111[[#This Row],[O]]="o",Horo82111[[#This Row],[Durée]],".") -> 0.25 | X8: =IF(Horo82111[[#This Row],[Début]]=0,"",Horo82111[[#This Row],[Fin]]-Horo82111[[#This Row],[Début]]) -> 0.010416667
A9: o | B9: =IF(Horo82111[[#This Row],[Jour]]="Lundi",$C$1+1, IF(Horo82111[[#This Row],[Jour]]="Mardi",$C$1+2, IF(Horo82111[[#This Row],[Jour]]="Mercredi",$C$1+3, IF(Horo82111[[#This Row],[Jour]]="Jeudi",$C$1+4, IF(Horo82111[[#This Row],[Jour]]="Vendredi",$C$1+5, IF(Horo82111[[#This Row],[Jour]]="Samedi",$C$1+6, IF(Horo82111[[#This Row],[Jour]]="Dimanche",$C$1, ))))))) -> 44453 | C9: Lundi | D9: 0.42708333 | E9: 0.42708333 | F9: FORGESTIK | G9: N/C | I9: 0.45833333 | J9: =IF(Horo82111[[#This Row],[Début]]=0,"",(Horo82111[[#This Row],[Durée (60)2]]-INT(Horo82111[[#This Row],[Durée (60)2]]))*24) -> 0 | K9: =SUMIF(Horo82111[Jour],C9,Horo82111[Durée]) -> 8.5 | L9: =IFERROR(SUMIF(Horo82111[[#This Row],[Jour]],Horo82111[[#This Row],[Jour]],Horo82111[[#This Row],[GPF]]) / Horo82111[[#This Row],[hrs]],"") -> 0 | M9: =IF("GPF"=Horo82111[[#This Row],[Tâche]],Horo82111[[#This Row],[Durée]],"") | N9: =IF("RI"=Horo82111[[#This Row],[Tâche]],Horo82111[[#This Row],[Durée]],"") | O9: =IF("GB"=Horo82111[[#This Row],[Tâche]],Horo82111[[#This Row],[Durée]],"") | P9: =IF("RD"=Horo82111[[#This Row],[Tâche]],Horo82111[[#This Row],[Durée]],"") | Q9: =IF("FG"=Horo82111[[#This Row],[Tâche]],Horo82111[[#This Row],[Durée]],"") | R9: =IF("CONGÉ"=Horo82111[[#This Row],[Tâche]],Horo82111[[#This Row],[Durée]],"") | S9: =IF("PS"=Horo82111[[#This Row],[Tâche]],Horo82111[[#This Row],[Durée]],"") | T9: =IF("TD"=Horo82111[[#This Row],[Tâche]],Horo82111[[#This Row],[Durée]],"") | U9: =IF("N/C"=Horo82111[[#This Row],[Tâche]],Horo82111[[#This Row],[Durée]],"") -> 0 | W9: =IF(Horo82111[[#This Row],[O]]="o",Horo82111[[#This Row],[Durée]],".") -> 0 | X9: =IF(Horo82111[[#This Row],[Début]]=0,"",Horo82111[[#This Row],[Fin]]-Horo82111[[#This Row],[Début]]) -> 0
A10: o | B10: =IF(Horo82111[[#This Row],[Jour]]="Lundi",$C$1+1, IF(Horo82111[[#This Row],[Jour]]="Mardi",$C$1+2, IF(Horo82111[[#This Row],[Jour]]="Mercredi",$C$1+3, IF(Horo82111[[#This Row],[Jour]]="Jeudi",$C$1+4, IF(Horo82111[[#This Row],[Jour]]="Vendredi",$C$1+5, IF(Horo82111[[#This Row],[Jour]]="Samedi",$C$1+6, IF(Horo82111[[#This Row],[Jour]]="Dimanche",$C$1, ))))))) -> 44453 | C10: Lundi | D10: 0.45833333 | E10: 0.5 | F10: HYPERTEC | G10: GPF | H10: Appel avec | I10: Francine - Étiquettes - Good receipt/Receiving SP | J10: =IF(Horo82111[[#This Row],[Début]]=0,"",(Horo82111[[#This Row],[Durée (60)2]]-INT(Horo82111[[#This Row],[Durée (60)2]]))*24) -> 1 | K10: =SUMIF(Horo82111[Jour],C10,Horo82111[Durée]) -> 8.5 | L10: =IFERROR(SUMIF(Horo82111[[#This Row],[Jour]],Horo82111[[#This Row],[Jour]],Horo82111[[#This Row],[GPF]]) / Horo82111[[#This Row],[hrs]],"") -> 0.11764706 | M10: =IF("GPF"=Horo82111[[#This Row],[Tâche]],Horo82111[[#This Row],[Durée]],"") -> 1 | N10: =IF("RI"=Horo82111[[#This Row],[Tâche]],Horo82111[[#This Row],[Durée]],"") | O10: =IF("GB"=Horo82111[[#This Row],[Tâche]],Horo82111[[#This Row],[Durée]],"") | P10: =IF("RD"=Horo82111[[#This Row],[Tâche]],Horo82111[[#This Row],[Durée]],"") | Q10: =IF("FG"=Horo82111[[#This Row],[Tâche]],Horo82111[[#This Row],[Durée]],"") | R10: =IF("CONGÉ"=Horo82111[[#This Row],[Tâche]],Horo82111[[#This Row],[Durée]],"") | S10: =IF("PS"=Horo82111[[#This Row],[Tâche]],Horo82111[[#This Row],[Durée]],"") | T10: =IF("TD"=Horo82111[[#This Row],[Tâche]],Horo82111[[#This Row],[Durée]],"") | U10: =IF("N/C"=Horo82111[[#This Row],[Tâche]],Horo82111[[#This Row],[Durée]],"") | W10: =IF(Horo82111[[#This Row],[O]]="o",Horo82111[[#This Row],[Durée]],".") -> 1 | X10: =IF(Horo82111[[#This Row],[Début]]=0,"",Horo82111[[#This Row],[Fin]]-Horo82111[[#This Row],[Début]]) -> 0.041666667
A11: o | B11: =IF(Horo82111[[#This Row],[Jour]]="Lundi",$C$1+1, IF(Horo82111[[#This Row],[Jour]]="Mardi",$C$1+2, IF(Horo82111[[#This Row],[Jour]]="Mercredi",$C$1+3, IF(Horo82111[[#This Row],[Jour]]="Jeudi",$C$1+4, IF(Horo82111[[#This Row],[Jour]]="Vendredi",$C$1+5, IF(Horo82111[[#This Row],[Jour]]="Samedi",$C$1+6, IF(Horo82111[[#This Row],[Jour]]="Dimanche",$C$1, ))))))) -> 44453 | C11: Lundi | D11: 0.5625 | E11: 0.70833333 | F11: HYPERTEC | G11: RD | J11: =IF(Horo82111[[#This Row],[Début]]=0,"",(Horo82111[[#This Row],[Durée (60)2]]-INT(Horo82111[[#This Row],[Durée (60)2]]))*24) -> 3.5 | K11: =SUMIF(Horo82111[Jour],C11,Horo82111[Durée]) -> 8.5 | L11: =IFERROR(SUMIF(Horo82111[[#This Row],[Jour]],Horo82111[[#This Row],[Jour]],Horo82111[[#This Row],[GPF]]) / Horo82111[[#This Row],[hrs]],"") -> 0 | M11: =IF("GPF"=Horo82111[[#This Row],[Tâche]],Horo82111[[#This Row],[Durée]],"") | N11: =IF("RI"=Horo82111[[#This Row],[Tâche]],Horo82111[[#This Row],[Durée]],"") | O11: =IF("GB"=Horo82111[[#This Row],[Tâche]],Horo82111[[#This Row],[Durée]],"") | P11: =IF("RD"=Horo82111[[#This Row],[Tâche]],Horo82111[[#This Row],[Durée]],"") -> 3.5 | Q11: =IF("FG"=Horo82111[[#This Row],[Tâche]],Horo82111[[#This Row],[Durée]],"") | R11: =IF("CONGÉ"=Horo82111[[#This Row],[Tâche]],Horo82111[[#This Row],[Durée]],"") | S11: =IF("PS"=Horo82111[[#This Row],[Tâche]],Horo82111[[#This Row],[Durée]],"") | T11: =IF("TD"=Horo82111[[#This Row],[Tâche]],Horo82111[[#This Row],[Durée]],"") | U11: =IF("N/C"=Horo82111[[#This Row],[Tâche]],Horo82111[[#This Row],[Durée]],"") | W11: =IF(Horo82111[[#This Row],[O]]="o",Horo82111[[#This Row],[Durée]],".") -> 3.5 | X11: =IF(Horo82111[[#This Row],[Début]]=0,"",Horo82111[[#This Row],[Fin]]-Horo82111[[#This Row],[Début]]) -> 0.14583333
A12: o | B12: =IF(Horo82111[[#This Row],[Jour]]="Lundi",$C$1+1, IF(Horo82111[[#This Row],[Jour]]="Mardi",$C$1+2, IF(Horo82111[[#This Row],[Jour]]="Mercredi",$C$1+3, IF(Horo82111[[#This Row],[Jour]]="Jeudi",$C$1+4, IF(Horo82111[[#This Row],[Jour]]="Vendredi",$C$1+5, IF(Horo82111[[#This Row],[Jour]]="Samedi",$C$1+6, IF(Horo82111[[#This Row],[Jour]]="Dimanche",$C$1, ))))))) -> 44453 | C12: Lundi | D12: 0.70833333 | E12: 0.75 | F12: FORGESTIK | G12: RD | I12: tests impresions article en qté sur les étiquettes différentes | J12: =IF(Horo82111[[#This Row],[Début]]=0,"",(Horo82111[[#This Row],[Durée (60)2]]-INT(Horo82111[[#This Row],[Durée (60)2]]))*24) -> 1 | K12: =SUMIF(Horo82111[Jour],C12,Horo82111[Durée]) -> 8.5 | L12: =IFERROR(SUMIF(Horo82111[[#This Row],[Jour]],Horo82111[[#This Row],[Jour]],Horo82111[[#This Row],[GPF]]) / Horo82111[[#This Row],[hrs]],"") -> 0 | M12: =IF("GPF"=Horo82111[[#This Row],[Tâche]],Horo82111[[#This Row],[Durée]],"") | N12: =IF("RI"=Horo82111[[#This Row],[Tâche]],Horo82111[[#This Row],[Durée]],"") | O12: =IF("GB"=Horo82111[[#This Row],[Tâche]],Horo82111[[#This Row],[Durée]],"") | P12: =IF("RD"=Horo82111[[#This Row],[Tâche]],Horo82111[[#This Row],[Durée]],"") -> 1 | Q12: =IF("FG"=Horo82111[[#This Row],[Tâche]],Horo82111[[#This Row],[Durée]],"") | R12: =IF("CONGÉ"=Horo82111[[#This Row],[Tâche]],Horo82111[[#This Row],[Durée]],"") | S12: =IF("PS"=Horo82111[[#This Row],[Tâche]],Horo82111[[#This Row],[Durée]],"") | T12: =IF("TD"=Horo82111[[#This Row],[Tâche]],Horo82111[[#This Row],[Durée]],"") | U12: =IF("N/C"=Horo82111[[#This Row],[Tâche]],Horo82111[[#This Row],[Durée]],"") | W12: =IF(Horo82111[[#This Row],[O]]="o",Horo82111[[#This Row],[Durée]],".") -> 1 | X12: =IF(Horo82111[[#This Row],[Début]]=0,"",Horo82111[[#This Row],[Fin]]-Horo82111[[#This Row],[Début]]) -> 0.041666667
A13: o | B13: =IF(Horo82111[[#This Row],[Jour]]="Lundi",$C$1+1, IF(Horo82111[[#This Row],[Jour]]="Mardi",$C$1+2, IF(Horo82111[[#This Row],[Jour]]="Mercredi",$C$1+3, IF(Horo82111[[#This Row],[Jour]]="Jeudi",$C$1+4, IF(Horo82111[[#This Row],[Jour]]="Vendredi",$C$1+5, IF(Horo82111[[#This Row],[Jour]]="Samedi",$C$1+6, IF(Horo82111[[#This Row],[Jour]]="Dimanche",$C$1, ))))))) -> 44454 | C13: Mardi | D13: 0.32291667 | E13: 0.34375 | F13: FORGESTIK | G13: GB | J13: =IF(Horo82111[[#This Row],[Début]]=0,"",(Horo82111[[#This Row],[Durée (60)2]]-INT(Horo82111[[#This Row],[Durée (60)2]]))*24) -> 0.5 | K13: =SUMIF(Horo82111[Jour],C13,Horo82111[Durée]) -> 8.75 | L13: =IFERROR(SUMIF(Horo82111[[#This Row],[Jour]],Horo82111[[#This Row],[Jour]],Horo82111[[#This Row],[GPF]]) / Horo82111[[#This Row],[hrs]],"") -> 0 | M13: =IF("GPF"=Horo82111[[#This Row],[Tâche]],Horo82111[[#This Row],[Durée]],"") | N13: =IF("RI"=Horo82111[[#This Row],[Tâche]],Horo82111[[#This Row],[Durée]],"") | O13: =IF("GB"=Horo82111[[#This Row],[Tâche]],Horo82111[[#This Row],[Durée]],"") -> 0.5 | P13: =IF("RD"=Horo82111[[#This Row],[Tâche]],Horo82111[[#This Row],[Durée]],"") | Q13: =IF("FG"=Horo82111[[#This Row],[Tâche]],Horo82111[[#This Row],[Durée]],"") | R13: =IF("CONGÉ"=Horo82111[[#This Row],[Tâche]],Horo82111[[#This Row],[Durée]],"") | S13: =IF("PS"=Horo82111[[#This Row],[Tâche]],Horo82111[[#This Row],[Durée]],"") | T13: =IF("TD"=Horo82111[[#This Row],[Tâche]],Horo82111[[#This Row],[Durée]],"") | U13: =IF("N/C"=Horo82111[[#This Row],[Tâche]],Horo82111[[#This Row],[Durée]],"") | W13: =IF(Horo82111[[#This Row],[O]]="o",Horo82111[[#This Row],[Durée]],".") -> 0.5 | X13: =IF(Horo82111[[#This Row],[Début]]=0,"",Horo82111[[#This Row],[Fin]]-Horo82111[[#This Row],[Début]]) -> 0.020833333
A14: o | B14: =IF(Horo82111[[#This Row],[Jour]]="Lundi",$C$1+1, IF(Horo82111[[#This Row],[Jour]]="Mardi",$C$1+2, IF(Horo82111[[#This Row],[Jour]]="Mercredi",$C$1+3, IF(Horo82111[[#This Row],[Jour]]="Jeudi",$C$1+4, IF(Horo82111[[#This Row],[Jour]]="Vendredi",$C$1+5, IF(Horo82111[[#This Row],[Jour]]="Samedi",$C$1+6, IF(Horo82111[[#This Row],[Jour]]="Dimanche",$C$1, ))))))) -> 44454 | C14: Mardi | D14: 0.34375 | E14: 0.39583333 | F14: RBF | G14: RD | H14: Développement | I14: Affichage sur scanneur - Quantité par défaut sur l'unité logistique de l'article - U_PMX_DQLU - modification WorkflowScript_ChecksScript | J14: =IF(Horo82111[[#This Row],[Début]]=0,"",(Horo82111[[#This Row],[Durée (60)2]]-INT(Horo82111[[#This Row],[Durée (60)2]]))*24) -> 1.25 | K14: =SUMIF(Horo82111[Jour],C14,Horo82111[Durée]) -> 8.75 | L14: =IFERROR(SUMIF(Horo82111[[#This Row],[Jour]],Horo82111[[#This Row],[Jour]],Horo82111[[#This Row],[GPF]]) / Horo82111[[#This Row],[hrs]],"") -> 0 | M14: =IF("GPF"=Horo82111[[#This Row],[Tâche]],Horo82111[[#This Row],[Durée]],"") | N14: =IF("RI"=Horo82111[[#This Row],[Tâche]],Horo82111[[#This Row],[Durée]],"") | O14: =IF("GB"=Horo82111[[#This Row],[Tâche]],Horo82111[[#This Row],[Durée]],"") | P14: =IF("RD"=Horo82111[[#This Row],[Tâche]],Horo82111[[#This Row],[Durée]],"") -> 1.25 | Q14: =IF("FG"=Horo82111[[#This Row],[Tâche]],Horo82111[[#This Row],[Durée]],"") | R14: =IF("CONGÉ"=Horo82111[[#This Row],[Tâche]],Horo82111[[#This Row],[Durée]],"") | S14: =IF("PS"=Horo82111[[#This Row],[Tâche]],Horo82111[[#This Row],[Durée]],"") | T14: =IF("TD"=Horo82111[[#This Row],[Tâche]],Horo82111[[#This Row],[Durée]],"") | U14: =IF("N/C"=Horo82111[[#This Row],[Tâche]],Horo82111[[#This Row],[Durée]],"") | W14: =IF(Horo82111[[#This Row],[O]]="o",Horo82111[[#This Row],[Durée]],".") -> 1.25 | X14: =IF(Horo82111[[#This Row],[Début]]=0,"",Horo82111[[#This Row],[Fin]]-Horo82111[[#This Row],[Début]]) -> 0.052083333
A15: o | B15: =IF(Horo82111[[#This Row],[Jour]]="Lundi",$C$1+1, IF(Horo82111[[#This Row],[Jour]]="Mardi",$C$1+2, IF(Horo82111[[#This Row],[Jour]]="Mercredi",$C$1+3, IF(Horo82111[[#This Row],[Jour]]="Jeudi",$C$1+4, IF(Horo82111[[#This Row],[Jour]]="Vendredi",$C$1+5, IF(Horo82111[[#This Row],[Jour]]="Samedi",$C$1+6, IF(Horo82111[[#This Row],[Jour]]="Dimanche",$C$1, ))))))) -> 44454 | C15: Mardi | D15: 0.39583333 | E15: 0.41666667 | F15: RBF | G15: GPF | H15: Support au test | I15: Appel avec Christian, Genevive et Brian | J15: =IF(Horo82111[[#This Row],[Début]]=0,"",(Horo82111[[#This Row],[Durée (60)2]]-INT(Horo82111[[#This Row],[Durée (60)2]]))*24) -> 0.5 | K15: =SUMIF(Horo82111[Jour],C15,Horo82111[Durée]) -> 8.75 | L15: =IFERROR(SUMIF(Horo82111[[#This Row],[Jour]],Horo82111[[#This Row],[Jour]],Horo82111[[#This Row],[GPF]]) / Horo82111[[#This Row],[hrs]],"") -> 0.057142857 | M15: =IF("GPF"=Horo82111[[#This Row],[Tâche]],Horo82111[[#This Row],[Durée]],"") -> 0.5 | N15: =IF("RI"=Horo82111[[#This Row],[Tâche]],Horo82111[[#This Row],[Durée]],"") | O15: =IF("GB"=Horo82111[[#This Row],[Tâche]],Horo82111[[#This Row],[Durée]],"") | P15: =IF("RD"=Horo82111[[#This Row],[Tâche]],Horo82111[[#This Row],[Durée]],"") | Q15: =IF("FG"=Horo82111[[#This Row],[Tâche]],Horo82111[[#This Row],[Durée]],"") | R15: =IF("CONGÉ"=Horo82111[[#This Row],[Tâche]],Horo82111[[#This Row],[Durée]],"") | S15: =IF("PS"=Horo82111[[#This Row],[Tâche]],Horo82111[[#This Row],[Durée]],"") | T15: =IF("TD"=Horo82111[[#This Row],[Tâche]],Horo82111[[#This Row],[Durée]],"") | U15: =IF("N/C"=Horo82111[[#This Row],[Tâche]],Horo82111[[#This Row],[Durée]],"") | W15: =IF(Horo82111[[#This Row],[O]]="o",Horo82111[[#This Row],[Durée]],".") -> 0.5 | X15: =IF(Horo82111[[#This Row],[Début]]=0,"",Horo82111[[#This Row],[Fin]]-Horo82111[[#This Row],[Début]]) -> 0.020833333
A16: o | B16: =IF(Horo82111[[#This Row],[Jour]]="Lundi",$C$1+1, IF(Horo82111[[#This Row],[Jour]]="Mardi",$C$1+2, IF(Horo82111[[#This Row],[Jour]]="Mercredi",$C$1+3, IF(Horo82111[[#This Row],[Jour]]="Jeudi",$C$1+4, IF(Horo82111[[#This Row],[Jour]]="Vendredi",$C$1+5, IF(Horo82111[[#This Row],[Jour]]="Samedi",$C$1+6, IF(Horo82111[[#This Row],[Jour]]="Dimanche",$C$1, ))))))) -> 44454 | C16: Mardi | D16: 0.41666667 | E16: 0.4375 | F16: RBF | G16: RD | H16: Développement | I16: Affichage sur scanneur - Quantité par défaut sur l'unité logistique de l'article - U_PMX_DQLU - modification WorkflowScript_ChecksScript | J16: =IF(Horo82111[[#This Row],[Début]]=0,"",(Horo82111[[#This Row],[Durée (60)2]]-INT(Horo82111[[#This Row],[Durée (60)2]]))*24) -> 0.5 | K16: =SUMIF(Horo82111[Jour],C16,Horo82111[Durée]) -> 8.75 | L16: =IFERROR(SUMIF(Horo82111[[#This Row],[Jour]],Horo82111[[#This Row],[Jour]],Horo82111[[#This Row],[GPF]]) / Horo82111[[#This Row],[hrs]],"") -> 0 | M16: =IF("GPF"=Horo82111[[#This Row],[Tâche]],Horo82111[[#This Row],[Durée]],"") | N16: =IF("RI"=Horo82111[[#This Row],[Tâche]],Horo82111[[#This Row],[Durée]],"") | O16: =IF("GB"=Horo82111[[#This Row],[Tâche]],Horo82111[[#This Row],[Durée]],"") | P16: =IF("RD"=Horo82111[[#This Row],[Tâche]],Horo82111[[#This Row],[Durée]],"") -> 0.5 | Q16: =IF("FG"=Horo82111[[#This Row],[Tâche]],Horo82111[[#This Row],[Durée]],"") | R16: =IF("CONGÉ"=Horo82111[[#This Row],[Tâche]],Horo82111[[#This Row],[Durée]],"") | S16: =IF("PS"=Horo82111[[#This Row],[Tâche]],Horo82111[[#This Row],[Durée]],"") | T16: =IF("TD"=Horo82111[[#This Row],[Tâche]],Horo82111[[#This Row],[Durée]],"") | U16: =IF("N/C"=Horo82111[[#This Row],[Tâche]],Horo82111[[#This Row],[Durée]],"") | W16: =IF(Horo82111[[#This Row],[O]]="o",Horo82111[[#This Row],[Durée]],".") -> 0.5 | X16: =IF(Horo82111[[#This Row],[Début]]=0,"",Horo82111[[#This Row],[Fin]]-Horo82111[[#This Row],[Début]]) -> 0.020833333
A17: o | B17: =IF(Horo82111[[#This Row],[Jour]]="Lundi",$C$1+1, IF(Horo82111[[#This Row],[Jour]]="Mardi",$C$1+2, IF(Horo82111[[#This Row],[Jour]]="Mercredi",$C$1+3, IF(Horo82111[[#This Row],[Jour]]="Jeudi",$C$1+4, IF(Horo82111[[#This Row],[Jour]]="Vendredi",$C$1+5, IF(Horo82111[[#This Row],[Jour]]="Samedi",$C$1+6, IF(Horo82111[[#This Row],[Jour]]="Dimanche",$C$1, ))))))) -> 44454 | C17: Mardi | D17: 0.4375 | E17: 0.5 | F17: FORGESTIK | G17: RD | H17: Billet | I17: [Boyum Solutions A/S - 270899] Re: Issue when Receiving Returnable Items - tests et réponse à Tim - its not working properly | J17: =IF(Horo82111[[#This Row],[Début]]=0,"",(Horo82111[[#This Row],[Durée (60)2]]-INT(Horo82111[[#This Row],[Durée (60)2]]))*24) -> 1.5 | K17: =SUMIF(Horo82111[Jour],C17,Horo82111[Durée]) -> 8.75 | L17: =IFERROR(SUMIF(Horo82111[[#This Row],[Jour]],Horo82111[[#This Row],[Jour]],Horo82111[[#This Row],[GPF]]) / Horo82111[[#This Row],[hrs]],"") -> 0 | M17: =IF("GPF"=Horo82111[[#This Row],[Tâche]],Horo82111[[#This Row],[Durée]],"") | N17: =IF("RI"=Horo82111[[#This Row],[Tâche]],Horo82111[[#This Row],[Durée]],"") | O17: =IF("GB"=Horo82111[[#This Row],[Tâche]],Horo82111[[#This Row],[Durée]],"") | P17: =IF("RD"=Horo82111[[#This Row],[Tâche]],Horo82111[[#This Row],[Durée]],"") -> 1.5 | Q17: =IF("FG"=Horo82111[[#This Row],[Tâche]],Horo82111[[#This Row],[Durée]],"") | R17: =IF("CONGÉ"=Horo82111[[#This Row],[Tâche]],Horo82111[[#This Row],[Durée]],"") | S17: =IF("PS"=Horo82111[[#This Row],[Tâche]],Horo82111[[#This Row],[Durée]],"") | T17: =IF("TD"=Horo82111[[#This Row],[Tâche]],Horo82111[[#This Row],[Durée]],"") | U17: =IF("N/C"=Horo82111[[#This Row],[Tâche]],Horo82111[[#This Row],[Durée]],"") | W17: =IF(Horo82111[[#This Row],[O]]="o",Horo82111[[#This Row],[Durée]],".") -> 1.5 | X17: =IF(Horo82111[[#This Row],[Début]]=0,"",Horo82111[[#This Row],[Fin]]-Horo82111[[#This Row],[Début]]) -> 0.0625
A18: o | B18: =IF(Horo82111[[#This Row],[Jour]]="Lundi",$C$1+1, IF(Horo82111[[#This Row],[Jour]]="Mardi",$C$1+2, IF(Horo82111[[#This Row],[Jour]]="Mercredi",$C$1+3, IF(Horo82111[[#This Row],[Jour]]="Jeudi",$C$1+4, IF(Horo82111[[#This Row],[Jour]]="Vendredi",$C$1+5, IF(Horo82111[[#This Row],[Jour]]="Samedi",$C$1+6, IF(Horo82111[[#This Row],[Jour]]="Dimanche",$C$1, ))))))) -> 44454 | C18: Mardi | D18: 0.5625 | E18: 0.60416667 | F18: FORGESTIK | G18: RD | H18: Billet | I18: [Boyum Solutions A/S - 270899] Re: Issue when Receiving Returnable Items - tests et réponse à Tim - its not working properly | J18: =IF(Horo82111[[#This Row],[Début]]=0,"",(Horo82111[[#This Row],[Durée (60)2]]-INT(Horo82111[[#This Row],[Durée (60)2]]))*24) -> 1 | K18: =SUMIF(Horo82111[Jour],C18,Horo82111[Durée]) -> 8.75 | L18: =IFERROR(SUMIF(Horo82111[[#This Row],[Jour]],Horo82111[[#This Row],[Jour]],Horo82111[[#This Row],[GPF]]) / Horo82111[[#This Row],[hrs]],"") -> 0 | M18: =IF("GPF"=Horo82111[[#This Row],[Tâche]],Horo82111[[#This Row],[Durée]],"") | N18: =IF("RI"=Horo82111[[#This Row],[Tâche]],Horo82111[[#This Row],[Durée]],"") | O18: =IF("GB"=Horo82111[[#This Row],[Tâche]],Horo82111[[#This Row],[Durée]],"") | P18: =IF("RD"=Horo82111[[#This Row],[Tâche]],Horo82111[[#This Row],[Durée]],"") -> 1 | Q18: =IF("FG"=Horo82111[[#This Row],[Tâche]],Horo82111[[#This Row],[Durée]],"") | R18: =IF("CONGÉ"=Horo82111[[#This Row],[Tâche]],Horo82111[[#This Row],[Durée]],"") | S18: =IF("PS"=Horo82111[[#This Row],[Tâche]],Horo82111[[#This Row],[Durée]],"") | T18: =IF("TD"=Horo82111[[#This Row],[Tâche]],Horo82111[[#This Row],[Durée]],"") | U18: =IF("N/C"=Horo82111[[#This Row],[Tâche]],Horo82111[[#This Row],[Durée]],"") | W18: =IF(Horo82111[[#This Row],[O]]="o",Horo82111[[#This Row],[Durée]],".") -> 1 | X18: =IF(Horo82111[[#This Row],[Début]]=0,"",Horo82111[[#This Row],[Fin]]-Horo82111[[#This Row],[Début]]) -> 0.041666667
A19: o | B19: =IF(Horo82111[[#This Row],[Jour]]="Lundi",$C$1+1, IF(Horo82111[[#This Row],[Jour]]="Mardi",$C$1+2, IF(Horo82111[[#This Row],[Jour]]="Mercredi",$C$1+3, IF(Horo82111[[#This Row],[Jour]]="Jeudi",$C$1+4, IF(Horo82111[[#This Row],[Jour]]="Vendredi",$C$1+5, IF(Horo82111[[#This Row],[Jour]]="Samedi",$C$1+6, IF(Horo82111[[#This Row],[Jour]]="Dimanche",$C$1, ))))))) -> 44454 | C19: Mardi | D19: 0.60416667 | E19: 0.66666667 | F19: HYPERTEC | G19: GPF | I19: T20250819.0016 - connexion sp -> Crystal étiquette Good receipt | J19: =IF(Horo82111[[#This Row],[Début]]=0,"",(Horo82111[[#This Row],[Durée (60)2]]-INT(Horo82111[[#This Row],[Durée (60)2]]))*24) -> 1.5 | K19: =SUMIF(Horo82111[Jour],C19,Horo82111[Durée]) -> 8.75 | L19: =IFERROR(SUMIF(Horo82111[[#This Row],[Jour]],Horo82111[[#This Row],[Jour]],Horo82111[[#This Row],[GPF]]) / Horo82111[[#This Row],[hrs]],"") -> 0.17142857 | M19: =IF("GPF"=Horo82111[[#This Row],[Tâche]],Horo82111[[#This Row],[Durée]],"") -> 1.5 | N19: =IF("RI"=Horo82111[[#This Row],[Tâche]],Horo82111[[#This Row],[Durée]],"") | O19: =IF("GB"=Horo82111[[#This Row],[Tâche]],Horo82111[[#This Row],[Durée]],"") | P19: =IF("RD"=Horo82111[[#This Row],[Tâche]],Horo82111[[#This Row],[Durée]],"") | Q19: =IF("FG"=Horo82111[[#This Row],[Tâche]],Horo82111[[#This Row],[Durée]],"") | R19: =IF("CONGÉ"=Horo82111[[#This Row],[Tâche]],Horo82111[[#This Row],[Durée]],"") | S19: =IF("PS"=Horo82111[[#This Row],[Tâche]],Horo82111[[#This Row],[Durée]],"") | T19: =IF("TD"=Horo82111[[#This Row],[Tâche]],Horo82111[[#This Row],[Durée]],"") | U19: =IF("N/C"=Horo82111[[#This Row],[Tâche]],Horo82111[[#This Row],[Durée]],"") | W19: =IF(Horo82111[[#This Row],[O]]="o",Horo82111[[#This Row],[Durée]],".") -> 1.5 | X19: =IF(Horo82111[[#This Row],[Début]]=0,"",Horo82111[[#This Row],[Fin]]-Horo82111[[#This Row],[Début]]) -> 0.0625
A20: o | B20: =IF(Horo82111[[#This Row],[Jour]]="Lundi",$C$1+1, IF(Horo82111[[#This Row],[Jour]]="Mardi",$C$1+2, IF(Horo82111[[#This Row],[Jour]]="Mercredi",$C$1+3, IF(Horo82111[[#This Row],[Jour]]="Jeudi",$C$1+4, IF(Horo82111[[#This Row],[Jour]]="Vendredi",$C$1+5, IF(Horo82111[[#This Row],[Jour]]="Samedi",$C$1+6, IF(Horo82111[[#This Row],[Jour]]="Dimanche",$C$1, ))))))) -> 44454 | C20: Mardi | D20: 0.66666667 | E20: 0.69791667 | F20: RBF | G20: GPF | H20: Étiquette | I20: Correction étiquette suite à l'appel avec Christian, … | J20: =IF(Horo82111[[#This Row],[Début]]=0,"",(Horo82111[[#This Row],[Durée (60)2]]-INT(Horo82111[[#This Row],[Durée (60)2]]))*24) -> 0.75 | K20: =SUMIF(Horo82111[Jour],C20,Horo82111[Durée]) -> 8.75 | L20: =IFERROR(SUMIF(Horo82111[[#This Row],[Jour]],Horo82111[[#This Row],[Jour]],Horo82111[[#This Row],[GPF]]) / Horo82111[[#This Row],[hrs]],"") -> 0.085714286 | M20: =IF("GPF"=Horo82111[[#This Row],[Tâche]],Horo82111[[#This Row],[Durée]],"") -> 0.75 | N20: =IF("RI"=Horo82111[[#This Row],[Tâche]],Horo82111[[#This Row],[Durée]],"") | O20: =IF("GB"=Horo82111[[#This Row],[Tâche]],Horo82111[[#This Row],[Durée]],"") | P20: =IF("RD"=Horo82111[[#This Row],[Tâche]],Horo82111[[#This Row],[Durée]],"") | Q20: =IF("FG"=Horo82111[[#This Row],[Tâche]],Horo82111[[#This Row],[Durée]],"") | R20: =IF("CONGÉ"=Horo82111[[#This Row],[Tâche]],Horo82111[[#This Row],[Durée]],"") | S20: =IF("PS"=Horo82111[[#This Row],[Tâche]],Horo82111[[#This Row],[Durée]],"") | T20: =IF("TD"=Horo82111[[#This Row],[Tâche]],Horo82111[[#This Row],[Durée]],"") | U20: =IF("N/C"=Horo82111[[#This Row],[Tâche]],Horo82111[[#This Row],[Durée]],"") | W20: =IF(Horo82111[[#This Row],[O]]="o",Horo82111[[#This Row],[Durée]],".") -> 0.75 | X20: =IF(Horo82111[[#This Row],[Début]]=0,"",Horo82111[[#This Row],[Fin]]-Horo82111[[#This Row],[Début]]) -> 0.03125
A21: o | B21: =IF(Horo82111[[#This Row],[Jour]]="Lundi",$C$1+1, IF(Horo82111[[#This Row],[Jour]]="Mardi",$C$1+2, IF(Horo82111[[#This Row],[Jour]]="Mercredi",$C$1+3, IF(Horo82111[[#This Row],[Jour]]="Jeudi",$C$1+4, IF(Horo82111[[#This Row],[Jour]]="Vendredi",$C$1+5, IF(Horo82111[[#This Row],[Jour]]="Samedi",$C$1+6, IF(Horo82111[[#This Row],[Jour]]="Dimanche",$C$1, ))))))) -> 44454 | C21: Mardi | D21: 0.69791667 | E21: 0.72916667 | F21: HYPERTEC | G21: GPF | H21: Étiquette | I21: T20250819.0016 - SKU label-Receiving | J21: =IF(Horo82111[[#This Row],[Début]]=0,"",(Horo82111[[#This Row],[Durée (60)2]]-INT(Horo82111[[#This Row],[Durée (60)2]]))*24) -> 0.75 | K21: =SUMIF(Horo82111[Jour],C21,Horo82111[Durée]) -> 8.75 | L21: =IFERROR(SUMIF(Horo82111[[#This Row],[Jour]],Horo82111[[#This Row],[Jour]],Horo82111[[#This Row],[GPF]]) / Horo82111[[#This Row],[hrs]],"") -> 0.085714286 | M21: =IF("GPF"=Horo82111[[#This Row],[Tâche]],Horo82111[[#This Row],[Durée]],"") -> 0.75 | N21: =IF("RI"=Horo82111[[#This Row],[Tâche]],Horo82111[[#This Row],[Durée]],"") | O21: =IF("GB"=Horo82111[[#This Row],[Tâche]],Horo82111[[#This Row],[Durée]],"") | P21: =IF("RD"=Horo82111[[#This Row],[Tâche]],Horo82111[[#This Row],[Durée]],"") | Q21: =IF("FG"=Horo82111[[#This Row],[Tâche]],Horo82111[[#This Row],[Durée]],"") | R21: =IF("CONGÉ"=Horo82111[[#This Row],[Tâche]],Horo82111[[#This Row],[Durée]],"") | S21: =IF("PS"=Horo82111[[#This Row],[Tâche]],Horo82111[[#This Row],[Durée]],"") | T21: =IF("TD"=Horo82111[[#This Row],[Tâche]],Horo82111[[#This Row],[Durée]],"") | U21: =IF("N/C"=Horo82111[[#This Row],[Tâche]],Horo82111[[#This Row],[Durée]],"") | W21: =IF(Horo82111[[#This Row],[O]]="o",Horo82111[[#This Row],[Durée]],".") -> 0.75 | X21: =IF(Horo82111[[#This Row],[Début]]=0,"",Horo82111[[#This Row],[Fin]]-Horo82111[[#This Row],[Début]]) -> 0.03125
A22: o | B22: =IF(Horo82111[[#This Row],[Jour]]="Lundi",$C$1+1, IF(Horo82111[[#This Row],[Jour]]="Mardi",$C$1+2, IF(Horo82111[[#This Row],[Jour]]="Mercredi",$C$1+3, IF(Horo82111[[#This Row],[Jour]]="Jeudi",$C$1+4, IF(Horo82111[[#This Row],[Jour]]="Vendredi",$C$1+5, IF(Horo82111[[#This Row],[Jour]]="Samedi",$C$1+6, IF(Horo82111[[#This Row],[Jour]]="Dimanche",$C$1, ))))))) -> 44454 | C22: Mardi | D22: 0.75 | E22: 0.77083333 | F22: HYPERTEC | G22: RD | H22: Étiquette | I22: T20250819.0016 -Picking Label | J22: =IF(Horo82111[[#This Row],[Début]]=0,"",(Horo82111[[#This Row],[Durée (60)2]]-INT(Horo82111[[#This Row],[Durée (60)2]]))*24) -> 0.5 | K22: =SUMIF(Horo82111[Jour],C22,Horo82111[Durée]) -> 8.75 | L22: =IFERROR(SUMIF(Horo82111[[#This Row],[Jour]],Horo82111[[#This Row],[Jour]],Horo82111[[#This Row],[GPF]]) / Horo82111[[#This Row],[hrs]],"") -> 0 | M22: =IF("GPF"=Horo82111[[#This Row],[Tâche]],Horo82111[[#This Row],[Durée]],"") | N22: =IF("RI"=Horo82111[[#This Row],[Tâche]],Horo82111[[#This Row],[Durée]],"") | O22: =IF("GB"=Horo82111[[#This Row],[Tâche]],Horo82111[[#This Row],[Durée]],"") | P22: =IF("RD"=Horo82111[[#This Row],[Tâche]],Horo82111[[#This Row],[Durée]],"") -> 0.5 | Q22: =IF("FG"=Horo82111[[#This Row],[Tâche]],Horo82111[[#This Row],[Durée]],"") | R22: =IF("CONGÉ"=Horo82111[[#This Row],[Tâche]],Horo82111[[#This Row],[Durée]],"") | S22: =IF("PS"=Horo82111[[#This Row],[Tâche]],Horo82111[[#This Row],[Durée]],"") | T22: =IF("TD"=Horo82111[[#This Row],[Tâche]],Horo82111[[#This Row],[Durée]],"") | U22: =IF("N/C"=Horo82111[[#This Row],[Tâche]],Horo82111[[#This Row],[Durée]],"") | W22: =IF(Horo82111[[#This Row],[O]]="o",Horo82111[[#This Row],[Durée]],".") -> 0.5 | X22: =IF(Horo82111[[#This Row],[Début]]=0,"",Horo82111[[#This Row],[Fin]]-Horo82111[[#This Row],[Début]]) -> 0.020833333
A23: o | B23: =IF(Horo82111[[#This Row],[Jour]]="Lundi",$C$1+1, IF(Horo82111[[#This Row],[Jour]]="Mardi",$C$1+2, IF(Horo82111[[#This Row],[Jour]]="Mercredi",$C$1+3, IF(Horo82111[[#This Row],[Jour]]="Jeudi",$C$1+4, IF(Horo82111[[#This Row],[Jour]]="Vendredi",$C$1+5, IF(Horo82111[[#This Row],[Jour]]="Samedi",$C$1+6, IF(Horo82111[[#This Row],[Jour]]="Dimanche",$C$1, ))))))) -> 44455 | C23: Mercredi | D23: 0.33333333 | E23: 0.35416667 | F23: FORGESTIK | G23: GB | H23: . | J23: =IF(Horo82111[[#This Row],[Début]]=0,"",(Horo82111[[#This Row],[Durée (60)2]]-INT(Horo82111[[#This Row],[Durée (60)2]]))*24) -> 0.5 | K23: =SUMIF(Horo82111[Jour],C23,Horo82111[Durée]) -> 7 | L23: =IFERROR(SUMIF(Horo82111[[#This Row],[Jour]],Horo82111[[#This Row],[Jour]],Horo82111[[#This Row],[GPF]]) / Horo82111[[#This Row],[hrs]],"") -> 0 | M23: =IF("GPF"=Horo82111[[#This Row],[Tâche]],Horo82111[[#This Row],[Durée]],"") | N23: =IF("RI"=Horo82111[[#This Row],[Tâche]],Horo82111[[#This Row],[Durée]],"") | O23: =IF("GB"=Horo82111[[#This Row],[Tâche]],Horo82111[[#This Row],[Durée]],"") -> 0.5 | P23: =IF("RD"=Horo82111[[#This Row],[Tâche]],Horo82111[[#This Row],[Durée]],"") | Q23: =IF("FG"=Horo82111[[#This Row],[Tâche]],Horo82111[[#This Row],[Durée]],"") | R23: =IF("CONGÉ"=Horo82111[[#This Row],[Tâche]],Horo82111[[#This Row],[Durée]],"") | S23: =IF("PS"=Horo82111[[#This Row],[Tâche]],Horo82111[[#This Row],[Durée]],"") | T23: =IF("TD"=Horo82111[[#This Row],[Tâche]],Horo82111[[#This Row],[Durée]],"") | U23: =IF("N/C"=Horo82111[[#This Row],[Tâche]],Horo82111[[#This Row],[Durée]],"") | W23: =IF(Horo82111[[#This Row],[O]]="o",Horo82111[[#This Row],[Durée]],".") -> 0.5 | X23: =IF(Horo82111[[#This Row],[Début]]=0,"",Horo82111[[#This Row],[Fin]]-Horo82111[[#This Row],[Début]]) -> 0.020833333
A24: o | B24: =IF(Horo82111[[#This Row],[Jour]]="Lundi",$C$1+1, IF(Horo82111[[#This Row],[Jour]]="Mardi",$C$1+2, IF(Horo82111[[#This Row],[Jour]]="Mercredi",$C$1+3, IF(Horo82111[[#This Row],[Jour]]="Jeudi",$C$1+4, IF(Horo82111[[#This Row],[Jour]]="Vendredi",$C$1+5, IF(Horo82111[[#This Row],[Jour]]="Samedi",$C$1+6, IF(Horo82111[[#This Row],[Jour]]="Dimanche",$C$1, ))))))) -> 44455 | C24: Mercredi | D24: 0.35416667 | E24: 0.39583333 | F24: HYPERTEC | G24: RD | H24: Étiquette | I24: T20250819.0016 -Picking Label | J24: =IF(Horo82111[[#This Row],[Début]]=0,"",(Horo82111[[#This Row],[Durée (60)2]]-INT(Horo82111[[#This Row],[Durée (60)2]]))*24) -> 1 | K24: =SUMIF(Horo82111[Jour],C24,Horo82111[Durée]) -> 7 | L24: =IFERROR(SUMIF(Horo82111[[#This Row],[Jour]],Horo82111[[#This Row],[Jour]],Horo82111[[#This Row],[GPF]]) / Horo82111[[#This Row],[hrs]],"") -> 0 | M24: =IF("GPF"=Horo82111[[#This Row],[Tâche]],Horo82111[[#This Row],[Durée]],"") | N24: =IF("RI"=Horo82111[[#This Row],[Tâche]],Horo82111[[#This Row],[Durée]],"") | O24: =IF("GB"=Horo82111[[#This Row],[Tâche]],Horo82111[[#This Row],[Durée]],"") | P24: =IF("RD"=Horo82111[[#This Row],[Tâche]],Horo82111[[#This Row],[Durée]],"") -> 1 | Q24: =IF("FG"=Horo82111[[#This Row],[Tâche]],Horo82111[[#This Row],[Durée]],"") | R24: =IF("CONGÉ"=Horo82111[[#This Row],[Tâche]],Horo82111[[#This Row],[Durée]],"") | S24: =IF("PS"=Horo82111[[#This Row],[Tâche]],Horo82111[[#This Row],[Durée]],"") | T24: =IF("TD"=Horo82111[[#This Row],[Tâche]],Horo82111[[#This Row],[Durée]],"") | U24: =IF("N/C"=Horo82111[[#This Row],[Tâche]],Horo82111[[#This Row],[Durée]],"") | W24: =IF(Horo82111[[#This Row],[O]]="o",Horo82111[[#This Row],[Durée]],".") -> 1 | X24: =IF(Horo82111[[#This Row],[Début]]=0,"",Horo82111[[#This Row],[Fin]]-Horo82111[[#This Row],[Début]]) -> 0.041666667
A25: o | B25: =IF(Horo82111[[#This Row],[Jour]]="Lundi",$C$1+1, IF(Horo82111[[#This Row],[Jour]]="Mardi",$C$1+2, IF(Horo82111[[#This Row],[Jour]]="Mercredi",$C$1+3, IF(Horo82111[[#This Row],[Jour]]="Jeudi",$C$1+4, IF(Horo82111[[#This Row],[Jour]]="Vendredi",$C$1+5, IF(Horo82111[[#This Row],[Jour]]="Samedi",$C$1+6, IF(Horo82111[[#This Row],[Jour]]="Dimanche",$C$1, ))))))) -> 44455 | C25: Mercredi | D25: 0.39583333 | E25: 0.41666667 | F25: AGENCE GRAVEL | G25: GPF | H25: Suivi de projet | J25: =IF(Horo82111[[#This Row],[Début]]=0,"",(Horo82111[[#This Row],[Durée (60)2]]-INT(Horo82111[[#This Row],[Durée (60)2]]))*24) -> 0.5 | K25: =SUMIF(Horo82111[Jour],C25,Horo82111[Durée]) -> 7 | L25: =IFERROR(SUMIF(Horo82111[[#This Row],[Jour]],Horo82111[[#This Row],[Jour]],Horo82111[[#This Row],[GPF]]) / Horo82111[[#This Row],[hrs]],"") -> 0.071428571 | M25: =IF("GPF"=Horo82111[[#This Row],[Tâche]],Horo82111[[#This Row],[Durée]],"") -> 0.5 | N25: =IF("RI"=Horo82111[[#This Row],[Tâche]],Horo82111[[#This Row],[Durée]],"") | O25: =IF("GB"=Horo82111[[#This Row],[Tâche]],Horo82111[[#This Row],[Durée]],"") | P25: =IF("RD"=Horo82111[[#This Row],[Tâche]],Horo82111[[#This Row],[Durée]],"") | Q25: =IF("FG"=Horo82111[[#This Row],[Tâche]],Horo82111[[#This Row],[Durée]],"") | R25: =IF("CONGÉ"=Horo82111[[#This Row],[Tâche]],Horo82111[[#This Row],[Durée]],"") | S25: =IF("PS"=Horo82111[[#This Row],[Tâche]],Horo82111[[#This Row],[Durée]],"") | T25: =IF("TD"=Horo82111[[#This Row],[Tâche]],Horo82111[[#This Row],[Durée]],"") | U25: =IF("N/C"=Horo82111[[#This Row],[Tâche]],Horo82111[[#This Row],[Durée]],"") | W25: =IF(Horo82111[[#This Row],[O]]="o",Horo82111[[#This Row],[Durée]],".") -> 0.5 | X25: =IF(Horo82111[[#This Row],[Début]]=0,"",Horo82111[[#This Row],[Fin]]-Horo82111[[#This Row],[Début]]) -> 0.020833333
A26: o | B26: =IF(Horo82111[[#This Row],[Jour]]="Lundi",$C$1+1, IF(Horo82111[[#This Row],[Jour]]="Mardi",$C$1+2, IF(Horo82111[[#This Row],[Jour]]="Mercredi",$C$1+3, IF(Horo82111[[#This Row],[Jour]]="Jeudi",$C$1+4, IF(Horo82111[[#This Row],[Jour]]="Vendredi",$C$1+5, IF(Horo82111[[#This Row],[Jour]]="Samedi",$C$1+6, IF(Horo82111[[#This Row],[Jour]]="Dimanche",$C$1, ))))))) -> 44455 | C26: Mercredi | D26: 0.41666667 | E26: 0.5 | F26: HYPERTEC | G26: GPF | H26: Étiquette | I26: T20250819.0016 -Picking Label | J26: =IF(Horo82111[[#This Row],[Début]]=0,"",(Horo82111[[#This Row],[Durée (60)2]]-INT(Horo82111[[#This Row],[Durée (60)2]]))*24) -> 2 | K26: =SUMIF(Horo82111[Jour],C26,Horo82111[Durée]) -> 7 | L26: =IFERROR(SUMIF(Horo82111[[#This Row],[Jour]],Horo82111[[#This Row],[Jour]],Horo82111[[#This Row],[GPF]]) / Horo82111[[#This Row],[hrs]],"") -> 0.28571429 | M26: =IF("GPF"=Horo82111[[#This Row],[Tâche]],Horo82111[[#This Row],[Durée]],"") -> 2 | N26: =IF("RI"=Horo82111[[#This Row],[Tâche]],Horo82111[[#This Row],[Durée]],"") | O26: =IF("GB"=Horo82111[[#This Row],[Tâche]],Horo82111[[#This Row],[Durée]],"") | P26: =IF("RD"=Horo82111[[#This Row],[Tâche]],Horo82111[[#This Row],[Durée]],"") | Q26: =IF("FG"=Horo82111[[#This Row],[Tâche]],Horo82111[[#This Row],[Durée]],"") | R26: =IF("CONGÉ"=Horo82111[[#This Row],[Tâche]],Horo82111[[#This Row],[Durée]],"") | S26: =IF("PS"=Horo82111[[#This Row],[Tâche]],Horo82111[[#This Row],[Durée]],"") | T26: =IF("TD"=Horo82111[[#This Row],[Tâche]],Horo82111[[#This Row],[Durée]],"") | U26: =IF("N/C"=Horo82111[[#This Row],[Tâche]],Horo82111[[#This Row],[Durée]],"") | W26: =IF(Horo82111[[#This Row],[O]]="o",Horo82111[[#This Row],[Durée]],".") -> 2 | X26: =IF(Horo82111[[#This Row],[Début]]=0,"",Horo82111[[#This Row],[Fin]]-Horo82111[[#This Row],[Début]]) -> 0.083333333
A27: o | B27: =IF(Horo82111[[#This Row],[Jour]]="Lundi",$C$1+1, IF(Horo82111[[#This Row],[Jour]]="Mardi",$C$1+2, IF(Horo82111[[#This Row],[Jour]]="Mercredi",$C$1+3, IF(Horo82111[[#This Row],[Jour]]="Jeudi",$C$1+4, IF(Horo82111[[#This Row],[Jour]]="Vendredi",$C$1+5, IF(Horo82111[[#This Row],[Jour]]="Samedi",$C$1+6, IF(Horo82111[[#This Row],[Jour]]="Dimanche",$C$1, ))))))) -> 44455 | C27: Mercredi | D27: 0.58333333 | E27: 0.625 | F27: HYPERTEC | G27: GPF | H27: Étiquette | I27: 15:00 - T20250819.0016 -Picking Label | J27: =IF(Horo82111[[#This Row],[Début]]=0,"",(Horo82111[[#This Row],[Durée (60)2]]-INT(Horo82111[[#This Row],[Durée (60)2]]))*24) -> 1 | K27: =SUMIF(Horo82111[Jour],C27,Horo82111[Durée]) -> 7 | L27: =IFERROR(SUMIF(Horo82111[[#This Row],[Jour]],Horo82111[[#This Row],[Jour]],Horo82111[[#This Row],[GPF]]) / Horo82111[[#This Row],[hrs]],"") -> 0.14285714 | M27: =IF("GPF"=Horo82111[[#This Row],[Tâche]],Horo82111[[#This Row],[Durée]],"") -> 1 | N27: =IF("RI"=Horo82111[[#This Row],[Tâche]],Horo82111[[#This Row],[Durée]],"") | O27: =IF("GB"=Horo82111[[#This Row],[Tâche]],Horo82111[[#This Row],[Durée]],"") | P27: =IF("RD"=Horo82111[[#This Row],[Tâche]],Horo82111[[#This Row],[Durée]],"") | Q27: =IF("FG"=Horo82111[[#This Row],[Tâche]],Horo82111[[#This Row],[Durée]],"") | R27: =IF("CONGÉ"=Horo82111[[#This Row],[Tâche]],Horo82111[[#This Row],[Durée]],"") | S27: =IF("PS"=Horo82111[[#This Row],[Tâche]],Horo82111[[#This Row],[Durée]],"") | T27: =IF("TD"=Horo82111[[#This Row],[Tâche]],Horo82111[[#This Row],[Durée]],"") | U27: =IF("N/C"=Horo82111[[#This Row],[Tâche]],Horo82111[[#This Row],[Durée]],"") | W27: =IF(Horo82111[[#This Row],[O]]="o",Horo82111[[#This Row],[Durée]],".") -> 1 | X27: =IF(Horo82111[[#This Row],[Début]]=0,"",Horo82111[[#This Row],[Fin]]-Horo82111[[#This Row],[Début]]) -> 0.041666667
A28: o | B28: =IF(Horo82111[[#This Row],[Jour]]="Lundi",$C$1+1, IF(Horo82111[[#This Row],[Jour]]="Mardi",$C$1+2, IF(Horo82111[[#This Row],[Jour]]="Mercredi",$C$1+3, IF(Horo82111[[#This Row],[Jour]]="Jeudi",$C$1+4, IF(Horo82111[[#This Row],[Jour]]="Vendredi",$C$1+5, IF(Horo82111[[#This Row],[Jour]]="Samedi",$C$1+6, IF(Horo82111[[#This Row],[Jour]]="Dimanche",$C$1, ))))))) -> 44455 | C28: Mercredi | D28: 0.625 | E28: 0.66666667 | F28: FORGESTIK | G28: RD | H28: Étiquette | I28: Crystal - impression du nombre d'étiquettes | J28: =IF(Horo82111[[#This Row],[Début]]=0,"",(Horo82111[[#This Row],[Durée (60)2]]-INT(Horo82111[[#This Row],[Durée (60)2]]))*24) -> 1 | K28: =SUMIF(Horo82111[Jour],C28,Horo82111[Durée]) -> 7 | L28: =IFERROR(SUMIF(Horo82111[[#This Row],[Jour]],Horo82111[[#This Row],[Jour]],Horo82111[[#This Row],[GPF]]) / Horo82111[[#This Row],[hrs]],"") -> 0 | M28: =IF("GPF"=Horo82111[[#This Row],[Tâche]],Horo82111[[#This Row],[Durée]],"") | N28: =IF("RI"=Horo82111[[#This Row],[Tâche]],Horo82111[[#This Row],[Durée]],"") | O28: =IF("GB"=Horo82111[[#This Row],[Tâche]],Horo82111[[#This Row],[Durée]],"") | P28: =IF("RD"=Horo82111[[#This Row],[Tâche]],Horo82111[[#This Row],[Durée]],"") -> 1 | Q28: =IF("FG"=Horo82111[[#This Row],[Tâche]],Horo82111[[#This Row],[Durée]],"") | R28: =IF("CONGÉ"=Horo82111[[#This Row],[Tâche]],Horo82111[[#This Row],[Durée]],"") | S28: =IF("PS"=Horo82111[[#This Row],[Tâche]],Horo82111[[#This Row],[Durée]],"") | T28: =IF("TD"=Horo82111[[#This Row],[Tâche]],Horo82111[[#This Row],[Durée]],"") | U28: =IF("N/C"=Horo82111[[#This Row],[Tâche]],Horo82111[[#This Row],[Durée]],"") | W28: =IF(Horo82111[[#This Row],[O]]="o",Horo82111[[#This Row],[Durée]],".") -> 1 | X28: =IF(Horo82111[[#This Row],[Début]]=0,"",Horo82111[[#This Row],[Fin]]-Horo82111[[#This Row],[Début]]) -> 0.041666667
A29: o | B29: =IF(Horo82111[[#This Row],[Jour]]="Lundi",$C$1+1, IF(Horo82111[[#This Row],[Jour]]="Mardi",$C$1+2, IF(Horo82111[[#This Row],[Jour]]="Mercredi",$C$1+3, IF(Horo82111[[#This Row],[Jour]]="Jeudi",$C$1+4, IF(Horo82111[[#This Row],[Jour]]="Vendredi",$C$1+5, IF(Horo82111[[#This Row],[Jour]]="Samedi",$C$1+6, IF(Horo82111[[#This Row],[Jour]]="Dimanche",$C$1, ))))))) -> 44455 | C29: Mercredi | D29: 0.66666667 | E29: 0.70833333 | F29: RBF | G29: GPF | H29: Étiquette | I29: 18:30 - Modification - Étiquette SSCC | J29: =IF(Horo82111[[#This Row],[Début]]=0,"",(Horo82111[[#This Row],[Durée (60)2]]-INT(Horo82111[[#This Row],[Durée (60)2]]))*24) -> 1 | K29: =SUMIF(Horo82111[Jour],C29,Horo82111[Durée]) -> 7 | L29: =IFERROR(SUMIF(Horo82111[[#This Row],[Jour]],Horo82111[[#This Row],[Jour]],Horo82111[[#This Row],[GPF]]) / Horo82111[[#This Row],[hrs]],"") -> 0.14285714 | M29: =IF("GPF"=Horo82111[[#This Row],[Tâche]],Horo82111[[#This Row],[Durée]],"") -> 1 | N29: =IF("RI"=Horo82111[[#This Row],[Tâche]],Horo82111[[#This Row],[Durée]],"") | O29: =IF("GB"=Horo82111[[#This Row],[Tâche]],Horo82111[[#This Row],[Durée]],"") | P29: =IF("RD"=Horo82111[[#This Row],[Tâche]],Horo82111[[#This Row],[Durée]],"") | Q29: =IF("FG"=Horo82111[[#This Row],[Tâche]],Horo82111[[#This Row],[Durée]],"") | R29: =IF("CONGÉ"=Horo82111[[#This Row],[Tâche]],Horo82111[[#This Row],[Durée]],"") | S29: =IF("PS"=Horo82111[[#This Row],[Tâche]],Horo82111[[#This Row],[Durée]],"") | T29: =IF("TD"=Horo82111[[#This Row],[Tâche]],Horo82111[[#This Row],[Durée]],"") | U29: =IF("N/C"=Horo82111[[#This Row],[Tâche]],Horo82111[[#This Row],[Durée]],"") | W29: =IF(Horo82111[[#This Row],[O]]="o",Horo82111[[#This Row],[Durée]],".") -> 1 | X29: =IF(Horo82111[[#This Row],[Début]]=0,"",Horo82111[[#This Row],[Fin]]-Horo82111[[#This Row],[Début]]) -> 0.041666667
A30: o | B30: =IF(Horo82111[[#This Row],[Jour]]="Lundi",$C$1+1, IF(Horo82111[[#This Row],[Jour]]="Mardi",$C$1+2, IF(Horo82111[[#This Row],[Jour]]="Mercredi",$C$1+3, IF(Horo82111[[#This Row],[Jour]]="Jeudi",$C$1+4, IF(Horo82111[[#This Row],[Jour]]="Vendredi",$C$1+5, IF(Horo82111[[#This Row],[Jour]]="Samedi",$C$1+6, IF(Horo82111[[#This Row],[Jour]]="Dimanche",$C$1, ))))))) -> 44456 | C30: Jeudi | D30: 0.29166667 | E30: 0.35416667 | F30: RBF | G30: TD | H30: Déplacement chez le client | I30: RBF Montréal | J30: =IF(Horo82111[[#This Row],[Début]]=0,"",(Horo82111[[#This Row],[Durée (60)2]]-INT(Horo82111[[#This Row],[Durée (60)2]]))*24) -> 1.5 | K30: =SUMIF(Horo82111[Jour],C30,Horo82111[Durée]) -> 9.25 | L30: =IFERROR(SUMIF(Horo82111[[#This Row],[Jour]],Horo82111[[#This Row],[Jour]],Horo82111[[#This Row],[GPF]]) / Horo82111[[#This Row],[hrs]],"") -> 0 | M30: =IF("GPF"=Horo82111[[#This Row],[Tâche]],Horo82111[[#This Row],[Durée]],"") | N30: =IF("RI"=Horo82111[[#This Row],[Tâche]],Horo82111[[#This Row],[Durée]],"") | O30: =IF("GB"=Horo82111[[#This Row],[Tâche]],Horo82111[[#This Row],[Durée]],"") | P30: =IF("RD"=Horo82111[[#This Row],[Tâche]],Horo82111[[#This Row],[Durée]],"") | Q30: =IF("FG"=Horo82111[[#This Row],[Tâche]],Horo82111[[#This Row],[Durée]],"") | R30: =IF("CONGÉ"=Horo82111[[#This Row],[Tâche]],Horo82111[[#This Row],[Durée]],"") | S30: =IF("PS"=Horo82111[[#This Row],[Tâche]],Horo82111[[#This Row],[Durée]],"") | T30: =IF("TD"=Horo82111[[#This Row],[Tâche]],Horo82111[[#This Row],[Durée]],"") -> 1.5 | U30: =IF("N/C"=Horo82111[[#This Row],[Tâche]],Horo82111[[#This Row],[Durée]],"") | W30: =IF(Horo82111[[#This Row],[O]]="o",Horo82111[[#This Row],[Durée]],".") -> 1.5 | X30: =IF(Horo82111[[#This Row],[Début]]=0,"",Horo82111[[#This Row],[Fin]]-Horo82111[[#This Row],[Début]]) -> 0.0625
A31: o | B31: =IF(Horo82111[[#This Row],[Jour]]="Lundi",$C$1+1, IF(Horo82111[[#This Row],[Jour]]="Mardi",$C$1+2, IF(Horo82111[[#This Row],[Jour]]="Mercredi",$C$1+3, IF(Horo82111[[#This Row],[Jour]]="Jeudi",$C$1+4, IF(Horo82111[[#This Row],[Jour]]="Vendredi",$C$1+5, IF(Horo82111[[#This Row],[Jour]]="Samedi",$C$1+6, IF(Horo82111[[#This Row],[Jour]]="Dimanche",$C$1, ))))))) -> 44456 | C31: Jeudi | D31: 0.35416667 | E31: 0.52083333 | F31: RBF | G31: GPF | H31: Formation PMX | I31: Rencontre sur place avec Christian,Geneviève, Brian, Francine | J31: =IF(Horo82111[[#This Row],[Début]]=0,"",(Horo82111[[#This Row],[Durée (60)2]]-INT(Horo82111[[#This Row],[Durée (60)2]]))*24) -> 4 | K31: =SUMIF(Horo82111[Jour],C31,Horo82111[Durée]) -> 9.25 | L31: =IFERROR(SUMIF(Horo82111[[#This Row],[Jour]],Horo82111[[#This Row],[Jour]],Horo82111[[#This Row],[GPF]]) / Horo82111[[#This Row],[hrs]],"") -> 0.43243243 | M31: =IF("GPF"=Horo82111[[#This Row],[Tâche]],Horo82111[[#This Row],[Durée]],"") -> 4 | N31: =IF("RI"=Horo82111[[#This Row],[Tâche]],Horo82111[[#This Row],[Durée]],"") | O31: =IF("GB"=Horo82111[[#This Row],[Tâche]],Horo82111[[#This Row],[Durée]],"") | P31: =IF("RD"=Horo82111[[#This Row],[Tâche]],Horo82111[[#This Row],[Durée]],"") | Q31: =IF("FG"=Horo82111[[#This Row],[Tâche]],Horo82111[[#This Row],[Durée]],"") | R31: =IF("CONGÉ"=Horo82111[[#This Row],[Tâche]],Horo82111[[#This Row],[Durée]],"") | S31: =IF("PS"=Horo82111[[#This Row],[Tâche]],Horo82111[[#This Row],[Durée]],"") | T31: =IF("TD"=Horo82111[[#This Row],[Tâche]],Horo82111[[#This Row],[Durée]],"") | U31: =IF("N/C"=Horo82111[[#This Row],[Tâche]],Horo82111[[#This Row],[Durée]],"") | W31: =IF(Horo82111[[#This Row],[O]]="o",Horo82111[[#This Row],[Durée]],".") -> 4 | X31: =IF(Horo82111[[#This Row],[Début]]=0,"",Horo82111[[#This Row],[Fin]]-Horo82111[[#This Row],[Début]]) -> 0.16666667
A32: o | B32: =IF(Horo82111[[#This Row],[Jour]]="Lundi",$C$1+1, IF(Horo82111[[#This Row],[Jour]]="Mardi",$C$1+2, IF(Horo82111[[#This Row],[Jour]]="Mercredi",$C$1+3, IF(Horo82111[[#This Row],[Jour]]="Jeudi",$C$1+4, IF(Horo82111[[#This Row],[Jour]]="Vendredi",$C$1+5, IF(Horo82111[[#This Row],[Jour]]="Samedi",$C$1+6, IF(Horo82111[[#This Row],[Jour]]="Dimanche",$C$1, ))))))) -> 44456 | C32: Jeudi | D32: 0.52083333 | E32: 0.55208333 | F32: RBF | G32: TD | H32: Déplacement chez le client | I32: RBF Montréal | J32: =IF(Horo82111[[#This Row],[Début]]=0,"",(Horo82111[[#This Row],[Durée (60)2]]-INT(Horo82111[[#This Row],[Durée (60)2]]))*24) -> 0.75 | K32: =SUMIF(Horo82111[Jour],C32,Horo82111[Durée]) -> 9.25 | L32: =IFERROR(SUMIF(Horo82111[[#This Row],[Jour]],Horo82111[[#This Row],[Jour]],Horo82111[[#This Row],[GPF]]) / Horo82111[[#This Row],[hrs]],"") -> 0 | M32: =IF("GPF"=Horo82111[[#This Row],[Tâche]],Horo82111[[#This Row],[Durée]],"") | N32: =IF("RI"=Horo82111[[#This Row],[Tâche]],Horo82111[[#This Row],[Durée]],"") | O32: =IF("GB"=Horo82111[[#This Row],[Tâche]],Horo82111[[#This Row],[Durée]],"") | P32: =IF("RD"=Horo82111[[#This Row],[Tâche]],Horo82111[[#This Row],[Durée]],"") | Q32: =IF("FG"=Horo82111[[#This Row],[Tâche]],Horo82111[[#This Row],[Durée]],"") | R32: =IF("CONGÉ"=Horo82111[[#This Row],[Tâche]],Horo82111[[#This Row],[Durée]],"") | S32: =IF("PS"=Horo82111[[#This Row],[Tâche]],Horo82111[[#This Row],[Durée]],"") | T32: =IF("TD"=Horo82111[[#This Row],[Tâche]],Horo82111[[#This Row],[Durée]],"") -> 0.75 | U32: =IF("N/C"=Horo82111[[#This Row],[Tâche]],Horo82111[[#This Row],[Durée]],"") | W32: =IF(Horo82111[[#This Row],[O]]="o",Horo82111[[#This Row],[Durée]],".") -> 0.75 | X32: =IF(Horo82111[[#This Row],[Début]]=0,"",Horo82111[[#This Row],[Fin]]-Horo82111[[#This Row],[Début]]) -> 0.03125
A33: o | B33: =IF(Horo82111[[#This Row],[Jour]]="Lundi",$C$1+1, IF(Horo82111[[#This Row],[Jour]]="Mardi",$C$1+2, IF(Horo82111[[#This Row],[Jour]]="Mercredi",$C$1+3, IF(Horo82111[[#This Row],[Jour]]="Jeudi",$C$1+4, IF(Horo82111[[#This Row],[Jour]]="Vendredi",$C$1+5, IF(Horo82111[[#This Row],[Jour]]="Samedi",$C$1+6, IF(Horo82111[[#This Row],[Jour]]="Dimanche",$C$1, ))))))) -> 44456 | C33: Jeudi | D33: 0.64583333 | E33: 0.65625 | F33: EURODIB | G33: GPF | H33: Billet | I33: T20250729.0009 - Installation dans Produmex des imprimantes Toshiba | J33: =IF(Horo82111[[#This Row],[Début]]=0,"",(Horo82111[[#This Row],[Durée (60)2]]-INT(Horo82111[[#This Row],[Durée (60)2]]))*24) -> 0.25 | K33: =SUMIF(Horo82111[Jour],C33,Horo82111[Durée]) -> 9.25 | L33: =IFERROR(SUMIF(Horo82111[[#This Row],[Jour]],Horo82111[[#This Row],[Jour]],Horo82111[[#This Row],[GPF]]) / Horo82111[[#This Row],[hrs]],"") -> 0.027027027 | M33: =IF("GPF"=Horo82111[[#This Row],[Tâche]],Horo82111[[#This Row],[Durée]],"") -> 0.25 | N33: =IF("RI"=Horo82111[[#This Row],[Tâche]],Horo82111[[#This Row],[Durée]],"") | O33: =IF("GB"=Horo82111[[#This Row],[Tâche]],Horo82111[[#This Row],[Durée]],"") | P33: =IF("RD"=Horo82111[[#This Row],[Tâche]],Horo82111[[#This Row],[Durée]],"") | Q33: =IF("FG"=Horo82111[[#This Row],[Tâche]],Horo82111[[#This Row],[Durée]],"") | R33: =IF("CONGÉ"=Horo82111[[#This Row],[Tâche]],Horo82111[[#This Row],[Durée]],"") | S33: =IF("PS"=Horo82111[[#This Row],[Tâche]],Horo82111[[#This Row],[Durée]],"") | T33: =IF("TD"=Horo82111[[#This Row],[Tâche]],Horo82111[[#This Row],[Durée]],"") | U33: =IF("N/C"=Horo82111[[#This Row],[Tâche]],Horo82111[[#This Row],[Durée]],"") | W33: =IF(Horo82111[[#This Row],[O]]="o",Horo82111[[#This Row],[Durée]],".") -> 0.25 | X33: =IF(Horo82111[[#This Row],[Début]]=0,"",Horo82111[[#This Row],[Fin]]-Horo82111[[#This Row],[Début]]) -> 0.010416667
A34: o | B34: =IF(Horo82111[[#This Row],[Jour]]="Lundi",$C$1+1, IF(Horo82111[[#This Row],[Jour]]="Mardi",$C$1+2, IF(Horo82111[[#This Row],[Jour]]="Mercredi",$C$1+3, IF(Horo82111[[#This Row],[Jour]]="Jeudi",$C$1+4, IF(Horo82111[[#This Row],[Jour]]="Vendredi",$C$1+5, IF(Horo82111[[#This Row],[Jour]]="Samedi",$C$1+6, IF(Horo82111[[#This Row],[Jour]]="Dimanche",$C$1, ))))))) -> 44456 | C34: Jeudi | D34: 0.65625 | E34: 0.6875 | F34: FORGESTIK | G34: GB | J34: =IF(Horo82111[[#This Row],[Début]]=0,"",(Horo82111[[#This Row],[Durée (60)2]]-INT(Horo82111[[#This Row],[Durée (60)2]]))*24) -> 0.75 | K34: =SUMIF(Horo82111[Jour],C34,Horo82111[Durée]) -> 9.25 | L34: =IFERROR(SUMIF(Horo82111[[#This Row],[Jour]],Horo82111[[#This Row],[Jour]],Horo82111[[#This Row],[GPF]]) / Horo82111[[#This Row],[hrs]],"") -> 0 | M34: =IF("GPF"=Horo82111[[#This Row],[Tâche]],Horo82111[[#This Row],[Durée]],"") | N34: =IF("RI"=Horo82111[[#This Row],[Tâche]],Horo82111[[#This Row],[Durée]],"") | O34: =IF("GB"=Horo82111[[#This Row],[Tâche]],Horo82111[[#This Row],[Durée]],"") -> 0.75 | P34: =IF("RD"=Horo82111[[#This Row],[Tâche]],Horo82111[[#This Row],[Durée]],"") | Q34: =IF("FG"=Horo82111[[#This Row],[Tâche]],Horo82111[[#This Row],[Durée]],"") | R34: =IF("CONGÉ"=Horo82111[[#This Row],[Tâche]],Horo82111[[#This Row],[Durée]],"") | S34: =IF("PS"=Horo82111[[#This Row],[Tâche]],Horo82111[[#This Row],[Durée]],"") | T34: =IF("TD"=Horo82111[[#This Row],[Tâche]],Horo82111[[#This Row],[Durée]],"") | U34: =IF("N/C"=Horo82111[[#This Row],[Tâche]],Horo82111[[#This Row],[Durée]],"") | W34: =IF(Horo82111[[#This Row],[O]]="o",Horo82111[[#This Row],[Durée]],".") -> 0.75 | X34: =IF(Horo82111[[#This Row],[Début]]=0,"",Horo82111[[#This Row],[Fin]]-Horo82111[[#This Row],[Début]]) -> 0.03125
A35: o | B35: =IF(Horo82111[[#This Row],[Jour]]="Lundi",$C$1+1, IF(Horo82111[[#This Row],[Jour]]="Mardi",$C$1+2, IF(Horo82111[[#This Row],[Jour]]="Mercredi",$C$1+3, IF(Horo82111[[#This Row],[Jour]]="Jeudi",$C$1+4, IF(Horo82111[[#This Row],[Jour]]="Vendredi",$C$1+5, IF(Horo82111[[#This Row],[Jour]]="Samedi",$C$1+6, IF(Horo82111[[#This Row],[Jour]]="Dimanche",$C$1, ))))))) -> 44456 | C35: Jeudi | D35: 0.6875 | E35: 0.77083333 | F35: FORGESTIK | G35: RD | H35: Preuve de concept | I35: Table temporaire pour imprimer étiquette SSCC et Good receipt | J35: =IF(Horo82111[[#This Row],[Début]]=0,"",(Horo82111[[#This Row],[Durée (60)2]]-INT(Horo82111[[#This Row],[Durée (60)2]]))*24) -> 2 | K35: =SUMIF(Horo82111[Jour],C35,Horo82111[Durée]) -> 9.25 | L35: =IFERROR(SUMIF(Horo82111[[#This Row],[Jour]],Horo82111[[#This Row],[Jour]],Horo82111[[#This Row],[GPF]]) / Horo82111[[#This Row],[hrs]],"") -> 0 | M35: =IF("GPF"=Horo82111[[#This Row],[Tâche]],Horo82111[[#This Row],[Durée]],"") | N35: =IF("RI"=Horo82111[[#This Row],[Tâche]],Horo82111[[#This Row],[Durée]],"") | O35: =IF("GB"=Horo82111[[#This Row],[Tâche]],Horo82111[[#This Row],[Durée]],"") | P35: =IF("RD"=Horo82111[[#This Row],[Tâche]],Horo82111[[#This Row],[Durée]],"") -> 2 | Q35: =IF("FG"=Horo82111[[#This Row],[Tâche]],Horo82111[[#This Row],[Durée]],"") | R35: =IF("CONGÉ"=Horo82111[[#This Row],[Tâche]],Horo82111[[#This Row],[Durée]],"") | S35: =IF("PS"=Horo82111[[#This Row],[Tâche]],Horo82111[[#This Row],[Durée]],"") | T35: =IF("TD"=Horo82111[[#This Row],[Tâche]],Horo82111[[#This Row],[Durée]],"") | U35: =IF("N/C"=Horo82111[[#This Row],[Tâche]],Horo82111[[#This Row],[Durée]],"") | W35: =IF(Horo82111[[#This Row],[O]]="o",Horo82111[[#This Row],[Durée]],".") -> 2 | X35: =IF(Horo82111[[#This Row],[Début]]=0,"",Horo82111[[#This Row],[Fin]]-Horo82111[[#This Row],[Début]]) -> 0.083333333
A36: o | B36: =IF(Horo82111[[#This Row],[Jour]]="Lundi",$C$1+1, IF(Horo82111[[#This Row],[Jour]]="Mardi",$C$1+2, IF(Horo82111[[#This Row],[Jour]]="Mercredi",$C$1+3, IF(Horo82111[[#This Row],[Jour]]="Jeudi",$C$1+4, IF(Horo82111[[#This Row],[Jour]]="Vendredi",$C$1+5, IF(Horo82111[[#This Row],[Jour]]="Samedi",$C$1+6, IF(Horo82111[[#This Row],[Jour]]="Dimanche",$C$1, ))))))) -> 44457 | C36: Vendredi | D36: 0.33333333 | E36: 0.35416667 | F36: FORGESTIK | G36: GB | H36: . | J36: =IF(Horo82111[[#This Row],[Début]]=0,"",(Horo82111[[#This Row],[Durée (60)2]]-INT(Horo82111[[#This Row],[Durée (60)2]]))*24) -> 0.5 | K36: =SUMIF(Horo82111[Jour],C36,Horo82111[Durée]) -> 6.5 | L36: =IFERROR(SUMIF(Horo82111[[#This Row],[Jour]],Horo82111[[#This Row],[Jour]],Horo82111[[#This Row],[GPF]]) / Horo82111[[#This Row],[hrs]],"") -> 0 | M36: =IF("GPF"=Horo82111[[#This Row],[Tâche]],Horo82111[[#This Row],[Durée]],"") | N36: =IF("RI"=Horo82111[[#This Row],[Tâche]],Horo82111[[#This Row],[Durée]],"") | O36: =IF("GB"=Horo82111[[#This Row],[Tâche]],Horo82111[[#This Row],[Durée]],"") -> 0.5 | P36: =IF("RD"=Horo82111[[#This Row],[Tâche]],Horo82111[[#This Row],[Durée]],"") | Q36: =IF("FG"=Horo82111[[#This Row],[Tâche]],Horo82111[[#This Row],[Durée]],"") | R36: =IF("CONGÉ"=Horo82111[[#This Row],[Tâche]],Horo82111[[#This Row],[Durée]],"") | S36: =IF("PS"=Horo82111[[#This Row],[Tâche]],Horo82111[[#This Row],[Durée]],"") | T36: =IF("TD"=Horo82111[[#This Row],[Tâche]],Horo82111[[#This Row],[Durée]],"") | U36: =IF("N/C"=Horo82111[[#This Row],[Tâche]],Horo82111[[#This Row],[Durée]],"") | W36: =IF(Horo82111[[#This Row],[O]]="o",Horo82111[[#This Row],[Durée]],".") -> 0.5 | X36: =IF(Horo82111[[#This Row],[Début]]=0,"",Horo82111[[#This Row],[Fin]]-Horo82111[[#This Row],[Début]]) -> 0.020833333
A37: o | B37: =IF(Horo82111[[#This Row],[Jour]]="Lundi",$C$1+1, IF(Horo82111[[#This Row],[Jour]]="Mardi",$C$1+2, IF(Horo82111[[#This Row],[Jour]]="Mercredi",$C$1+3, IF(Horo82111[[#This Row],[Jour]]="Jeudi",$C$1+4, IF(Horo82111[[#This Row],[Jour]]="Vendredi",$C$1+5, IF(Horo82111[[#This Row],[Jour]]="Samedi",$C$1+6, IF(Horo82111[[#This Row],[Jour]]="Dimanche",$C$1, ))))))) -> 44457 | C37: Vendredi | D37: 0.35416667 | E37: 0.39583333 | F37: HYPERTEC | G37: RD | H37: Étiquette client | I37: T20250819.0016 -Picking Label | J37: =IF(Horo82111[[#This Row],[Début]]=0,"",(Horo82111[[#This Row],[Durée (60)2]]-INT(Horo82111[[#This Row],[Durée (60)2]]))*24) -> 1 | K37: =SUMIF(Horo82111[Jour],C37,Horo82111[Durée]) -> 6.5 | L37: =IFERROR(SUMIF(Horo82111[[#This Row],[Jour]],Horo82111[[#This Row],[Jour]],Horo82111[[#This Row],[GPF]]) / Horo82111[[#This Row],[hrs]],"") -> 0 | M37: =IF("GPF"=Horo82111[[#This Row],[Tâche]],Horo82111[[#This Row],[Durée]],"") | N37: =IF("RI"=Horo82111[[#This Row],[Tâche]],Horo82111[[#This Row],[Durée]],"") | O37: =IF("GB"=Horo82111[[#This Row],[Tâche]],Horo82111[[#This Row],[Durée]],"") | P37: =IF("RD"=Horo82111[[#This Row],[Tâche]],Horo82111[[#This Row],[Durée]],"") -> 1 | Q37: =IF("FG"=Horo82111[[#This Row],[Tâche]],Horo82111[[#This Row],[Durée]],"") | R37: =IF("CONGÉ"=Horo82111[[#This Row],[Tâche]],Horo82111[[#This Row],[Durée]],"") | S37: =IF("PS"=Horo82111[[#This Row],[Tâche]],Horo82111[[#This Row],[Durée]],"") | T37: =IF("TD"=Horo82111[[#This Row],[Tâche]],Horo82111[[#This Row],[Durée]],"") | U37: =IF("N/C"=Horo82111[[#This Row],[Tâche]],Horo82111[[#This Row],[Durée]],"") | W37: =IF(Horo82111[[#This Row],[O]]="o",Horo82111[[#This Row],[Durée]],".") -> 1 | X37: =IF(Horo82111[[#This Row],[Début]]=0,"",Horo82111[[#This Row],[Fin]]-Horo82111[[#This Row],[Début]]) -> 0.041666667
A38: o | B38: =IF(Horo82111[[#This Row],[Jour]]="Lundi",$C$1+1, IF(Horo82111[[#This Row],[Jour]]="Mardi",$C$1+2, IF(Horo82111[[#This Row],[Jour]]="Mercredi",$C$1+3, IF(Horo82111[[#This Row],[Jour]]="Jeudi",$C$1+4, IF(Horo82111[[#This Row],[Jour]]="Vendredi",$C$1+5, IF(Horo82111[[#This Row],[Jour]]="Samedi",$C$1+6, IF(Horo82111[[#This Row],[Jour]]="Dimanche",$C$1, ))))))) -> 44457 | C38: Vendredi | D38: 0.39583333 | E38: 0.45833333 | F38: HYPERTEC | G38: N/C | H38: Étiquette client | I38: T20250819.0016 - Appel avec Michel et Francine | J38: =IF(Horo82111[[#This Row],[Début]]=0,"",(Horo82111[[#This Row],[Durée (60)2]]-INT(Horo82111[[#This Row],[Durée (60)2]]))*24) -> 1.5 | K38: =SUMIF(Horo82111[Jour],C38,Horo82111[Durée]) -> 6.5 | L38: =IFERROR(SUMIF(Horo82111[[#This Row],[Jour]],Horo82111[[#This Row],[Jour]],Horo82111[[#This Row],[GPF]]) / Horo82111[[#This Row],[hrs]],"") -> 0 | M38: =IF("GPF"=Horo82111[[#This Row],[Tâche]],Horo82111[[#This Row],[Durée]],"") | N38: =IF("RI"=Horo82111[[#This Row],[Tâche]],Horo82111[[#This Row],[Durée]],"") | O38: =IF("GB"=Horo82111[[#This Row],[Tâche]],Horo82111[[#This Row],[Durée]],"") | P38: =IF("RD"=Horo82111[[#This Row],[Tâche]],Horo82111[[#This Row],[Durée]],"") | Q38: =IF("FG"=Horo82111[[#This Row],[Tâche]],Horo82111[[#This Row],[Durée]],"") | R38: =IF("CONGÉ"=Horo82111[[#This Row],[Tâche]],Horo82111[[#This Row],[Durée]],"") | S38: =IF("PS"=Horo82111[[#This Row],[Tâche]],Horo82111[[#This Row],[Durée]],"") | T38: =IF("TD"=Horo82111[[#This Row],[Tâche]],Horo82111[[#This Row],[Durée]],"") | U38: =IF("N/C"=Horo82111[[#This Row],[Tâche]],Horo82111[[#This Row],[Durée]],"") -> 1.5 | W38: =IF(Horo82111[[#This Row],[O]]="o",Horo82111[[#This Row],[Durée]],".") -> 1.5 | X38: =IF(Horo82111[[#This Row],[Début]]=0,"",Horo82111[[#This Row],[Fin]]-Horo82111[[#This Row],[Début]]) -> 0.0625
A39: o | B39: =IF(Horo82111[[#This Row],[Jour]]="Lundi",$C$1+1, IF(Horo82111[[#This Row],[Jour]]="Mardi",$C$1+2, IF(Horo82111[[#This Row],[Jour]]="Mercredi",$C$1+3, IF(Horo82111[[#This Row],[Jour]]="Jeudi",$C$1+4, IF(Horo82111[[#This Row],[Jour]]="Vendredi",$C$1+5, IF(Horo82111[[#This Row],[Jour]]="Samedi",$C$1+6, IF(Horo82111[[#This Row],[Jour]]="Dimanche",$C$1, ))))))) -> 44457 | C39: Vendredi | D39: 0.45833333 | E39: 0.47916667 | F39: HYPERTEC | G39: GB | H39: Étiquette client | I39: T20250819.0016 -Picking Label | J39: =IF(Horo82111[[#This Row],[Début]]=0,"",(Horo82111[[#This Row],[Durée (60)2]]-INT(Horo82111[[#This Row],[Durée (60)2]]))*24) -> 0.5 | K39: =SUMIF(Horo82111[Jour],C39,Horo82111[Durée]) -> 6.5 | L39: =IFERROR(SUMIF(Horo82111[[#This Row],[Jour]],Horo82111[[#This Row],[Jour]],Horo82111[[#This Row],[GPF]]) / Horo82111[[#This Row],[hrs]],"") -> 0 | M39: =IF("GPF"=Horo82111[[#This Row],[Tâche]],Horo82111[[#This Row],[Durée]],"") | N39: =IF("RI"=Horo82111[[#This Row],[Tâche]],Horo82111[[#This Row],[Durée]],"") | O39: =IF("GB"=Horo82111[[#This Row],[Tâche]],Horo82111[[#This Row],[Durée]],"") -> 0.5 | P39: =IF("RD"=Horo82111[[#This Row],[Tâche]],Horo82111[[#This Row],[Durée]],"") | Q39: =IF("FG"=Horo82111[[#This Row],[Tâche]],Horo82111[[#This Row],[Durée]],"") | R39: =IF("CONGÉ"=Horo82111[[#This Row],[Tâche]],Horo82111[[#This Row],[Durée]],"") | S39: =IF("PS"=Horo82111[[#This Row],[Tâche]],Horo82111[[#This Row],[Durée]],"") | T39: =IF("TD"=Horo82111[[#This Row],[Tâche]],Horo82111[[#This Row],[Durée]],"") | U39: =IF("N/C"=Horo82111[[#This Row],[Tâche]],Horo82111[[#This Row],[Durée]],"") | W39: =IF(Horo82111[[#This Row],[O]]="o",Horo82111[[#This Row],[Durée]],".") -> 0.5 | X39: =IF(Horo82111[[#This Row],[Début]]=0,"",Horo82111[[#This Row],[Fin]]-Horo82111[[#This Row],[Début]]) -> 0.020833333
A40: o | B40: =IF(Horo82111[[#This Row],[Jour]]="Lundi",$C$1+1, IF(Horo82111[[#This Row],[Jour]]="Mardi",$C$1+2, IF(Horo82111[[#This Row],[Jour]]="Mercredi",$C$1+3, IF(Horo82111[[#This Row],[Jour]]="Jeudi",$C$1+4, IF(Horo82111[[#This Row],[Jour]]="Vendredi",$C$1+5, IF(Horo82111[[#This Row],[Jour]]="Samedi",$C$1+6, IF(Horo82111[[#This Row],[Jour]]="Dimanche",$C$1, ))))))) -> 44457 | C40: Vendredi | D40: 0.5625 | E40: 0.6875 | F40: HYPERTEC | G40: RD | H40: Étiquette client | I40: T20250819.0016 -Picking Label | J40: =IF(Horo82111[[#This Row],[Début]]=0,"",(Horo82111[[#This Row],[Durée (60)2]]-INT(Horo82111[[#This Row],[Durée (60)2]]))*24) -> 3 | K40: =SUMIF(Horo82111[Jour],C40,Horo82111[Durée]) -> 6.5 | L40: =IFERROR(SUMIF(Horo82111[[#This Row],[Jour]],Horo82111[[#This Row],[Jour]],Horo82111[[#This Row],[GPF]]) / Horo82111[[#This Row],[hrs]],"") -> 0 | M40: =IF("GPF"=Horo82111[[#This Row],[Tâche]],Horo82111[[#This Row],[Durée]],"") | N40: =IF("RI"=Horo82111[[#This Row],[Tâche]],Horo82111[[#This Row],[Durée]],"") | O40: =IF("GB"=Horo82111[[#This Row],[Tâche]],Horo82111[[#This Row],[Durée]],"") | P40: =IF("RD"=Horo82111[[#This Row],[Tâche]],Horo82111[[#This Row],[Durée]],"") -> 3 | Q40: =IF("FG"=Horo82111[[#This Row],[Tâche]],Horo82111[[#This Row],[Durée]],"") | R40: =IF("CONGÉ"=Horo82111[[#This Row],[Tâche]],Horo82111[[#This Row],[Durée]],"") | S40: =IF("PS"=Horo82111[[#This Row],[Tâche]],Horo82111[[#This Row],[Durée]],"") | T40: =IF("TD"=Horo82111[[#This Row],[Tâche]],Horo82111[[#This Row],[Durée]],"") | U40: =IF("N/C"=Horo82111[[#This Row],[Tâche]],Horo82111[[#This Row],[Durée]],"") | W40: =IF(Horo82111[[#This Row],[O]]="o",Horo82111[[#This Row],[Durée]],".") -> 3 | X40: =IF(Horo82111[[#This Row],[Début]]=0,"",Horo82111[[#This Row],[Fin]]-Horo82111[[#This Row],[Début]]) -> 0.125
A41: o | B41: =IF(Horo82111[[#This Row],[Jour]]="Lundi",$C$1+1, IF(Horo82111[[#This Row],[Jour]]="Mardi",$C$1+2, IF(Horo82111[[#This Row],[Jour]]="Mercredi",$C$1+3, IF(Horo82111[[#This Row],[Jour]]="Jeudi",$C$1+4, IF(Horo82111[[#This Row],[Jour]]="Vendredi",$C$1+5, IF(Horo82111[[#This Row],[Jour]]="Samedi",$C$1+6, IF(Horo82111[[#This Row],[Jour]]="Dimanche",$C$1, ))))))) -> 44457 | C41: Vendredi | D41: 0.6875 | E41: 0.6875 | F41: HYPERTEC | G41: N/C | H41: Étiquette client | I41: 17:30 - T20250819.0016 -Picking Label | J41: =IF(Horo82111[[#This Row],[Début]]=0,"",(Horo82111[[#This Row],[Durée (60)2]]-INT(Horo82111[[#This Row],[Durée (60)2]]))*24) -> 0 | K41: =SUMIF(Horo82111[Jour],C41,Horo82111[Durée]) -> 6.5 | L41: =IFERROR(SUMIF(Horo82111[[#This Row],[Jour]],Horo82111[[#This Row],[Jour]],Horo82111[[#This Row],[GPF]]) / Horo82111[[#This Row],[hrs]],"") -> 0 | M41: =IF("GPF"=Horo82111[[#This Row],[Tâche]],Horo82111[[#This Row],[Durée]],"") | N41: =IF("RI"=Horo82111[[#This Row],[Tâche]],Horo82111[[#This Row],[Durée]],"") | O41: =IF("GB"=Horo82111[[#This Row],[Tâche]],Horo82111[[#This Row],[Durée]],"") | P41: =IF("RD"=Horo82111[[#This Row],[Tâche]],Horo82111[[#This Row],[Durée]],"") | Q41: =IF("FG"=Horo82111[[#This Row],[Tâche]],Horo82111[[#This Row],[Durée]],"") | R41: =IF("CONGÉ"=Horo82111[[#This Row],[Tâche]],Horo82111[[#This Row],[Durée]],"") | S41: =IF("PS"=Horo82111[[#This Row],[Tâche]],Horo82111[[#This Row],[Durée]],"") | T41: =IF("TD"=Horo82111[[#This Row],[Tâche]],Horo82111[[#This Row],[Durée]],"") | U41: =IF("N/C"=Horo82111[[#This Row],[Tâche]],Horo82111[[#This Row],[Durée]],"") -> 0 | W41: =IF(Horo82111[[#This Row],[O]]="o",Horo82111[[#This Row],[Durée]],".") -> 0 | X41: =IF(Horo82111[[#This Row],[Début]]=0,"",Horo82111[[#This Row],[Fin]]-Horo82111[[#This Row],[Début]]) -> 0
A42: . | B42: =IF(Horo82111[[#This Row],[Jour]]="Lundi",$C$1+1, IF(Horo82111[[#This Row],[Jour]]="Mardi",$C$1+2, IF(Horo82111[[#This Row],[Jour]]="Mercredi",$C$1+3, IF(Horo82111[[#This Row],[Jour]]="Jeudi",$C$1+4, IF(Horo82111[[#This Row],[Jour]]="Vendredi",$C$1+5, IF(Horo82111[[#This Row],[Jour]]="Samedi",$C$1+6, IF(Horo82111[[#This Row],[Jour]]="Dimanche",$C$1, ))))))) -> 44457 | C42: Vendredi | J42: =IF(Horo82111[[#This Row],[Début]]=0,"",(Horo82111[[#This Row],[Durée (60)2]]-INT(Horo82111[[#This Row],[Durée (60)2]]))*24) | K42: =SUMIF(Horo82111[Jour],C42,Horo82111[Durée]) -> 6.5 | L42: =IFERROR(SUMIF(Horo82111[[#This Row],[Jour]],Horo82111[[#This Row],[Jour]],Horo82111[[#This Row],[GPF]]) / Horo82111[[#This Row],[hrs]],"") -> 0 | M42: =IF("GPF"=Horo82111[[#This Row],[Tâche]],Horo82111[[#This Row],[Durée]],"") | N42: =IF("RI"=Horo82111[[#This Row],[Tâche]],Horo82111[[#This Row],[Durée]],"") | O42: =IF("GB"=Horo82111[[#This Row],[Tâche]],Horo82111[[#This Row],[Durée]],"") | P42: =IF("RD"=Horo82111[[#This Row],[Tâche]],Horo82111[[#This Row],[Durée]],"") | Q42: =IF("FG"=Horo82111[[#This Row],[Tâche]],Horo82111[[#This Row],[Durée]],"") | R42: =IF("CONGÉ"=Horo82111[[#This Row],[Tâche]],Horo82111[[#This Row],[Durée]],"") | S42: =IF("PS"=Horo82111[[#This Row],[Tâche]],Horo82111[[#This Row],[Durée]],"") | T42: =IF("TD"=Horo82111[[#This Row],[Tâche]],Horo82111[[#This Row],[Durée]],"") | U42: =IF("N/C"=Horo82111[[#This Row],[Tâche]],Horo82111[[#This Row],[Durée]],"") | W42: =IF(Horo82111[[#This Row],[O]]="o",Horo82111[[#This Row],[Durée]],".") -> . | X42: =IF(Horo82111[[#This Row],[Début]]=0,"",Horo82111[[#This Row],[Fin]]-Horo82111[[#This Row],[Début]])
A43: . | B43: =IF(Horo82111[[#This Row],[Jour]]="Lundi",$C$1+1, IF(Horo82111[[#This Row],[Jour]]="Mardi",$C$1+2, IF(Horo82111[[#This Row],[Jour]]="Mercredi",$C$1+3, IF(Horo82111[[#This Row],[Jour]]="Jeudi",$C$1+4, IF(Horo82111[[#This Row],[Jour]]="Vendredi",$C$1+5, IF(Horo82111[[#This Row],[Jour]]="Samedi",$C$1+6, IF(Horo82111[[#This Row],[Jour]]="Dimanche",$C$1, ))))))) -> 0 | F43: FORGESTIK | G43: N/C | H43: . | J43: =IF(Horo82111[[#This Row],[Début]]=0,"",(Horo82111[[#This Row],[Durée (60)2]]-INT(Horo82111[[#This Row],[Durée (60)2]]))*24) | K43: =SUMIF(Horo82111[Jour],C43,Horo82111[Durée]) -> 0 | L43: =IFERROR(SUMIF(Horo82111[[#This Row],[Jour]],Horo82111[[#This Row],[Jour]],Horo82111[[#This Row],[GPF]]) / Horo82111[[#This Row],[hrs]],"") | M43: =IF("GPF"=Horo82111[[#This Row],[Tâche]],Horo82111[[#This Row],[Durée]],"") | N43: =IF("RI"=Horo82111[[#This Row],[Tâche]],Horo82111[[#This Row],[Durée]],"") | O43: =IF("GB"=Horo82111[[#This Row],[Tâche]],Horo82111[[#This Row],[Durée]],"") | P43: =IF("RD"=Horo82111[[#This Row],[Tâche]],Horo82111[[#This Row],[Durée]],"") | Q43: =IF("FG"=Horo82111[[#This Row],[Tâche]],Horo82111[[#This Row],[Durée]],"") | R43: =IF("CONGÉ"=Horo82111[[#This Row],[Tâche]],Horo82111[[#This Row],[Durée]],"") | S43: =IF("PS"=Horo82111[[#This Row],[Tâche]],Horo82111[[#This Row],[Durée]],"") | T43: =IF("TD"=Horo82111[[#This Row],[Tâche]],Horo82111[[#This Row],[Durée]],"") | U43: =IF("N/C"=Horo82111[[#This Row],[Tâche]],Horo82111[[#This Row],[Durée]],"") | W43: =IF(Horo82111[[#This Row],[O]]="o",Horo82111[[#This Row],[Durée]],".") -> . | X43: =IF(Horo82111[[#This Row],[Début]]=0,"",Horo82111[[#This Row],[Fin]]-Horo82111[[#This Row],[Début]])
A50: % | B50: Clients | C50: Total
A51: =IF((SUMIF(Horo82111[Client],B51,Horo82111[Durée]) / Total)=0,"",(SUMIF(Horo82111[Client],B51,Horo82111[Durée]) / Total)) -> 0.28571429 | B51: FORGESTIK | C51: =IF(SUMIF(Horo82111[Client],B51,Horo82111[Durée])=0,"",SUMIF(Horo82111[Client],B51,Horo82111[Durée])) -> 11
A52: =IF((SUMIF(Horo82111[Client],B52,Horo82111[Durée]) / Total)=0,"",(SUMIF(Horo82111[Client],B52,Horo82111[Durée]) / Total)) -> 0.012987013 | B52: AGENCE GRAVEL | C52: =IF(SUMIF(Horo82111[Client],B52,Horo82111[Durée])=0,"",SUMIF(Horo82111[Client],B52,Horo82111[Durée])) -> 0.5
A53: =IF((SUMIF(Horo82111[Client],B53,Horo82111[Durée]) / Total)=0,"",(SUMIF(Horo82111[Client],B53,Horo82111[Durée]) / Total)) | B53: ZITTA | C53: =IF(SUMIF(Horo82111[Client],B53,Horo82111[Durée])=0,"",SUMIF(Horo82111[Client],B53,Horo82111[Durée]))
A54: =IF((SUMIF(Horo82111[Client],B54,Horo82111[Durée]) / Total)=0,"",(SUMIF(Horo82111[Client],B54,Horo82111[Durée]) / Total)) -> 0.0064935065 | B54: EURODIB | C54: =IF(SUMIF(Horo82111[Client],B54,Horo82111[Durée])=0,"",SUMIF(Horo82111[Client],B54,Horo82111[Durée])) -> 0.25
A55: =IF((SUMIF(Horo82111[Client],B55,Horo82111[Durée]) / Total)=0,"",(SUMIF(Horo82111[Client],B55,Horo82111[Durée]) / Total)) | B55: AREVA | C55: =IF(SUMIF(Horo82111[Client],B55,Horo82111[Durée])=0,"",SUMIF(Horo82111[Client],B55,Horo82111[Durée]))
A56: =IF((SUMIF(Horo82111[Client],B56,Horo82111[Durée]) / Total)=0,"",(SUMIF(Horo82111[Client],B56,Horo82111[Durée]) / Total)) | B56: ATLANTIS POMPE | C56: =IF(SUMIF(Horo82111[Client],B56,Horo82111[Durée])=0,"",SUMIF(Horo82111[Client],B56,Horo82111[Durée]))
A57: =IF((SUMIF(Horo82111[Client],B57,Horo82111[Durée]) / Total)=0,"",(SUMIF(Horo82111[Client],B57,Horo82111[Durée]) / Total)) | B57: BTRUST | C57: =IF(SUMIF(Horo82111[Client],B57,Horo82111[Durée])=0,"",SUMIF(Horo82111[Client],B57,Horo82111[Durée]))
A58: =IF((SUMIF(Horo82111[Client],B58,Horo82111[Durée]) / Total)=0,"",(SUMIF(Horo82111[Client],B58,Horo82111[Durée]) / Total)) | B58: CARNOT | C58: =IF(SUMIF(Horo82111[Client],B58,Horo82111[Durée])=0,"",SUMIF(Horo82111[Client],B58,Horo82111[Durée]))
A59: =IF((SUMIF(Horo82111[Client],B59,Horo82111[Durée]) / Total)=0,"",(SUMIF(Horo82111[Client],B59,Horo82111[Durée]) / Total)) | B59: CÉRAGRÈS | C59: =IF(SUMIF(Horo82111[Client],B59,Horo82111[Durée])=0,"",SUMIF(Horo82111[Client],B59,Horo82111[Durée]))
A60: =IF((SUMIF(Horo82111[Client],B60,Horo82111[Durée]) / Total)=0,"",(SUMIF(Horo82111[Client],B60,Horo82111[Durée]) / Total)) -> 0.0064935065 | B60: COATICOOK | C60: =IF(SUMIF(Horo82111[Client],B60,Horo82111[Durée])=0,"",SUMIF(Horo82111[Client],B60,Horo82111[Durée])) -> 0.25
A61: =IF((SUMIF(Horo82111[Client],B61,Horo82111[Durée]) / Total)=0,"",(SUMIF(Horo82111[Client],B61,Horo82111[Durée]) / Total)) | B61: DANFREIGHT | C61: =IF(SUMIF(Horo82111[Client],B61,Horo82111[Durée])=0,"",SUMIF(Horo82111[Client],B61,Horo82111[Durée]))
A62: =IF((SUMIF(Horo82111[Client],B62,Horo82111[Durée]) / Total)=0,"",(SUMIF(Horo82111[Client],B62,Horo82111[Durée]) / Total)) | B62: DISSAN | C62: =IF(SUMIF(Horo82111[Client],B62,Horo82111[Durée])=0,"",SUMIF(Horo82111[Client],B62,Horo82111[Durée]))
... A78: =IF((SUMIF(Horo82111[Client],B78,Horo82111[Durée]) / Total)=0,"",(SUMIF(Horo82111[Client],B78,Horo82111[Durée]) / Total)) | B78: ADC | C78: =IF(SUMIF(Horo82111[Client],B78,Horo82111[Durée])=0,"",SUMIF(Horo82111[Client],B78,Horo82111[Durée]))

Sheet Semaine 7-09-2025
B1: ="Semaine du :" -> Semaine du : | C1: 44445 | D1: ="( "&AVERAGE($E$2:$I$2)&" )" -> ( 8 ) | E1: =IFERROR("Lun.: " & TEXT($Y$2,"00%"),"Lun.: 0%") -> Lun.: 29% | F1: =IFERROR("Mar.: " & TEXT($Z$2,"00%"),"Mar.: 0%") -> Mar.: 41% | G1: =IFERROR("Mer.: " & TEXT($AA$2,"00%"),"Mer.: 0%") -> Mer.: 81% | H1: =IFERROR("Jeu.: " & TEXT($AB$2,"00%"),"Jeu.: 0%") -> Jeu.: 40% | I1: =IFERROR("Ven.: " & TEXT($AC$2,"00%"),"Ven.: 0%") -> Ven.: 40% | J1: =IFERROR("S.: " & TEXT($AD$2,"00%"),"S.: 0%") -> S.: 00% | K1: =IFERROR("D.: " & TEXT($AE$2,"00%"), "D.: 0%") -> D.: 00% | M1: =M2/Total -> 0.48051948 | N1: =N2/$C$2 -> 0.0125 | O1: =O2/$C$2 -> 0.08125 | P1: =P2/$C$2 -> 0.325 | Q1: =Q2/$C$2 -> 0.11875 | R1: =R2/$C$2 -> 0 | S1: =S2/$C$2 -> 0 | T1: =T2/$C$2 -> 0 | U1: =U2/$C$2 -> 0 | X1: =SUM(#REF!) -> #REF! | Y1: Lundi | Z1: Mardi | AA1: Mercredi | AB1: Jeudi | AC1: Vendredi | AD1: Samedi | AE1: Dimanche
B2: =X2 -> 0.4625 | C2: =SUM(Horo82109[Durée]) -> 40 | D2: =ROUND(SUM(Horo82109[T]),2) & " / " & ROUND($C$2-SUM(Horo82109[T]),2) -> 40 / 0 | E2: =SUMIF(Horo82109[Jour],"Lundi",Horo82109[Durée]) -> 7.75 | F2: =SUMIF(Horo82109[Jour],"Mardi",Horo82109[Durée]) -> 8 | G2: =SUMIF(Horo82109[Jour],"Mercredi",Horo82109[Durée]) -> 8 | H2: =SUMIF(Horo82109[Jour],"Jeudi",Horo82109[Durée]) -> 8.75 | I2: =SUMIF(Horo82109[Jour],"Vendredi",Horo82109[Durée]) -> 7.5 | J2: =SUMIF(Horo82109[Jour],"Samedi",Horo82109[Durée]) -> 0 | K2: =SUMIF(Horo82109[Jour],"Dimanche",Horo82109[Durée]) -> 0 | M2: =SUM(Horo82109[GPF]) -> 18.5 | N2: =SUM(Horo82109[RI]) -> 0.5 | O2: =SUM(Horo82109[GB]) -> 3.25 | P2: =SUM(Horo82109[RD]) -> 13 | Q2: =SUM(Horo82109[FG]) -> 4.75 | R2: =SUM(Horo82109[CONGÉ]) -> 0 | S2: =SUM(Horo82109[PS]) -> 0 | T2: =SUM(Horo82109[TD]) -> 0 | U2: =SUM(Horo82109[N/C]) -> 0 | V2: =(C2-(SUM(N2:T2))) -> 18.5 | W2: =C2-(R2+S2+T2) -> 40 | X2: =V2/W2 -> 0.4625 | Y2: =SUMIF(Horo82109[Jour],"Lundi",Horo82109[GPF]) / $E$2 -> 0.29032258 | Z2: =SUMIF(Horo82109[Jour],"Mardi",Horo82109[GPF]) / $F$2 -> 0.40625 | AA2: =SUMIF(Horo82109[Jour],"Mercredi",Horo82109[GPF]) / $G$2 -> 0.8125 | AB2: =SUMIF(Horo82109[Jour],"Jeudi",Horo82109[GPF]) / $H$2 -> 0.4 | AC2: =SUMIF(Horo82109[Jour],"Vendredi",Horo82109[GPF]) / $I$2 -> 0.4 | AD2: =IFERROR(SUMIF(Horo82109[Jour],"Samedi",Horo82109[GPF]) / $J$2,0) -> 0 | AE2: =IFERROR(SUMIF(Horo82109[Jour],"Dimanche",Horo82109[GPF]) / $K$2,0) -> 0
A3: O | B3: Date | C3: Jour | D3: Début | E3: Fin | F3: Client | G3: Tâche | H3: Description | I3: Description 2 | J3: Durée | K3: hrs | L3: % | M3: GPF | N3: RI | O3: GB | P3: RD | Q3: FG | R3: CONGÉ | S3: PS | T3: TD | U3: N/C | V3: W | W3: T | X3: Durée (60)2
A4: o | B4: =IF(Horo82109[[#This Row],[Jour]]="Lundi",$C$1+1, IF(Horo82109[[#This Row],[Jour]]="Mardi",$C$1+2, IF(Horo82109[[#This Row],[Jour]]="Mercredi",$C$1+3, IF(Horo82109[[#This Row],[Jour]]="Jeudi",$C$1+4, IF(Horo82109[[#This Row],[Jour]]="Vendredi",$C$1+5, IF(Horo82109[[#This Row],[Jour]]="Samedi",$C$1+6, IF(Horo82109[[#This Row],[Jour]]="Dimanche",$C$1, ))))))) -> 44446 | C4: Lundi | D4: 0.33333333 | E4: 0.36458333 | F4: FORGESTIK | G4: GB | H4: . | J4: =IF(Horo82109[[#This Row],[Début]]=0,"",(Horo82109[[#This Row],[Durée (60)2]]-INT(Horo82109[[#This Row],[Durée (60)2]]))*24) -> 0.75 | K4: =SUMIF(Horo82109[Jour],C4,Horo82109[Durée]) -> 7.75 | L4: =IFERROR(SUMIF(Horo82109[[#This Row],[Jour]],Horo82109[[#This Row],[Jour]],Horo82109[[#This Row],[GPF]]) / Horo82109[[#This Row],[hrs]],"") -> 0 | M4: =IF("GPF"=Horo82109[[#This Row],[Tâche]],Horo82109[[#This Row],[Durée]],"") | N4: =IF("RI"=Horo82109[[#This Row],[Tâche]],Horo82109[[#This Row],[Durée]],"") | O4: =IF("GB"=Horo82109[[#This Row],[Tâche]],Horo82109[[#This Row],[Durée]],"") -> 0.75 | P4: =IF("RD"=Horo82109[[#This Row],[Tâche]],Horo82109[[#This Row],[Durée]],"") | Q4: =IF("FG"=Horo82109[[#This Row],[Tâche]],Horo82109[[#This Row],[Durée]],"") | R4: =IF("CONGÉ"=Horo82109[[#This Row],[Tâche]],Horo82109[[#This Row],[Durée]],"") | S4: =IF("PS"=Horo82109[[#This Row],[Tâche]],Horo82109[[#This Row],[Durée]],"") | T4: =IF("TD"=Horo82109[[#This Row],[Tâche]],Horo82109[[#This Row],[Durée]],"") | U4: =IF("N/C"=Horo82109[[#This Row],[Tâche]],Horo82109[[#This Row],[Durée]],"") | W4: =IF(Horo82109[[#This Row],[O]]="o",Horo82109[[#This Row],[Durée]],".") -> 0.75 | X4: =IF(Horo82109[[#This Row],[Début]]=0,"",Horo82109[[#This Row],[Fin]]-Horo82109[[#This Row],[Début]]) -> 0.03125
A5: o | B5: =IF(Horo82109[[#This Row],[Jour]]="Lundi",$C$1+1, IF(Horo82109[[#This Row],[Jour]]="Mardi",$C$1+2, IF(Horo82109[[#This Row],[Jour]]="Mercredi",$C$1+3, IF(Horo82109[[#This Row],[Jour]]="Jeudi",$C$1+4, IF(Horo82109[[#This Row],[Jour]]="Vendredi",$C$1+5, IF(Horo82109[[#This Row],[Jour]]="Samedi",$C$1+6, IF(Horo82109[[#This Row],[Jour]]="Dimanche",$C$1, ))))))) -> 44446 | C5: Lundi | D5: 0.36458333 | E5: 0.38541667 | F5: FORGESTIK | G5: RI | H5: Réunion OPS | J5: =IF(Horo82109[[#This Row],[Début]]=0,"",(Horo82109[[#This Row],[Durée (60)2]]-INT(Horo82109[[#This Row],[Durée (60)2]]))*24) -> 0.5 | K5: =SUMIF(Horo82109[Jour],C5,Horo82109[Durée]) -> 7.75 | L5: =IFERROR(SUMIF(Horo82109[[#This Row],[Jour]],Horo82109[[#This Row],[Jour]],Horo82109[[#This Row],[GPF]]) / Horo82109[[#This Row],[hrs]],"") -> 0 | M5: =IF("GPF"=Horo82109[[#This Row],[Tâche]],Horo82109[[#This Row],[Durée]],"") | N5: =IF("RI"=Horo82109[[#This Row],[Tâche]],Horo82109[[#This Row],[Durée]],"") -> 0.5 | O5: =IF("GB"=Horo82109[[#This Row],[Tâche]],Horo82109[[#This Row],[Durée]],"") | P5: =IF("RD"=Horo82109[[#This Row],[Tâche]],Horo82109[[#This Row],[Durée]],"") | Q5: =IF("FG"=Horo82109[[#This Row],[Tâche]],Horo82109[[#This Row],[Durée]],"") | R5: =IF("CONGÉ"=Horo82109[[#This Row],[Tâche]],Horo82109[[#This Row],[Durée]],"") | S5: =IF("PS"=Horo82109[[#This Row],[Tâche]],Horo82109[[#This Row],[Durée]],"") | T5: =IF("TD"=Horo82109[[#This Row],[Tâche]],Horo82109[[#This Row],[Durée]],"") | U5: =IF("N/C"=Horo82109[[#This Row],[Tâche]],Horo82109[[#This Row],[Durée]],"") | W5: =IF(Horo82109[[#This Row],[O]]="o",Horo82109[[#This Row],[Durée]],".") -> 0.5 | X5: =IF(Horo82109[[#This Row],[Début]]=0,"",Horo82109[[#This Row],[Fin]]-Horo82109[[#This Row],[Début]]) -> 0.020833333
A6: o | B6: =IF(Horo82109[[#This Row],[Jour]]="Lundi",$C$1+1, IF(Horo82109[[#This Row],[Jour]]="Mardi",$C$1+2, IF(Horo82109[[#This Row],[Jour]]="Mercredi",$C$1+3, IF(Horo82109[[#This Row],[Jour]]="Jeudi",$C$1+4, IF(Horo82109[[#This Row],[Jour]]="Vendredi",$C$1+5, IF(Horo82109[[#This Row],[Jour]]="Samedi",$C$1+6, IF(Horo82109[[#This Row],[Jour]]="Dimanche",$C$1, ))))))) -> 44446 | C6: Lundi | D6: 0.38541667 | E6: 0.39583333 | F6: FORGESTIK | G6: GB | H6: . | J6: =IF(Horo82109[[#This Row],[Début]]=0,"",(Horo82109[[#This Row],[Durée (60)2]]-INT(Horo82109[[#This Row],[Durée (60)2]]))*24) -> 0.25 | K6: =SUMIF(Horo82109[Jour],C6,Horo82109[Durée]) -> 7.75 | L6: =IFERROR(SUMIF(Horo82109[[#This Row],[Jour]],Horo82109[[#This Row],[Jour]],Horo82109[[#This Row],[GPF]]) / Horo82109[[#This Row],[hrs]],"") -> 0 | M6: =IF("GPF"=Horo82109[[#This Row],[Tâche]],Horo82109[[#This Row],[Durée]],"") | N6: =IF("RI"=Horo82109[[#This Row],[Tâche]],Horo82109[[#This Row],[Durée]],"") | O6: =IF("GB"=Horo82109[[#This Row],[Tâche]],Horo82109[[#This Row],[Durée]],"") -> 0.25 | P6: =IF("RD"=Horo82109[[#This Row],[Tâche]],Horo82109[[#This Row],[Durée]],"") | Q6: =IF("FG"=Horo82109[[#This Row],[Tâche]],Horo82109[[#This Row],[Durée]],"") | R6: =IF("CONGÉ"=Horo82109[[#This Row],[Tâche]],Horo82109[[#This Row],[Durée]],"") | S6: =IF("PS"=Horo82109[[#This Row],[Tâche]],Horo82109[[#This Row],[Durée]],"") | T6: =IF("TD"=Horo82109[[#This Row],[Tâche]],Horo82109[[#This Row],[Durée]],"") | U6: =IF("N/C"=Horo82109[[#This Row],[Tâche]],Horo82109[[#This Row],[Durée]],"") | W6: =IF(Horo82109[[#This Row],[O]]="o",Horo82109[[#This Row],[Durée]],".") -> 0.25 | X6: =IF(Horo82109[[#This Row],[Début]]=0,"",Horo82109[[#This Row],[Fin]]-Horo82109[[#This Row],[Début]]) -> 0.010416667
A7: o | B7: =IF(Horo82109[[#This Row],[Jour]]="Lundi",$C$1+1, IF(Horo82109[[#This Row],[Jour]]="Mardi",$C$1+2, IF(Horo82109[[#This Row],[Jour]]="Mercredi",$C$1+3, IF(Horo82109[[#This Row],[Jour]]="Jeudi",$C$1+4, IF(Horo82109[[#This Row],[Jour]]="Vendredi",$C$1+5, IF(Horo82109[[#This Row],[Jour]]="Samedi",$C$1+6, IF(Horo82109[[#This Row],[Jour]]="Dimanche",$C$1, ))))))) -> 44446 | C7: Lundi | D7: 0.39583333 | E7: 0.40625 | F7: SUPREME ŒUF | G7: GPF | H7: Appel avec | I7: Vincent - Nathalie - Francine - Reda : Serveurs Produmex WMS | J7: =IF(Horo82109[[#This Row],[Début]]=0,"",(Horo82109[[#This Row],[Durée (60)2]]-INT(Horo82109[[#This Row],[Durée (60)2]]))*24) -> 0.25 | K7: =SUMIF(Horo82109[Jour],C7,Horo82109[Durée]) -> 7.75 | L7: =IFERROR(SUMIF(Horo82109[[#This Row],[Jour]],Horo82109[[#This Row],[Jour]],Horo82109[[#This Row],[GPF]]) / Horo82109[[#This Row],[hrs]],"") -> 0.032258065 | M7: =IF("GPF"=Horo82109[[#This Row],[Tâche]],Horo82109[[#This Row],[Durée]],"") -> 0.25 | N7: =IF("RI"=Horo82109[[#This Row],[Tâche]],Horo82109[[#This Row],[Durée]],"") | O7: =IF("GB"=Horo82109[[#This Row],[Tâche]],Horo82109[[#This Row],[Durée]],"") | P7: =IF("RD"=Horo82109[[#This Row],[Tâche]],Horo82109[[#This Row],[Durée]],"") | Q7: =IF("FG"=Horo82109[[#This Row],[Tâche]],Horo82109[[#This Row],[Durée]],"") | R7: =IF("CONGÉ"=Horo82109[[#This Row],[Tâche]],Horo82109[[#This Row],[Durée]],"") | S7: =IF("PS"=Horo82109[[#This Row],[Tâche]],Horo82109[[#This Row],[Durée]],"") | T7: =IF("TD"=Horo82109[[#This Row],[Tâche]],Horo82109[[#This Row],[Durée]],"") | U7: =IF("N/C"=Horo82109[[#This Row],[Tâche]],Horo82109[[#This Row],[Durée]],"") | W7: =IF(Horo82109[[#This Row],[O]]="o",Horo82109[[#This Row],[Durée]],".") -> 0.25 | X7: =IF(Horo82109[[#This Row],[Début]]=0,"",Horo82109[[#This Row],[Fin]]-Horo82109[[#This Row],[Début]]) -> 0.010416667
A8: o | B8: =IF(Horo82109[[#This Row],[Jour]]="Lundi",$C$1+1, IF(Horo82109[[#This Row],[Jour]]="Mardi",$C$1+2, IF(Horo82109[[#This Row],[Jour]]="Mercredi",$C$1+3, IF(Horo82109[[#This Row],[Jour]]="Jeudi",$C$1+4, IF(Horo82109[[#This Row],[Jour]]="Vendredi",$C$1+5, IF(Horo82109[[#This Row],[Jour]]="Samedi",$C$1+6, IF(Horo82109[[#This Row],[Jour]]="Dimanche",$C$1, ))))))) -> 44446 | C8: Lundi | D8: 0.41666667 | E8: 0.5 | F8: SUPREME ŒUF | G8: RD | H8: Billet | I8: Préparation Billet Boyum pour les articles consignable | J8: =IF(Horo82109[[#This Row],[Début]]=0,"",(Horo82109[[#This Row],[Durée (60)2]]-INT(Horo82109[[#This Row],[Durée (60)2]]))*24) -> 2 | K8: =SUMIF(Horo82109[Jour],C8,Horo82109[Durée]) -> 7.75 | L8: =IFERROR(SUMIF(Horo82109[[#This Row],[Jour]],Horo82109[[#This Row],[Jour]],Horo82109[[#This Row],[GPF]]) / Horo82109[[#This Row],[hrs]],"") -> 0 | M8: =IF("GPF"=Horo82109[[#This Row],[Tâche]],Horo82109[[#This Row],[Durée]],"") | N8: =IF("RI"=Horo82109[[#This Row],[Tâche]],Horo82109[[#This Row],[Durée]],"") | O8: =IF("GB"=Horo82109[[#This Row],[Tâche]],Horo82109[[#This Row],[Durée]],"") | P8: =IF("RD"=Horo82109[[#This Row],[Tâche]],Horo82109[[#This Row],[Durée]],"") -> 2 | Q8: =IF("FG"=Horo82109[[#This Row],[Tâche]],Horo82109[[#This Row],[Durée]],"") | R8: =IF("CONGÉ"=Horo82109[[#This Row],[Tâche]],Horo82109[[#This Row],[Durée]],"") | S8: =IF("PS"=Horo82109[[#This Row],[Tâche]],Horo82109[[#This Row],[Durée]],"") | T8: =IF("TD"=Horo82109[[#This Row],[Tâche]],Horo82109[[#This Row],[Durée]],"") | U8: =IF("N/C"=Horo82109[[#This Row],[Tâche]],Horo82109[[#This Row],[Durée]],"") | W8: =IF(Horo82109[[#This Row],[O]]="o",Horo82109[[#This Row],[Durée]],".") -> 2 | X8: =IF(Horo82109[[#This Row],[Début]]=0,"",Horo82109[[#This Row],[Fin]]-Horo82109[[#This Row],[Début]]) -> 0.083333333
A9: o | B9: =IF(Horo82109[[#This Row],[Jour]]="Lundi",$C$1+1, IF(Horo82109[[#This Row],[Jour]]="Mardi",$C$1+2, IF(Horo82109[[#This Row],[Jour]]="Mercredi",$C$1+3, IF(Horo82109[[#This Row],[Jour]]="Jeudi",$C$1+4, IF(Horo82109[[#This Row],[Jour]]="Vendredi",$C$1+5, IF(Horo82109[[#This Row],[Jour]]="Samedi",$C$1+6, IF(Horo82109[[#This Row],[Jour]]="Dimanche",$C$1, ))))))) -> 44446 | C9: Lundi | D9: 0.57291667 | E9: 0.65625 | F9: ATLANTIS POMPE | G9: GPF | H9: Billet | I9: T20250915.0007 - Changer les générateurs de LOG de DEBUG à WARN sur les 21 serveurs. Modifier les générateurs de log file pour réduire le nombre d'écriture dans les fichiers. - 2 heures total / 6 minutes par serveurs | J9: =IF(Horo82109[[#This Row],[Début]]=0,"",(Horo82109[[#This Row],[Durée (60)2]]-INT(Horo82109[[#This Row],[Durée (60)2]]))*24) -> 2 | K9: =SUMIF(Horo82109[Jour],C9,Horo82109[Durée]) -> 7.75 | L9: =IFERROR(SUMIF(Horo82109[[#This Row],[Jour]],Horo82109[[#This Row],[Jour]],Horo82109[[#This Row],[GPF]]) / Horo82109[[#This Row],[hrs]],"") -> 0.25806452 | M9: =IF("GPF"=Horo82109[[#This Row],[Tâche]],Horo82109[[#This Row],[Durée]],"") -> 2 | N9: =IF("RI"=Horo82109[[#This Row],[Tâche]],Horo82109[[#This Row],[Durée]],"") | O9: =IF("GB"=Horo82109[[#This Row],[Tâche]],Horo82109[[#This Row],[Durée]],"") | P9: =IF("RD"=Horo82109[[#This Row],[Tâche]],Horo82109[[#This Row],[Durée]],"") | Q9: =IF("FG"=Horo82109[[#This Row],[Tâche]],Horo82109[[#This Row],[Durée]],"") | R9: =IF("CONGÉ"=Horo82109[[#This Row],[Tâche]],Horo82109[[#This Row],[Durée]],"") | S9: =IF("PS"=Horo82109[[#This Row],[Tâche]],Horo82109[[#This Row],[Durée]],"") | T9: =IF("TD"=Horo82109[[#This Row],[Tâche]],Horo82109[[#This Row],[Durée]],"") | U9: =IF("N/C"=Horo82109[[#This Row],[Tâche]],Horo82109[[#This Row],[Durée]],"") | W9: =IF(Horo82109[[#This Row],[O]]="o",Horo82109[[#This Row],[Durée]],".") -> 2 | X9: =IF(Horo82109[[#This Row],[Début]]=0,"",Horo82109[[#This Row],[Fin]]-Horo82109[[#This Row],[Début]]) -> 0.083333333
A10: o | B10: =IF(Horo82109[[#This Row],[Jour]]="Lundi",$C$1+1, IF(Horo82109[[#This Row],[Jour]]="Mardi",$C$1+2, IF(Horo82109[[#This Row],[Jour]]="Mercredi",$C$1+3, IF(Horo82109[[#This Row],[Jour]]="Jeudi",$C$1+4, IF(Horo82109[[#This Row],[Jour]]="Vendredi",$C$1+5, IF(Horo82109[[#This Row],[Jour]]="Samedi",$C$1+6, IF(Horo82109[[#This Row],[Jour]]="Dimanche",$C$1, ))))))) -> 44446 | C10: Lundi | D10: 0.65625 | E10: 0.69791667 | F10: FORGESTIK | G10: RD | H10: Preuve de concept | J10: =IF(Horo82109[[#This Row],[Début]]=0,"",(Horo82109[[#This Row],[Durée (60)2]]-INT(Horo82109[[#This Row],[Durée (60)2]]))*24) -> 1 | K10: =SUMIF(Horo82109[Jour],C10,Horo82109[Durée]) -> 7.75 | L10: =IFERROR(SUMIF(Horo82109[[#This Row],[Jour]],Horo82109[[#This Row],[Jour]],Horo82109[[#This Row],[GPF]]) / Horo82109[[#This Row],[hrs]],"") -> 0 | M10: =IF("GPF"=Horo82109[[#This Row],[Tâche]],Horo82109[[#This Row],[Durée]],"") | N10: =IF("RI"=Horo82109[[#This Row],[Tâche]],Horo82109[[#This Row],[Durée]],"") | O10: =IF("GB"=Horo82109[[#This Row],[Tâche]],Horo82109[[#This Row],[Durée]],"") | P10: =IF("RD"=Horo82109[[#This Row],[Tâche]],Horo82109[[#This Row],[Durée]],"") -> 1 | Q10: =IF("FG"=Horo82109[[#This Row],[Tâche]],Horo82109[[#This Row],[Durée]],"") | R10: =IF("CONGÉ"=Horo82109[[#This Row],[Tâche]],Horo82109[[#This Row],[Durée]],"") | S10: =IF("PS"=Horo82109[[#This Row],[Tâche]],Horo82109[[#This Row],[Durée]],"") | T10: =IF("TD"=Horo82109[[#This Row],[Tâche]],Horo82109[[#This Row],[Durée]],"") | U10: =IF("N/C"=Horo82109[[#This Row],[Tâche]],Horo82109[[#This Row],[Durée]],"") | W10: =IF(Horo82109[[#This Row],[O]]="o",Horo82109[[#This Row],[Durée]],".") -> 1 | X10: =IF(Horo82109[[#This Row],[Début]]=0,"",Horo82109[[#This Row],[Fin]]-Horo82109[[#This Row],[Début]]) -> 0.041666667
A11: o | B11: =IF(Horo82109[[#This Row],[Jour]]="Lundi",$C$1+1, IF(Horo82109[[#This Row],[Jour]]="Mardi",$C$1+2, IF(Horo82109[[#This Row],[Jour]]="Mercredi",$C$1+3, IF(Horo82109[[#This Row],[Jour]]="Jeudi",$C$1+4, IF(Horo82109[[#This Row],[Jour]]="Vendredi",$C$1+5, IF(Horo82109[[#This Row],[Jour]]="Samedi",$C$1+6, IF(Horo82109[[#This Row],[Jour]]="Dimanche",$C$1, ))))))) -> 44446 | C11: Lundi | D11: 0.69791667 | E11: 0.73958333 | F11: FORGESTIK | G11: FG | H11: Formation C# | J11: =IF(Horo82109[[#This Row],[Début]]=0,"",(Horo82109[[#This Row],[Durée (60)2]]-INT(Horo82109[[#This Row],[Durée (60)2]]))*24) -> 1 | K11: =SUMIF(Horo82109[Jour],C11,Horo82109[Durée]) -> 7.75 | L11: =IFERROR(SUMIF(Horo82109[[#This Row],[Jour]],Horo82109[[#This Row],[Jour]],Horo82109[[#This Row],[GPF]]) / Horo82109[[#This Row],[hrs]],"") -> 0 | M11: =IF("GPF"=Horo82109[[#This Row],[Tâche]],Horo82109[[#This Row],[Durée]],"") | N11: =IF("RI"=Horo82109[[#This Row],[Tâche]],Horo82109[[#This Row],[Durée]],"") | O11: =IF("GB"=Horo82109[[#This Row],[Tâche]],Horo82109[[#This Row],[Durée]],"") | P11: =IF("RD"=Horo82109[[#This Row],[Tâche]],Horo82109[[#This Row],[Durée]],"") | Q11: =IF("FG"=Horo82109[[#This Row],[Tâche]],Horo82109[[#This Row],[Durée]],"") -> 1 | R11: =IF("CONGÉ"=Horo82109[[#This Row],[Tâche]],Horo82109[[#This Row],[Durée]],"") | S11: =IF("PS"=Horo82109[[#This Row],[Tâche]],Horo82109[[#This Row],[Durée]],"") | T11: =IF("TD"=Horo82109[[#This Row],[Tâche]],Horo82109[[#This Row],[Durée]],"") | U11: =IF("N/C"=Horo82109[[#This Row],[Tâche]],Horo82109[[#This Row],[Durée]],"") | W11: =IF(Horo82109[[#This Row],[O]]="o",Horo82109[[#This Row],[Durée]],".") -> 1 | X11: =IF(Horo82109[[#This Row],[Début]]=0,"",Horo82109[[#This Row],[Fin]]-Horo82109[[#This Row],[Début]]) -> 0.041666667
A12: o | B12: =IF(Horo82109[[#This Row],[Jour]]="Lundi",$C$1+1, IF(Horo82109[[#This Row],[Jour]]="Mardi",$C$1+2, IF(Horo82109[[#This Row],[Jour]]="Mercredi",$C$1+3, IF(Horo82109[[#This Row],[Jour]]="Jeudi",$C$1+4, IF(Horo82109[[#This Row],[Jour]]="Vendredi",$C$1+5, IF(Horo82109[[#This Row],[Jour]]="Samedi",$C$1+6, IF(Horo82109[[#This Row],[Jour]]="Dimanche",$C$1, ))))))) -> 44447 | C12: Mardi | D12: 0.33333333 | E12: 0.35416667 | F12: FORGESTIK | G12: GB | H12: Analyse fonctionnelle | I12: Autotask - gestion fichiers | J12: =IF(Horo82109[[#This Row],[Début]]=0,"",(Horo82109[[#This Row],[Durée (60)2]]-INT(Horo82109[[#This Row],[Durée (60)2]]))*24) -> 0.5 | K12: =SUMIF(Horo82109[Jour],C12,Horo82109[Durée]) -> 8 | L12: =IFERROR(SUMIF(Horo82109[[#This Row],[Jour]],Horo82109[[#This Row],[Jour]],Horo82109[[#This Row],[GPF]]) / Horo82109[[#This Row],[hrs]],"") -> 0 | M12: =IF("GPF"=Horo82109[[#This Row],[Tâche]],Horo82109[[#This Row],[Durée]],"") | N12: =IF("RI"=Horo82109[[#This Row],[Tâche]],Horo82109[[#This Row],[Durée]],"") | O12: =IF("GB"=Horo82109[[#This Row],[Tâche]],Horo82109[[#This Row],[Durée]],"") -> 0.5 | P12: =IF("RD"=Horo82109[[#This Row],[Tâche]],Horo82109[[#This Row],[Durée]],"") | Q12: =IF("FG"=Horo82109[[#This Row],[Tâche]],Horo82109[[#This Row],[Durée]],"") | R12: =IF("CONGÉ"=Horo82109[[#This Row],[Tâche]],Horo82109[[#This Row],[Durée]],"") | S12: =IF("PS"=Horo82109[[#This Row],[Tâche]],Horo82109[[#This Row],[Durée]],"") | T12: =IF("TD"=Horo82109[[#This Row],[Tâche]],Horo82109[[#This Row],[Durée]],"") | U12: =IF("N/C"=Horo82109[[#This Row],[Tâche]],Horo82109[[#This Row],[Durée]],"") | W12: =IF(Horo82109[[#This Row],[O]]="o",Horo82109[[#This Row],[Durée]],".") -> 0.5 | X12: =IF(Horo82109[[#This Row],[Début]]=0,"",Horo82109[[#This Row],[Fin]]-Horo82109[[#This Row],[Début]]) -> 0.020833333
A13: o | B13: =IF(Horo82109[[#This Row],[Jour]]="Lundi",$C$1+1, IF(Horo82109[[#This Row],[Jour]]="Mardi",$C$1+2, IF(Horo82109[[#This Row],[Jour]]="Mercredi",$C$1+3, IF(Horo82109[[#This Row],[Jour]]="Jeudi",$C$1+4, IF(Horo82109[[#This Row],[Jour]]="Vendredi",$C$1+5, IF(Horo82109[[#This Row],[Jour]]="Samedi",$C$1+6, IF(Horo82109[[#This Row],[Jour]]="Dimanche",$C$1, ))))))) -> 44447 | C13: Mardi | D13: 0.35416667 | E13: 0.36458333 | F13: AGENCE GRAVEL | G13: GPF | H13: Suivi de projet | J13: =IF(Horo82109[[#This Row],[Début]]=0,"",(Horo82109[[#This Row],[Durée (60)2]]-INT(Horo82109[[#This Row],[Durée (60)2]]))*24) -> 0.25 | K13: =SUMIF(Horo82109[Jour],C13,Horo82109[Durée]) -> 8 | L13: =IFERROR(SUMIF(Horo82109[[#This Row],[Jour]],Horo82109[[#This Row],[Jour]],Horo82109[[#This Row],[GPF]]) / Horo82109[[#This Row],[hrs]],"") -> 0.03125 | M13: =IF("GPF"=Horo82109[[#This Row],[Tâche]],Horo82109[[#This Row],[Durée]],"") -> 0.25 | N13: =IF("RI"=Horo82109[[#This Row],[Tâche]],Horo82109[[#This Row],[Durée]],"") | O13: =IF("GB"=Horo82109[[#This Row],[Tâche]],Horo82109[[#This Row],[Durée]],"") | P13: =IF("RD"=Horo82109[[#This Row],[Tâche]],Horo82109[[#This Row],[Durée]],"") | Q13: =IF("FG"=Horo82109[[#This Row],[Tâche]],Horo82109[[#This Row],[Durée]],"") | R13: =IF("CONGÉ"=Horo82109[[#This Row],[Tâche]],Horo82109[[#This Row],[Durée]],"") | S13: =IF("PS"=Horo82109[[#This Row],[Tâche]],Horo82109[[#This Row],[Durée]],"") | T13: =IF("TD"=Horo82109[[#This Row],[Tâche]],Horo82109[[#This Row],[Durée]],"") | U13: =IF("N/C"=Horo82109[[#This Row],[Tâche]],Horo82109[[#This Row],[Durée]],"") | W13: =IF(Horo82109[[#This Row],[O]]="o",Horo82109[[#This Row],[Durée]],".") -> 0.25 | X13: =IF(Horo82109[[#This Row],[Début]]=0,"",Horo82109[[#This Row],[Fin]]-Horo82109[[#This Row],[Début]]) -> 0.010416667
A14: o | B14: =IF(Horo82109[[#This Row],[Jour]]="Lundi",$C$1+1, IF(Horo82109[[#This Row],[Jour]]="Mardi",$C$1+2, IF(Horo82109[[#This Row],[Jour]]="Mercredi",$C$1+3, IF(Horo82109[[#This Row],[Jour]]="Jeudi",$C$1+4, IF(Horo82109[[#This Row],[Jour]]="Vendredi",$C$1+5, IF(Horo82109[[#This Row],[Jour]]="Samedi",$C$1+6, IF(Horo82109[[#This Row],[Jour]]="Dimanche",$C$1, ))))))) -> 44447 | C14: Mardi | D14: 0.36458333 | E14: 0.39583333 | F14: FORGESTIK | G14: FG | H14: Formation SAP -PMX | J14: =IF(Horo82109[[#This Row],[Début]]=0,"",(Horo82109[[#This Row],[Durée (60)2]]-INT(Horo82109[[#This Row],[Durée (60)2]]))*24) -> 0.75 | K14: =SUMIF(Horo82109[Jour],C14,Horo82109[Durée]) -> 8 | L14: =IFERROR(SUMIF(Horo82109[[#This Row],[Jour]],Horo82109[[#This Row],[Jour]],Horo82109[[#This Row],[GPF]]) / Horo82109[[#This Row],[hrs]],"") -> 0 | M14: =IF("GPF"=Horo82109[[#This Row],[Tâche]],Horo82109[[#This Row],[Durée]],"") | N14: =IF("RI"=Horo82109[[#This Row],[Tâche]],Horo82109[[#This Row],[Durée]],"") | O14: =IF("GB"=Horo82109[[#This Row],[Tâche]],Horo82109[[#This Row],[Durée]],"") | P14: =IF("RD"=Horo82109[[#This Row],[Tâche]],Horo82109[[#This Row],[Durée]],"") | Q14: =IF("FG"=Horo82109[[#This Row],[Tâche]],Horo82109[[#This Row],[Durée]],"") -> 0.75 | R14: =IF("CONGÉ"=Horo82109[[#This Row],[Tâche]],Horo82109[[#This Row],[Durée]],"") | S14: =IF("PS"=Horo82109[[#This Row],[Tâche]],Horo82109[[#This Row],[Durée]],"") | T14: =IF("TD"=Horo82109[[#This Row],[Tâche]],Horo82109[[#This Row],[Durée]],"") | U14: =IF("N/C"=Horo82109[[#This Row],[Tâche]],Horo82109[[#This Row],[Durée]],"") | W14: =IF(Horo82109[[#This Row],[O]]="o",Horo82109[[#This Row],[Durée]],".") -> 0.75 | X14: =IF(Horo82109[[#This Row],[Début]]=0,"",Horo82109[[#This Row],[Fin]]-Horo82109[[#This Row],[Début]]) -> 0.03125
A15: o | B15: =IF(Horo82109[[#This Row],[Jour]]="Lundi",$C$1+1, IF(Horo82109[[#This Row],[Jour]]="Mardi",$C$1+2, IF(Horo82109[[#This Row],[Jour]]="Mercredi",$C$1+3, IF(Horo82109[[#This Row],[Jour]]="Jeudi",$C$1+4, IF(Horo82109[[#This Row],[Jour]]="Vendredi",$C$1+5, IF(Horo82109[[#This Row],[Jour]]="Samedi",$C$1+6, IF(Horo82109[[#This Row],[Jour]]="Dimanche",$C$1, ))))))) -> 44447 | C15: Mardi | D15: 0.39583333 | E15: 0.41666667 | F15: RBF | G15: GPF | H15: Suivi de projet | J15: =IF(Horo82109[[#This Row],[Début]]=0,"",(Horo82109[[#This Row],[Durée (60)2]]-INT(Horo82109[[#This Row],[Durée (60)2]]))*24) -> 0.5 | K15: =SUMIF(Horo82109[Jour],C15,Horo82109[Durée]) -> 8 | L15: =IFERROR(SUMIF(Horo82109[[#This Row],[Jour]],Horo82109[[#This Row],[Jour]],Horo82109[[#This Row],[GPF]]) / Horo82109[[#This Row],[hrs]],"") -> 0.0625 | M15: =IF("GPF"=Horo82109[[#This Row],[Tâche]],Horo82109[[#This Row],[Durée]],"") -> 0.5 | N15: =IF("RI"=Horo82109[[#This Row],[Tâche]],Horo82109[[#This Row],[Durée]],"") | O15: =IF("GB"=Horo82109[[#This Row],[Tâche]],Horo82109[[#This Row],[Durée]],"") | P15: =IF("RD"=Horo82109[[#This Row],[Tâche]],Horo82109[[#This Row],[Durée]],"") | Q15: =IF("FG"=Horo82109[[#This Row],[Tâche]],Horo82109[[#This Row],[Durée]],"") | R15: =IF("CONGÉ"=Horo82109[[#This Row],[Tâche]],Horo82109[[#This Row],[Durée]],"") | S15: =IF("PS"=Horo82109[[#This Row],[Tâche]],Horo82109[[#This Row],[Durée]],"") | T15: =IF("TD"=Horo82109[[#This Row],[Tâche]],Horo82109[[#This Row],[Durée]],"") | U15: =IF("N/C"=Horo82109[[#This Row],[Tâche]],Horo82109[[#This Row],[Durée]],"") | W15: =IF(Horo82109[[#This Row],[O]]="o",Horo82109[[#This Row],[Durée]],".") -> 0.5 | X15: =IF(Horo82109[[#This Row],[Début]]=0,"",Horo82109[[#This Row],[Fin]]-Horo82109[[#This Row],[Début]]) -> 0.020833333
A16: o | B16: =IF(Horo82109[[#This Row],[Jour]]="Lundi",$C$1+1, IF(Horo82109[[#This Row],[Jour]]="Mardi",$C$1+2, IF(Horo82109[[#This Row],[Jour]]="Mercredi",$C$1+3, IF(Horo82109[[#This Row],[Jour]]="Jeudi",$C$1+4, IF(Horo82109[[#This Row],[Jour]]="Vendredi",$C$1+5, IF(Horo82109[[#This Row],[Jour]]="Samedi",$C$1+6, IF(Horo82109[[#This Row],[Jour]]="Dimanche",$C$1, ))))))) -> 44447 | C16: Mardi | D16: 0.41666667 | E16: 0.4375 | F16: AGENCE GRAVEL | G16: GPF | H16: Appel avec | I16: Vantree | J16: =IF(Horo82109[[#This Row],[Début]]=0,"",(Horo82109[[#This Row],[Durée (60)2]]-INT(Horo82109[[#This Row],[Durée (60)2]]))*24) -> 0.5 | K16: =SUMIF(Horo82109[Jour],C16,Horo82109[Durée]) -> 8 | L16: =IFERROR(SUMIF(Horo82109[[#This Row],[Jour]],Horo82109[[#This Row],[Jour]],Horo82109[[#This Row],[GPF]]) / Horo82109[[#This Row],[hrs]],"") -> 0.0625 | M16: =IF("GPF"=Horo82109[[#This Row],[Tâche]],Horo82109[[#This Row],[Durée]],"") -> 0.5 | N16: =IF("RI"=Horo82109[[#This Row],[Tâche]],Horo82109[[#This Row],[Durée]],"") | O16: =IF("GB"=Horo82109[[#This Row],[Tâche]],Horo82109[[#This Row],[Durée]],"") | P16: =IF("RD"=Horo82109[[#This Row],[Tâche]],Horo82109[[#This Row],[Durée]],"") | Q16: =IF("FG"=Horo82109[[#This Row],[Tâche]],Horo82109[[#This Row],[Durée]],"") | R16: =IF("CONGÉ"=Horo82109[[#This Row],[Tâche]],Horo82109[[#This Row],[Durée]],"") | S16: =IF("PS"=Horo82109[[#This Row],[Tâche]],Horo82109[[#This Row],[Durée]],"") | T16: =IF("TD"=Horo82109[[#This Row],[Tâche]],Horo82109[[#This Row],[Durée]],"") | U16: =IF("N/C"=Horo82109[[#This Row],[Tâche]],Horo82109[[#This Row],[Durée]],"") | W16: =IF(Horo82109[[#This Row],[O]]="o",Horo82109[[#This Row],[Durée]],".") -> 0.5 | X16: =IF(Horo82109[[#This Row],[Début]]=0,"",Horo82109[[#This Row],[Fin]]-Horo82109[[#This Row],[Début]]) -> 0.020833333
A17: o | B17: =IF(Horo82109[[#This Row],[Jour]]="Lundi",$C$1+1, IF(Horo82109[[#This Row],[Jour]]="Mardi",$C$1+2, IF(Horo82109[[#This Row],[Jour]]="Mercredi",$C$1+3, IF(Horo82109[[#This Row],[Jour]]="Jeudi",$C$1+4, IF(Horo82109[[#This Row],[Jour]]="Vendredi",$C$1+5, IF(Horo82109[[#This Row],[Jour]]="Samedi",$C$1+6, IF(Horo82109[[#This Row],[Jour]]="Dimanche",$C$1, ))))))) -> 44447 | C17: Mardi | D17: 0.4375 | E17: 0.47916667 | F17: HYPERTEC | G17: RD | H17: Appel avec | J17: =IF(Horo82109[[#This Row],[Début]]=0,"",(Horo82109[[#This Row],[Durée (60)2]]-INT(Horo82109[[#This Row],[Durée (60)2]]))*24) -> 1 | K17: =SUMIF(Horo82109[Jour],C17,Horo82109[Durée]) -> 8 | L17: =IFERROR(SUMIF(Horo82109[[#This Row],[Jour]],Horo82109[[#This Row],[Jour]],Horo82109[[#This Row],[GPF]]) / Horo82109[[#This Row],[hrs]],"") -> 0 | M17: =IF("GPF"=Horo82109[[#This Row],[Tâche]],Horo82109[[#This Row],[Durée]],"") | N17: =IF("RI"=Horo82109[[#This Row],[Tâche]],Horo82109[[#This Row],[Durée]],"") | O17: =IF("GB"=Horo82109[[#This Row],[Tâche]],Horo82109[[#This Row],[Durée]],"") | P17: =IF("RD"=Horo82109[[#This Row],[Tâche]],Horo82109[[#This Row],[Durée]],"") -> 1 | Q17: =IF("FG"=Horo82109[[#This Row],[Tâche]],Horo82109[[#This Row],[Durée]],"") | R17: =IF("CONGÉ"=Horo82109[[#This Row],[Tâche]],Horo82109[[#This Row],[Durée]],"") | S17: =IF("PS"=Horo82109[[#This Row],[Tâche]],Horo82109[[#This Row],[Durée]],"") | T17: =IF("TD"=Horo82109[[#This Row],[Tâche]],Horo82109[[#This Row],[Durée]],"") | U17: =IF("N/C"=Horo82109[[#This Row],[Tâche]],Horo82109[[#This Row],[Durée]],"") | W17: =IF(Horo82109[[#This Row],[O]]="o",Horo82109[[#This Row],[Durée]],".") -> 1 | X17: =IF(Horo82109[[#This Row],[Début]]=0,"",Horo82109[[#This Row],[Fin]]-Horo82109[[#This Row],[Début]]) -> 0.041666667
A18: o | B18: =IF(Horo82109[[#This Row],[Jour]]="Lundi",$C$1+1, IF(Horo82109[[#This Row],[Jour]]="Mardi",$C$1+2, IF(Horo82109[[#This Row],[Jour]]="Mercredi",$C$1+3, IF(Horo82109[[#This Row],[Jour]]="Jeudi",$C$1+4, IF(Horo82109[[#This Row],[Jour]]="Vendredi",$C$1+5, IF(Horo82109[[#This Row],[Jour]]="Samedi",$C$1+6, IF(Horo82109[[#This Row],[Jour]]="Dimanche",$C$1, ))))))) -> 44447 | C18: Mardi | D18: 0.5625 | E18: 0.64583333 | F18: SUPREME ŒUF | G18: RD | H18: Billet | I18: Préparation Billet Boyum pour les articles consignable | J18: =IF(Horo82109[[#This Row],[Début]]=0,"",(Horo82109[[#This Row],[Durée (60)2]]-INT(Horo82109[[#This Row],[Durée (60)2]]))*24) -> 2 | K18: =SUMIF(Horo82109[Jour],C18,Horo82109[Durée]) -> 8 | L18: =IFERROR(SUMIF(Horo82109[[#This Row],[Jour]],Horo82109[[#This Row],[Jour]],Horo82109[[#This Row],[GPF]]) / Horo82109[[#This Row],[hrs]],"") -> 0 | M18: =IF("GPF"=Horo82109[[#This Row],[Tâche]],Horo82109[[#This Row],[Durée]],"") | N18: =IF("RI"=Horo82109[[#This Row],[Tâche]],Horo82109[[#This Row],[Durée]],"") | O18: =IF("GB"=Horo82109[[#This Row],[Tâche]],Horo82109[[#This Row],[Durée]],"") | P18: =IF("RD"=Horo82109[[#This Row],[Tâche]],Horo82109[[#This Row],[Durée]],"") -> 2 | Q18: =IF("FG"=Horo82109[[#This Row],[Tâche]],Horo82109[[#This Row],[Durée]],"") | R18: =IF("CONGÉ"=Horo82109[[#This Row],[Tâche]],Horo82109[[#This Row],[Durée]],"") | S18: =IF("PS"=Horo82109[[#This Row],[Tâche]],Horo82109[[#This Row],[Durée]],"") | T18: =IF("TD"=Horo82109[[#This Row],[Tâche]],Horo82109[[#This Row],[Durée]],"") | U18: =IF("N/C"=Horo82109[[#This Row],[Tâche]],Horo82109[[#This Row],[Durée]],"") | W18: =IF(Horo82109[[#This Row],[O]]="o",Horo82109[[#This Row],[Durée]],".") -> 2 | X18: =IF(Horo82109[[#This Row],[Début]]=0,"",Horo82109[[#This Row],[Fin]]-Horo82109[[#This Row],[Début]]) -> 0.083333333
A19: o | B19: =IF(Horo82109[[#This Row],[Jour]]="Lundi",$C$1+1, IF(Horo82109[[#This Row],[Jour]]="Mardi",$C$1+2, IF(Horo82109[[#This Row],[Jour]]="Mercredi",$C$1+3, IF(Horo82109[[#This Row],[Jour]]="Jeudi",$C$1+4, IF(Horo82109[[#This Row],[Jour]]="Vendredi",$C$1+5, IF(Horo82109[[#This Row],[Jour]]="Samedi",$C$1+6, IF(Horo82109[[#This Row],[Jour]]="Dimanche",$C$1, ))))))) -> 44447 | C19: Mardi | D19: 0.64583333 | E19: 0.72916667 | F19: HYPERTEC | G19: GPF | H19: Étiquette | I19: item Label | J19: =IF(Horo82109[[#This Row],[Début]]=0,"",(Horo82109[[#This Row],[Durée (60)2]]-INT(Horo82109[[#This Row],[Durée (60)2]]))*24) -> 2 | K19: =SUMIF(Horo82109[Jour],C19,Horo82109[Durée]) -> 8 | L19: =IFERROR(SUMIF(Horo82109[[#This Row],[Jour]],Horo82109[[#This Row],[Jour]],Horo82109[[#This Row],[GPF]]) / Horo82109[[#This Row],[hrs]],"") -> 0.25 | M19: =IF("GPF"=Horo82109[[#This Row],[Tâche]],Horo82109[[#This Row],[Durée]],"") -> 2 | N19: =IF("RI"=Horo82109[[#This Row],[Tâche]],Horo82109[[#This Row],[Durée]],"") | O19: =IF("GB"=Horo82109[[#This Row],[Tâche]],Horo82109[[#This Row],[Durée]],"") | P19: =IF("RD"=Horo82109[[#This Row],[Tâche]],Horo82109[[#This Row],[Durée]],"") | Q19: =IF("FG"=Horo82109[[#This Row],[Tâche]],Horo82109[[#This Row],[Durée]],"") | R19: =IF("CONGÉ"=Horo82109[[#This Row],[Tâche]],Horo82109[[#This Row],[Durée]],"") | S19: =IF("PS"=Horo82109[[#This Row],[Tâche]],Horo82109[[#This Row],[Durée]],"") | T19: =IF("TD"=Horo82109[[#This Row],[Tâche]],Horo82109[[#This Row],[Durée]],"") | U19: =IF("N/C"=Horo82109[[#This Row],[Tâche]],Horo82109[[#This Row],[Durée]],"") | W19: =IF(Horo82109[[#This Row],[O]]="o",Horo82109[[#This Row],[Durée]],".") -> 2 | X19: =IF(Horo82109[[#This Row],[Début]]=0,"",Horo82109[[#This Row],[Fin]]-Horo82109[[#This Row],[Début]]) -> 0.083333333
A20: o | B20: =IF(Horo82109[[#This Row],[Jour]]="Lundi",$C$1+1, IF(Horo82109[[#This Row],[Jour]]="Mardi",$C$1+2, IF(Horo82109[[#This Row],[Jour]]="Mercredi",$C$1+3, IF(Horo82109[[#This Row],[Jour]]="Jeudi",$C$1+4, IF(Horo82109[[#This Row],[Jour]]="Vendredi",$C$1+5, IF(Horo82109[[#This Row],[Jour]]="Samedi",$C$1+6, IF(Horo82109[[#This Row],[Jour]]="Dimanche",$C$1, ))))))) -> 44447 | C20: Mardi | D20: 0.72916667 | E20: 0.75 | F20: FORGESTIK | G20: FG | H20: Formation C# | J20: =IF(Horo82109[[#This Row],[Début]]=0,"",(Horo82109[[#This Row],[Durée (60)2]]-INT(Horo82109[[#This Row],[Durée (60)2]]))*24) -> 0.5 | K20: =SUMIF(Horo82109[Jour],C20,Horo82109[Durée]) -> 8 | L20: =IFERROR(SUMIF(Horo82109[[#This Row],[Jour]],Horo82109[[#This Row],[Jour]],Horo82109[[#This Row],[GPF]]) / Horo82109[[#This Row],[hrs]],"") -> 0 | M20: =IF("GPF"=Horo82109[[#This Row],[Tâche]],Horo82109[[#This Row],[Durée]],"") | N20: =IF("RI"=Horo82109[[#This Row],[Tâche]],Horo82109[[#This Row],[Durée]],"") | O20: =IF("GB"=Horo82109[[#This Row],[Tâche]],Horo82109[[#This Row],[Durée]],"") | P20: =IF("RD"=Horo82109[[#This Row],[Tâche]],Horo82109[[#This Row],[Durée]],"") | Q20: =IF("FG"=Horo82109[[#This Row],[Tâche]],Horo82109[[#This Row],[Durée]],"") -> 0.5 | R20: =IF("CONGÉ"=Horo82109[[#This Row],[Tâche]],Horo82109[[#This Row],[Durée]],"") | S20: =IF("PS"=Horo82109[[#This Row],[Tâche]],Horo82109[[#This Row],[Durée]],"") | T20: =IF("TD"=Horo82109[[#This Row],[Tâche]],Horo82109[[#This Row],[Durée]],"") | U20: =IF("N/C"=Horo82109[[#This Row],[Tâche]],Horo82109[[#This Row],[Durée]],"") | W20: =IF(Horo82109[[#This Row],[O]]="o",Horo82109[[#This Row],[Durée]],".") -> 0.5 | X20: =IF(Horo82109[[#This Row],[Début]]=0,"",Horo82109[[#This Row],[Fin]]-Horo82109[[#This Row],[Début]]) -> 0.020833333
A21: o | B21: =IF(Horo82109[[#This Row],[Jour]]="Lundi",$C$1+1, IF(Horo82109[[#This Row],[Jour]]="Mardi",$C$1+2, IF(Horo82109[[#This Row],[Jour]]="Mercredi",$C$1+3, IF(Horo82109[[#This Row],[Jour]]="Jeudi",$C$1+4, IF(Horo82109[[#This Row],[Jour]]="Vendredi",$C$1+5, IF(Horo82109[[#This Row],[Jour]]="Samedi",$C$1+6, IF(Horo82109[[#This Row],[Jour]]="Dimanche",$C$1, ))))))) -> 44448 | C21: Mercredi | D21: 0.33333333 | E21: 0.35416667 | F21: FORGESTIK | G21: GB | H21: . | J21: =IF(Horo82109[[#This Row],[Début]]=0,"",(Horo82109[[#This Row],[Durée (60)2]]-INT(Horo82109[[#This Row],[Durée (60)2]]))*24) -> 0.5 | K21: =SUMIF(Horo82109[Jour],C21,Horo82109[Durée]) -> 8 | L21: =IFERROR(SUMIF(Horo82109[[#This Row],[Jour]],Horo82109[[#This Row],[Jour]],Horo82109[[#This Row],[GPF]]) / Horo82109[[#This Row],[hrs]],"") -> 0 | M21: =IF("GPF"=Horo82109[[#This Row],[Tâche]],Horo82109[[#This Row],[Durée]],"") | N21: =IF("RI"=Horo82109[[#This Row],[Tâche]],Horo82109[[#This Row],[Durée]],"") | O21: =IF("GB"=Horo82109[[#This Row],[Tâche]],Horo82109[[#This Row],[Durée]],"") -> 0.5 | P21: =IF("RD"=Horo82109[[#This Row],[Tâche]],Horo82109[[#This Row],[Durée]],"") | Q21: =IF("FG"=Horo82109[[#This Row],[Tâche]],Horo82109[[#This Row],[Durée]],"") | R21: =IF("CONGÉ"=Horo82109[[#This Row],[Tâche]],Horo82109[[#This Row],[Durée]],"") | S21: =IF("PS"=Horo82109[[#This Row],[Tâche]],Horo82109[[#This Row],[Durée]],"") | T21: =IF("TD"=Horo82109[[#This Row],[Tâche]],Horo82109[[#This Row],[Durée]],"") | U21: =IF("N/C"=Horo82109[[#This Row],[Tâche]],Horo82109[[#This Row],[Durée]],"") | W21: =IF(Horo82109[[#This Row],[O]]="o",Horo82109[[#This Row],[Durée]],".") -> 0.5 | X21: =IF(Horo82109[[#This Row],[Début]]=0,"",Horo82109[[#This Row],[Fin]]-Horo82109[[#This Row],[Début]]) -> 0.020833333
A22: o | B22: =IF(Horo82109[[#This Row],[Jour]]="Lundi",$C$1+1, IF(Horo82109[[#This Row],[Jour]]="Mardi",$C$1+2, IF(Horo82109[[#This Row],[Jour]]="Mercredi",$C$1+3, IF(Horo82109[[#This Row],[Jour]]="Jeudi",$C$1+4, IF(Horo82109[[#This Row],[Jour]]="Vendredi",$C$1+5, IF(Horo82109[[#This Row],[Jour]]="Samedi",$C$1+6, IF(Horo82109[[#This Row],[Jour]]="Dimanche",$C$1, ))))))) -> 44448 | C22: Mercredi | D22: 0.375 | E22: 0.5 | F22: HYPERTEC | G22: GPF | H22: Étiquette | J22: =IF(Horo82109[[#This Row],[Début]]=0,"",(Horo82109[[#This Row],[Durée (60)2]]-INT(Horo82109[[#This Row],[Durée (60)2]]))*24) -> 3 | K22: =SUMIF(Horo82109[Jour],C22,Horo82109[Durée]) -> 8 | L22: =IFERROR(SUMIF(Horo82109[[#This Row],[Jour]],Horo82109[[#This Row],[Jour]],Horo82109[[#This Row],[GPF]]) / Horo82109[[#This Row],[hrs]],"") -> 0.375 | M22: =IF("GPF"=Horo82109[[#This Row],[Tâche]],Horo82109[[#This Row],[Durée]],"") -> 3 | N22: =IF("RI"=Horo82109[[#This Row],[Tâche]],Horo82109[[#This Row],[Durée]],"") | O22: =IF("GB"=Horo82109[[#This Row],[Tâche]],Horo82109[[#This Row],[Durée]],"") | P22: =IF("RD"=Horo82109[[#This Row],[Tâche]],Horo82109[[#This Row],[Durée]],"") | Q22: =IF("FG"=Horo82109[[#This Row],[Tâche]],Horo82109[[#This Row],[Durée]],"") | R22: =IF("CONGÉ"=Horo82109[[#This Row],[Tâche]],Horo82109[[#This Row],[Durée]],"") | S22: =IF("PS"=Horo82109[[#This Row],[Tâche]],Horo82109[[#This Row],[Durée]],"") | T22: =IF("TD"=Horo82109[[#This Row],[Tâche]],Horo82109[[#This Row],[Durée]],"") | U22: =IF("N/C"=Horo82109[[#This Row],[Tâche]],Horo82109[[#This Row],[Durée]],"") | W22: =IF(Horo82109[[#This Row],[O]]="o",Horo82109[[#This Row],[Durée]],".") -> 3 | X22: =IF(Horo82109[[#This Row],[Début]]=0,"",Horo82109[[#This Row],[Fin]]-Horo82109[[#This Row],[Début]]) -> 0.125
A23: o | B23: =IF(Horo82109[[#This Row],[Jour]]="Lundi",$C$1+1, IF(Horo82109[[#This Row],[Jour]]="Mardi",$C$1+2, IF(Horo82109[[#This Row],[Jour]]="Mercredi",$C$1+3, IF(Horo82109[[#This Row],[Jour]]="Jeudi",$C$1+4, IF(Horo82109[[#This Row],[Jour]]="Vendredi",$C$1+5, IF(Horo82109[[#This Row],[Jour]]="Samedi",$C$1+6, IF(Horo82109[[#This Row],[Jour]]="Dimanche",$C$1, ))))))) -> 44448 | C23: Mercredi | D23: 0.54166667 | E23: 0.58333333 | F23: AGENCE GRAVEL | G23: FG | H23: Suivi de projet | J23: =IF(Horo82109[[#This Row],[Début]]=0,"",(Horo82109[[#This Row],[Durée (60)2]]-INT(Horo82109[[#This Row],[Durée (60)2]]))*24) -> 1 | K23: =SUMIF(Horo82109[Jour],C23,Horo82109[Durée]) -> 8 | L23: =IFERROR(SUMIF(Horo82109[[#This Row],[Jour]],Horo82109[[#This Row],[Jour]],Horo82109[[#This Row],[GPF]]) / Horo82109[[#This Row],[hrs]],"") -> 0 | M23: =IF("GPF"=Horo82109[[#This Row],[Tâche]],Horo82109[[#This Row],[Durée]],"") | N23: =IF("RI"=Horo82109[[#This Row],[Tâche]],Horo82109[[#This Row],[Durée]],"") | O23: =IF("GB"=Horo82109[[#This Row],[Tâche]],Horo82109[[#This Row],[Durée]],"") | P23: =IF("RD"=Horo82109[[#This Row],[Tâche]],Horo82109[[#This Row],[Durée]],"") | Q23: =IF("FG"=Horo82109[[#This Row],[Tâche]],Horo82109[[#This Row],[Durée]],"") -> 1 | R23: =IF("CONGÉ"=Horo82109[[#This Row],[Tâche]],Horo82109[[#This Row],[Durée]],"") | S23: =IF("PS"=Horo82109[[#This Row],[Tâche]],Horo82109[[#This Row],[Durée]],"") | T23: =IF("TD"=Horo82109[[#This Row],[Tâche]],Horo82109[[#This Row],[Durée]],"") | U23: =IF("N/C"=Horo82109[[#This Row],[Tâche]],Horo82109[[#This Row],[Durée]],"") | W23: =IF(Horo82109[[#This Row],[O]]="o",Horo82109[[#This Row],[Durée]],".") -> 1 | X23: =IF(Horo82109[[#This Row],[Début]]=0,"",Horo82109[[#This Row],[Fin]]-Horo82109[[#This Row],[Début]]) -> 0.041666667
A24: o | B24: =IF(Horo82109[[#This Row],[Jour]]="Lundi",$C$1+1, IF(Horo82109[[#This Row],[Jour]]="Mardi",$C$1+2, IF(Horo82109[[#This Row],[Jour]]="Mercredi",$C$1+3, IF(Horo82109[[#This Row],[Jour]]="Jeudi",$C$1+4, IF(Horo82109[[#This Row],[Jour]]="Vendredi",$C$1+5, IF(Horo82109[[#This Row],[Jour]]="Samedi",$C$1+6, IF(Horo82109[[#This Row],[Jour]]="Dimanche",$C$1, ))))))) -> 44448 | C24: Mercredi | D24: 0.58333333 | E24: 0.72916667 | F24: HYPERTEC | G24: GPF | H24: Étiquette | J24: =IF(Horo82109[[#This Row],[Début]]=0,"",(Horo82109[[#This Row],[Durée (60)2]]-INT(Horo82109[[#This Row],[Durée (60)2]]))*24) -> 3.5 | K24: =SUMIF(Horo82109[Jour],C24,Horo82109[Durée]) -> 8 | L24: =IFERROR(SUMIF(Horo82109[[#This Row],[Jour]],Horo82109[[#This Row],[Jour]],Horo82109[[#This Row],[GPF]]) / Horo82109[[#This Row],[hrs]],"") -> 0.4375 | M24: =IF("GPF"=Horo82109[[#This Row],[Tâche]],Horo82109[[#This Row],[Durée]],"") -> 3.5 | N24: =IF("RI"=Horo82109[[#This Row],[Tâche]],Horo82109[[#This Row],[Durée]],"") | O24: =IF("GB"=Horo82109[[#This Row],[Tâche]],Horo82109[[#This Row],[Durée]],"") | P24: =IF("RD"=Horo82109[[#This Row],[Tâche]],Horo82109[[#This Row],[Durée]],"") | Q24: =IF("FG"=Horo82109[[#This Row],[Tâche]],Horo82109[[#This Row],[Durée]],"") | R24: =IF("CONGÉ"=Horo82109[[#This Row],[Tâche]],Horo82109[[#This Row],[Durée]],"") | S24: =IF("PS"=Horo82109[[#This Row],[Tâche]],Horo82109[[#This Row],[Durée]],"") | T24: =IF("TD"=Horo82109[[#This Row],[Tâche]],Horo82109[[#This Row],[Durée]],"") | U24: =IF("N/C"=Horo82109[[#This Row],[Tâche]],Horo82109[[#This Row],[Durée]],"") | W24: =IF(Horo82109[[#This Row],[O]]="o",Horo82109[[#This Row],[Durée]],".") -> 3.5 | X24: =IF(Horo82109[[#This Row],[Début]]=0,"",Horo82109[[#This Row],[Fin]]-Horo82109[[#This Row],[Début]]) -> 0.14583333
A25: o | B25: =IF(Horo82109[[#This Row],[Jour]]="Lundi",$C$1+1, IF(Horo82109[[#This Row],[Jour]]="Mardi",$C$1+2, IF(Horo82109[[#This Row],[Jour]]="Mercredi",$C$1+3, IF(Horo82109[[#This Row],[Jour]]="Jeudi",$C$1+4, IF(Horo82109[[#This Row],[Jour]]="Vendredi",$C$1+5, IF(Horo82109[[#This Row],[Jour]]="Samedi",$C$1+6, IF(Horo82109[[#This Row],[Jour]]="Dimanche",$C$1, ))))))) -> 44449 | C25: Jeudi | D25: 0.32291667 | E25: 0.33333333 | F25: FORGESTIK | G25: GB | H25: . | J25: =IF(Horo82109[[#This Row],[Début]]=0,"",(Horo82109[[#This Row],[Durée (60)2]]-INT(Horo82109[[#This Row],[Durée (60)2]]))*24) -> 0.25 | K25: =SUMIF(Horo82109[Jour],C25,Horo82109[Durée]) -> 8.75 | L25: =IFERROR(SUMIF(Horo82109[[#This Row],[Jour]],Horo82109[[#This Row],[Jour]],Horo82109[[#This Row],[GPF]]) / Horo82109[[#This Row],[hrs]],"") -> 0 | M25: =IF("GPF"=Horo82109[[#This Row],[Tâche]],Horo82109[[#This Row],[Durée]],"") | N25: =IF("RI"=Horo82109[[#This Row],[Tâche]],Horo82109[[#This Row],[Durée]],"") | O25: =IF("GB"=Horo82109[[#This Row],[Tâche]],Horo82109[[#This Row],[Durée]],"") -> 0.25 | P25: =IF("RD"=Horo82109[[#This Row],[Tâche]],Horo82109[[#This Row],[Durée]],"") | Q25: =IF("FG"=Horo82109[[#This Row],[Tâche]],Horo82109[[#This Row],[Durée]],"") | R25: =IF("CONGÉ"=Horo82109[[#This Row],[Tâche]],Horo82109[[#This Row],[Durée]],"") | S25: =IF("PS"=Horo82109[[#This Row],[Tâche]],Horo82109[[#This Row],[Durée]],"") | T25: =IF("TD"=Horo82109[[#This Row],[Tâche]],Horo82109[[#This Row],[Durée]],"") | U25: =IF("N/C"=Horo82109[[#This Row],[Tâche]],Horo82109[[#This Row],[Durée]],"") | W25: =IF(Horo82109[[#This Row],[O]]="o",Horo82109[[#This Row],[Durée]],".") -> 0.25 | X25: =IF(Horo82109[[#This Row],[Début]]=0,"",Horo82109[[#This Row],[Fin]]-Horo82109[[#This Row],[Début]]) -> 0.010416667
A26: o | B26: =IF(Horo82109[[#This Row],[Jour]]="Lundi",$C$1+1, IF(Horo82109[[#This Row],[Jour]]="Mardi",$C$1+2, IF(Horo82109[[#This Row],[Jour]]="Mercredi",$C$1+3, IF(Horo82109[[#This Row],[Jour]]="Jeudi",$C$1+4, IF(Horo82109[[#This Row],[Jour]]="Vendredi",$C$1+5, IF(Horo82109[[#This Row],[Jour]]="Samedi",$C$1+6, IF(Horo82109[[#This Row],[Jour]]="Dimanche",$C$1, ))))))) -> 44449 | C26: Jeudi | D26: 0.35416667 | E26: 0.41666667 | F26: HYPERTEC | G26: GPF | H26: Étiquette | J26: =IF(Horo82109[[#This Row],[Début]]=0,"",(Horo82109[[#This Row],[Durée (60)2]]-INT(Horo82109[[#This Row],[Durée (60)2]]))*24) -> 1.5 | K26: =SUMIF(Horo82109[Jour],C26,Horo82109[Durée]) -> 8.75 | L26: =IFERROR(SUMIF(Horo82109[[#This Row],[Jour]],Horo82109[[#This Row],[Jour]],Horo82109[[#This Row],[GPF]]) / Horo82109[[#This Row],[hrs]],"") -> 0.17142857 | M26: =IF("GPF"=Horo82109[[#This Row],[Tâche]],Horo82109[[#This Row],[Durée]],"") -> 1.5 | N26: =IF("RI"=Horo82109[[#This Row],[Tâche]],Horo82109[[#This Row],[Durée]],"") | O26: =IF("GB"=Horo82109[[#This Row],[Tâche]],Horo82109[[#This Row],[Durée]],"") | P26: =IF("RD"=Horo82109[[#This Row],[Tâche]],Horo82109[[#This Row],[Durée]],"") | Q26: =IF("FG"=Horo82109[[#This Row],[Tâche]],Horo82109[[#This Row],[Durée]],"") | R26: =IF("CONGÉ"=Horo82109[[#This Row],[Tâche]],Horo82109[[#This Row],[Durée]],"") | S26: =IF("PS"=Horo82109[[#This Row],[Tâche]],Horo82109[[#This Row],[Durée]],"") | T26: =IF("TD"=Horo82109[[#This Row],[Tâche]],Horo82109[[#This Row],[Durée]],"") | U26: =IF("N/C"=Horo82109[[#This Row],[Tâche]],Horo82109[[#This Row],[Durée]],"") | W26: =IF(Horo82109[[#This Row],[O]]="o",Horo82109[[#This Row],[Durée]],".") -> 1.5 | X26: =IF(Horo82109[[#This Row],[Début]]=0,"",Horo82109[[#This Row],[Fin]]-Horo82109[[#This Row],[Début]]) -> 0.0625
A27: o | B27: =IF(Horo82109[[#This Row],[Jour]]="Lundi",$C$1+1, IF(Horo82109[[#This Row],[Jour]]="Mardi",$C$1+2, IF(Horo82109[[#This Row],[Jour]]="Mercredi",$C$1+3, IF(Horo82109[[#This Row],[Jour]]="Jeudi",$C$1+4, IF(Horo82109[[#This Row],[Jour]]="Vendredi",$C$1+5, IF(Horo82109[[#This Row],[Jour]]="Samedi",$C$1+6, IF(Horo82109[[#This Row],[Jour]]="Dimanche",$C$1, ))))))) -> 44449 | C27: Jeudi | D27: 0.41666667 | E27: 0.42708333 | F27: COATICOOK | G27: GPF | H27: Suivi de projet | J27: =IF(Horo82109[[#This Row],[Début]]=0,"",(Horo82109[[#This Row],[Durée (60)2]]-INT(Horo82109[[#This Row],[Durée (60)2]]))*24) -> 0.25 | K27: =SUMIF(Horo82109[Jour],C27,Horo82109[Durée]) -> 8.75 | L27: =IFERROR(SUMIF(Horo82109[[#This Row],[Jour]],Horo82109[[#This Row],[Jour]],Horo82109[[#This Row],[GPF]]) / Horo82109[[#This Row],[hrs]],"") -> 0.028571429 | M27: =IF("GPF"=Horo82109[[#This Row],[Tâche]],Horo82109[[#This Row],[Durée]],"") -> 0.25 | N27: =IF("RI"=Horo82109[[#This Row],[Tâche]],Horo82109[[#This Row],[Durée]],"") | O27: =IF("GB"=Horo82109[[#This Row],[Tâche]],Horo82109[[#This Row],[Durée]],"") | P27: =IF("RD"=Horo82109[[#This Row],[Tâche]],Horo82109[[#This Row],[Durée]],"") | Q27: =IF("FG"=Horo82109[[#This Row],[Tâche]],Horo82109[[#This Row],[Durée]],"") | R27: =IF("CONGÉ"=Horo82109[[#This Row],[Tâche]],Horo82109[[#This Row],[Durée]],"") | S27: =IF("PS"=Horo82109[[#This Row],[Tâche]],Horo82109[[#This Row],[Durée]],"") | T27: =IF("TD"=Horo82109[[#This Row],[Tâche]],Horo82109[[#This Row],[Durée]],"") | U27: =IF("N/C"=Horo82109[[#This Row],[Tâche]],Horo82109[[#This Row],[Durée]],"") | W27: =IF(Horo82109[[#This Row],[O]]="o",Horo82109[[#This Row],[Durée]],".") -> 0.25 | X27: =IF(Horo82109[[#This Row],[Début]]=0,"",Horo82109[[#This Row],[Fin]]-Horo82109[[#This Row],[Début]]) -> 0.010416667
A28: o | B28: =IF(Horo82109[[#This Row],[Jour]]="Lundi",$C$1+1, IF(Horo82109[[#This Row],[Jour]]="Mardi",$C$1+2, IF(Horo82109[[#This Row],[Jour]]="Mercredi",$C$1+3, IF(Horo82109[[#This Row],[Jour]]="Jeudi",$C$1+4, IF(Horo82109[[#This Row],[Jour]]="Vendredi",$C$1+5, IF(Horo82109[[#This Row],[Jour]]="Samedi",$C$1+6, IF(Horo82109[[#This Row],[Jour]]="Dimanche",$C$1, ))))))) -> 44449 | C28: Jeudi | D28: 0.42708333 | E28: 0.5 | F28: HYPERTEC | G28: GPF | H28: Étiquette | J28: =IF(Horo82109[[#This Row],[Début]]=0,"",(Horo82109[[#This Row],[Durée (60)2]]-INT(Horo82109[[#This Row],[Durée (60)2]]))*24) -> 1.75 | K28: =SUMIF(Horo82109[Jour],C28,Horo82109[Durée]) -> 8.75 | L28: =IFERROR(SUMIF(Horo82109[[#This Row],[Jour]],Horo82109[[#This Row],[Jour]],Horo82109[[#This Row],[GPF]]) / Horo82109[[#This Row],[hrs]],"") -> 0.2 | M28: =IF("GPF"=Horo82109[[#This Row],[Tâche]],Horo82109[[#This Row],[Durée]],"") -> 1.75 | N28: =IF("RI"=Horo82109[[#This Row],[Tâche]],Horo82109[[#This Row],[Durée]],"") | O28: =IF("GB"=Horo82109[[#This Row],[Tâche]],Horo82109[[#This Row],[Durée]],"") | P28: =IF("RD"=Horo82109[[#This Row],[Tâche]],Horo82109[[#This Row],[Durée]],"") | Q28: =IF("FG"=Horo82109[[#This Row],[Tâche]],Horo82109[[#This Row],[Durée]],"") | R28: =IF("CONGÉ"=Horo82109[[#This Row],[Tâche]],Horo82109[[#This Row],[Durée]],"") | S28: =IF("PS"=Horo82109[[#This Row],[Tâche]],Horo82109[[#This Row],[Durée]],"") | T28: =IF("TD"=Horo82109[[#This Row],[Tâche]],Horo82109[[#This Row],[Durée]],"") | U28: =IF("N/C"=Horo82109[[#This Row],[Tâche]],Horo82109[[#This Row],[Durée]],"") | W28: =IF(Horo82109[[#This Row],[O]]="o",Horo82109[[#This Row],[Durée]],".") -> 1.75 | X28: =IF(Horo82109[[#This Row],[Début]]=0,"",Horo82109[[#This Row],[Fin]]-Horo82109[[#This Row],[Début]]) -> 0.072916667
A29: o | B29: =IF(Horo82109[[#This Row],[Jour]]="Lundi",$C$1+1, IF(Horo82109[[#This Row],[Jour]]="Mardi",$C$1+2, IF(Horo82109[[#This Row],[Jour]]="Mercredi",$C$1+3, IF(Horo82109[[#This Row],[Jour]]="Jeudi",$C$1+4, IF(Horo82109[[#This Row],[Jour]]="Vendredi",$C$1+5, IF(Horo82109[[#This Row],[Jour]]="Samedi",$C$1+6, IF(Horo82109[[#This Row],[Jour]]="Dimanche",$C$1, ))))))) -> 44449 | C29: Jeudi | D29: 0.5625 | E29: 0.77083333 | F29: HYPERTEC | G29: RD | H29: Preuve de concept | I29: Étiquette | J29: =IF(Horo82109[[#This Row],[Début]]=0,"",(Horo82109[[#This Row],[Durée (60)2]]-INT(Horo82109[[#This Row],[Durée (60)2]]))*24) -> 5 | K29: =SUMIF(Horo82109[Jour],C29,Horo82109[Durée]) -> 8.75 | L29: =IFERROR(SUMIF(Horo82109[[#This Row],[Jour]],Horo82109[[#This Row],[Jour]],Horo82109[[#This Row],[GPF]]) / Horo82109[[#This Row],[hrs]],"") -> 0 | M29: =IF("GPF"=Horo82109[[#This Row],[Tâche]],Horo82109[[#This Row],[Durée]],"") | N29: =IF("RI"=Horo82109[[#This Row],[Tâche]],Horo82109[[#This Row],[Durée]],"") | O29: =IF("GB"=Horo82109[[#This Row],[Tâche]],Horo82109[[#This Row],[Durée]],"") | P29: =IF("RD"=Horo82109[[#This Row],[Tâche]],Horo82109[[#This Row],[Durée]],"") -> 5 | Q29: =IF("FG"=Horo82109[[#This Row],[Tâche]],Horo82109[[#This Row],[Durée]],"") | R29: =IF("CONGÉ"=Horo82109[[#This Row],[Tâche]],Horo82109[[#This Row],[Durée]],"") | S29: =IF("PS"=Horo82109[[#This Row],[Tâche]],Horo82109[[#This Row],[Durée]],"") | T29: =IF("TD"=Horo82109[[#This Row],[Tâche]],Horo82109[[#This Row],[Durée]],"") | U29: =IF("N/C"=Horo82109[[#This Row],[Tâche]],Horo82109[[#This Row],[Durée]],"") | W29: =IF(Horo82109[[#This Row],[O]]="o",Horo82109[[#This Row],[Durée]],".") -> 5 | X29: =IF(Horo82109[[#This Row],[Début]]=0,"",Horo82109[[#This Row],[Fin]]-Horo82109[[#This Row],[Début]]) -> 0.20833333
A30: o | B30: =IF(Horo82109[[#This Row],[Jour]]="Lundi",$C$1+1, IF(Horo82109[[#This Row],[Jour]]="Mardi",$C$1+2, IF(Horo82109[[#This Row],[Jour]]="Mercredi",$C$1+3, IF(Horo82109[[#This Row],[Jour]]="Jeudi",$C$1+4, IF(Horo82109[[#This Row],[Jour]]="Vendredi",$C$1+5, IF(Horo82109[[#This Row],[Jour]]="Samedi",$C$1+6, IF(Horo82109[[#This Row],[Jour]]="Dimanche",$C$1, ))))))) -> 44450 | C30: Vendredi | D30: 0.33333333 | E30: 0.35416667 | F30: FORGESTIK | G30: GB | H30: . | J30: =IF(Horo82109[[#This Row],[Début]]=0,"",(Horo82109[[#This Row],[Durée (60)2]]-INT(Horo82109[[#This Row],[Durée (60)2]]))*24) -> 0.5 | K30: =SUMIF(Horo82109[Jour],C30,Horo82109[Durée]) -> 7.5 | L30: =IFERROR(SUMIF(Horo82109[[#This Row],[Jour]],Horo82109[[#This Row],[Jour]],Horo82109[[#This Row],[GPF]]) / Horo82109[[#This Row],[hrs]],"") -> 0 | M30: =IF("GPF"=Horo82109[[#This Row],[Tâche]],Horo82109[[#This Row],[Durée]],"") | N30: =IF("RI"=Horo82109[[#This Row],[Tâche]],Horo82109[[#This Row],[Durée]],"") | O30: =IF("GB"=Horo82109[[#This Row],[Tâche]],Horo82109[[#This Row],[Durée]],"") -> 0.5 | P30: =IF("RD"=Horo82109[[#This Row],[Tâche]],Horo82109[[#This Row],[Durée]],"") | Q30: =IF("FG"=Horo82109[[#This Row],[Tâche]],Horo82109[[#This Row],[Durée]],"") | R30: =IF("CONGÉ"=Horo82109[[#This Row],[Tâche]],Horo82109[[#This Row],[Durée]],"") | S30: =IF("PS"=Horo82109[[#This Row],[Tâche]],Horo82109[[#This Row],[Durée]],"") | T30: =IF("TD"=Horo82109[[#This Row],[Tâche]],Horo82109[[#This Row],[Durée]],"") | U30: =IF("N/C"=Horo82109[[#This Row],[Tâche]],Horo82109[[#This Row],[Durée]],"") | W30: =IF(Horo82109[[#This Row],[O]]="o",Horo82109[[#This Row],[Durée]],".") -> 0.5 | X30: =IF(Horo82109[[#This Row],[Début]]=0,"",Horo82109[[#This Row],[Fin]]-Horo82109[[#This Row],[Début]]) -> 0.020833333
A31: o | B31: =IF(Horo82109[[#This Row],[Jour]]="Lundi",$C$1+1, IF(Horo82109[[#This Row],[Jour]]="Mardi",$C$1+2, IF(Horo82109[[#This Row],[Jour]]="Mercredi",$C$1+3, IF(Horo82109[[#This Row],[Jour]]="Jeudi",$C$1+4, IF(Horo82109[[#This Row],[Jour]]="Vendredi",$C$1+5, IF(Horo82109[[#This Row],[Jour]]="Samedi",$C$1+6, IF(Horo82109[[#This Row],[Jour]]="Dimanche",$C$1, ))))))) -> 44450 | C31: Vendredi | D31: 0.35416667 | E31: 0.375 | F31: SUPREME ŒUF | G31: GPF | H31: Suivi de projet | J31: =IF(Horo82109[[#This Row],[Début]]=0,"",(Horo82109[[#This Row],[Durée (60)2]]-INT(Horo82109[[#This Row],[Durée (60)2]]))*24) -> 0.5 | K31: =SUMIF(Horo82109[Jour],C31,Horo82109[Durée]) -> 7.5 | L31: =IFERROR(SUMIF(Horo82109[[#This Row],[Jour]],Horo82109[[#This Row],[Jour]],Horo82109[[#This Row],[GPF]]) / Horo82109[[#This Row],[hrs]],"") -> 0.066666667 | M31: =IF("GPF"=Horo82109[[#This Row],[Tâche]],Horo82109[[#This Row],[Durée]],"") -> 0.5 | N31: =IF("RI"=Horo82109[[#This Row],[Tâche]],Horo82109[[#This Row],[Durée]],"") | O31: =IF("GB"=Horo82109[[#This Row],[Tâche]],Horo82109[[#This Row],[Durée]],"") | P31: =IF("RD"=Horo82109[[#This Row],[Tâche]],Horo82109[[#This Row],[Durée]],"") | Q31: =IF("FG"=Horo82109[[#This Row],[Tâche]],Horo82109[[#This Row],[Durée]],"") | R31: =IF("CONGÉ"=Horo82109[[#This Row],[Tâche]],Horo82109[[#This Row],[Durée]],"") | S31: =IF("PS"=Horo82109[[#This Row],[Tâche]],Horo82109[[#This Row],[Durée]],"") | T31: =IF("TD"=Horo82109[[#This Row],[Tâche]],Horo82109[[#This Row],[Durée]],"") | U31: =IF("N/C"=Horo82109[[#This Row],[Tâche]],Horo82109[[#This Row],[Durée]],"") | W31: =IF(Horo82109[[#This Row],[O]]="o",Horo82109[[#This Row],[Durée]],".") -> 0.5 | X31: =IF(Horo82109[[#This Row],[Début]]=0,"",Horo82109[[#This Row],[Fin]]-Horo82109[[#This Row],[Début]]) -> 0.020833333
A32: o | B32: =IF(Horo82109[[#This Row],[Jour]]="Lundi",$C$1+1, IF(Horo82109[[#This Row],[Jour]]="Mardi",$C$1+2, IF(Horo82109[[#This Row],[Jour]]="Mercredi",$C$1+3, IF(Horo82109[[#This Row],[Jour]]="Jeudi",$C$1+4, IF(Horo82109[[#This Row],[Jour]]="Vendredi",$C$1+5, IF(Horo82109[[#This Row],[Jour]]="Samedi",$C$1+6, IF(Horo82109[[#This Row],[Jour]]="Dimanche",$C$1, ))))))) -> 44450 | C32: Vendredi | D32: 0.375 | E32: 0.39583333 | F32: AGENCE GRAVEL | G32: GPF | H32: Suivi de projet | J32: =IF(Horo82109[[#This Row],[Début]]=0,"",(Horo82109[[#This Row],[Durée (60)2]]-INT(Horo82109[[#This Row],[Durée (60)2]]))*24) -> 0.5 | K32: =SUMIF(Horo82109[Jour],C32,Horo82109[Durée]) -> 7.5 | L32: =IFERROR(SUMIF(Horo82109[[#This Row],[Jour]],Horo82109[[#This Row],[Jour]],Horo82109[[#This Row],[GPF]]) / Horo82109[[#This Row],[hrs]],"") -> 0.066666667 | M32: =IF("GPF"=Horo82109[[#This Row],[Tâche]],Horo82109[[#This Row],[Durée]],"") -> 0.5 | N32: =IF("RI"=Horo82109[[#This Row],[Tâche]],Horo82109[[#This Row],[Durée]],"") | O32: =IF("GB"=Horo82109[[#This Row],[Tâche]],Horo82109[[#This Row],[Durée]],"") | P32: =IF("RD"=Horo82109[[#This Row],[Tâche]],Horo82109[[#This Row],[Durée]],"") | Q32: =IF("FG"=Horo82109[[#This Row],[Tâche]],Horo82109[[#This Row],[Durée]],"") | R32: =IF("CONGÉ"=Horo82109[[#This Row],[Tâche]],Horo82109[[#This Row],[Durée]],"") | S32: =IF("PS"=Horo82109[[#This Row],[Tâche]],Horo82109[[#This Row],[Durée]],"") | T32: =IF("TD"=Horo82109[[#This Row],[Tâche]],Horo82109[[#This Row],[Durée]],"") | U32: =IF("N/C"=Horo82109[[#This Row],[Tâche]],Horo82109[[#This Row],[Durée]],"") | W32: =IF(Horo82109[[#This Row],[O]]="o",Horo82109[[#This Row],[Durée]],".") -> 0.5 | X32: =IF(Horo82109[[#This Row],[Début]]=0,"",Horo82109[[#This Row],[Fin]]-Horo82109[[#This Row],[Début]]) -> 0.020833333
A33: o | B33: =IF(Horo82109[[#This Row],[Jour]]="Lundi",$C$1+1, IF(Horo82109[[#This Row],[Jour]]="Mardi",$C$1+2, IF(Horo82109[[#This Row],[Jour]]="Mercredi",$C$1+3, IF(Horo82109[[#This Row],[Jour]]="Jeudi",$C$1+4, IF(Horo82109[[#This Row],[Jour]]="Vendredi",$C$1+5, IF(Horo82109[[#This Row],[Jour]]="Samedi",$C$1+6, IF(Horo82109[[#This Row],[Jour]]="Dimanche",$C$1, ))))))) -> 44450 | C33: Vendredi | D33: 0.39583333 | E33: 0.47916667 | F33: COATICOOK | G33: GPF | H33: Installation de Produmex | I33: PMX version | J33: =IF(Horo82109[[#This Row],[Début]]=0,"",(Horo82109[[#This Row],[Durée (60)2]]-INT(Horo82109[[#This Row],[Durée (60)2]]))*24) -> 2 | K33: =SUMIF(Horo82109[Jour],C33,Horo82109[Durée]) -> 7.5 | L33: =IFERROR(SUMIF(Horo82109[[#This Row],[Jour]],Horo82109[[#This Row],[Jour]],Horo82109[[#This Row],[GPF]]) / Horo82109[[#This Row],[hrs]],"") -> 0.26666667 | M33: =IF("GPF"=Horo82109[[#This Row],[Tâche]],Horo82109[[#This Row],[Durée]],"") -> 2 | N33: =IF("RI"=Horo82109[[#This Row],[Tâche]],Horo82109[[#This Row],[Durée]],"") | O33: =IF("GB"=Horo82109[[#This Row],[Tâche]],Horo82109[[#This Row],[Durée]],"") | P33: =IF("RD"=Horo82109[[#This Row],[Tâche]],Horo82109[[#This Row],[Durée]],"") | Q33: =IF("FG"=Horo82109[[#This Row],[Tâche]],Horo82109[[#This Row],[Durée]],"") | R33: =IF("CONGÉ"=Horo82109[[#This Row],[Tâche]],Horo82109[[#This Row],[Durée]],"") | S33: =IF("PS"=Horo82109[[#This Row],[Tâche]],Horo82109[[#This Row],[Durée]],"") | T33: =IF("TD"=Horo82109[[#This Row],[Tâche]],Horo82109[[#This Row],[Durée]],"") | U33: =IF("N/C"=Horo82109[[#This Row],[Tâche]],Horo82109[[#This Row],[Durée]],"") | W33: =IF(Horo82109[[#This Row],[O]]="o",Horo82109[[#This Row],[Durée]],".") -> 2 | X33: =IF(Horo82109[[#This Row],[Début]]=0,"",Horo82109[[#This Row],[Fin]]-Horo82109[[#This Row],[Début]]) -> 0.083333333
A34: o | B34: =IF(Horo82109[[#This Row],[Jour]]="Lundi",$C$1+1, IF(Horo82109[[#This Row],[Jour]]="Mardi",$C$1+2, IF(Horo82109[[#This Row],[Jour]]="Mercredi",$C$1+3, IF(Horo82109[[#This Row],[Jour]]="Jeudi",$C$1+4, IF(Horo82109[[#This Row],[Jour]]="Vendredi",$C$1+5, IF(Horo82109[[#This Row],[Jour]]="Samedi",$C$1+6, IF(Horo82109[[#This Row],[Jour]]="Dimanche",$C$1, ))))))) -> 44450 | C34: Vendredi | D34: 0.5625 | E34: 0.64583333 | F34: FORGESTIK | G34: RD | H34: Preuve de concept | I34: Étiquette | J34: =IF(Horo82109[[#This Row],[Début]]=0,"",(Horo82109[[#This Row],[Durée (60)2]]-INT(Horo82109[[#This Row],[Durée (60)2]]))*24) -> 2 | K34: =SUMIF(Horo82109[Jour],C34,Horo82109[Durée]) -> 7.5 | L34: =IFERROR(SUMIF(Horo82109[[#This Row],[Jour]],Horo82109[[#This Row],[Jour]],Horo82109[[#This Row],[GPF]]) / Horo82109[[#This Row],[hrs]],"") -> 0 | M34: =IF("GPF"=Horo82109[[#This Row],[Tâche]],Horo82109[[#This Row],[Durée]],"") | N34: =IF("RI"=Horo82109[[#This Row],[Tâche]],Horo82109[[#This Row],[Durée]],"") | O34: =IF("GB"=Horo82109[[#This Row],[Tâche]],Horo82109[[#This Row],[Durée]],"") | P34: =IF("RD"=Horo82109[[#This Row],[Tâche]],Horo82109[[#This Row],[Durée]],"") -> 2 | Q34: =IF("FG"=Horo82109[[#This Row],[Tâche]],Horo82109[[#This Row],[Durée]],"") | R34: =IF("CONGÉ"=Horo82109[[#This Row],[Tâche]],Horo82109[[#This Row],[Durée]],"") | S34: =IF("PS"=Horo82109[[#This Row],[Tâche]],Horo82109[[#This Row],[Durée]],"") | T34: =IF("TD"=Horo82109[[#This Row],[Tâche]],Horo82109[[#This Row],[Durée]],"") | U34: =IF("N/C"=Horo82109[[#This Row],[Tâche]],Horo82109[[#This Row],[Durée]],"") | W34: =IF(Horo82109[[#This Row],[O]]="o",Horo82109[[#This Row],[Durée]],".") -> 2 | X34: =IF(Horo82109[[#This Row],[Début]]=0,"",Horo82109[[#This Row],[Fin]]-Horo82109[[#This Row],[Début]]) -> 0.083333333
A35: o | B35: =IF(Horo82109[[#This Row],[Jour]]="Lundi",$C$1+1, IF(Horo82109[[#This Row],[Jour]]="Mardi",$C$1+2, IF(Horo82109[[#This Row],[Jour]]="Mercredi",$C$1+3, IF(Horo82109[[#This Row],[Jour]]="Jeudi",$C$1+4, IF(Horo82109[[#This Row],[Jour]]="Vendredi",$C$1+5, IF(Horo82109[[#This Row],[Jour]]="Samedi",$C$1+6, IF(Horo82109[[#This Row],[Jour]]="Dimanche",$C$1, ))))))) -> 44450 | C35: Vendredi | D35: 0.64583333 | E35: 0.66666667 | F35: FORGESTIK | G35: GB | J35: =IF(Horo82109[[#This Row],[Début]]=0,"",(Horo82109[[#This Row],[Durée (60)2]]-INT(Horo82109[[#This Row],[Durée (60)2]]))*24) -> 0.5 | K35: =SUMIF(Horo82109[Jour],C35,Horo82109[Durée]) -> 7.5 | L35: =IFERROR(SUMIF(Horo82109[[#This Row],[Jour]],Horo82109[[#This Row],[Jour]],Horo82109[[#This Row],[GPF]]) / Horo82109[[#This Row],[hrs]],"") -> 0 | M35: =IF("GPF"=Horo82109[[#This Row],[Tâche]],Horo82109[[#This Row],[Durée]],"") | N35: =IF("RI"=Horo82109[[#This Row],[Tâche]],Horo82109[[#This Row],[Durée]],"") | O35: =IF("GB"=Horo82109[[#This Row],[Tâche]],Horo82109[[#This Row],[Durée]],"") -> 0.5 | P35: =IF("RD"=Horo82109[[#This Row],[Tâche]],Horo82109[[#This Row],[Durée]],"") | Q35: =IF("FG"=Horo82109[[#This Row],[Tâche]],Horo82109[[#This Row],[Durée]],"") | R35: =IF("CONGÉ"=Horo82109[[#This Row],[Tâche]],Horo82109[[#This Row],[Durée]],"") | S35: =IF("PS"=Horo82109[[#This Row],[Tâche]],Horo82109[[#This Row],[Durée]],"") | T35: =IF("TD"=Horo82109[[#This Row],[Tâche]],Horo82109[[#This Row],[Durée]],"") | U35: =IF("N/C"=Horo82109[[#This Row],[Tâche]],Horo82109[[#This Row],[Durée]],"") | W35: =IF(Horo82109[[#This Row],[O]]="o",Horo82109[[#This Row],[Durée]],".") -> 0.5 | X35: =IF(Horo82109[[#This Row],[Début]]=0,"",Horo82109[[#This Row],[Fin]]-Horo82109[[#This Row],[Début]]) -> 0.020833333
